Workbook
Name _: #REF!
Name _: #REF!
Name _: #REF!
Name _: #REF!
Name _: #REF!
Name _: #REF!
Name _: #REF!
Name ___UFP123: #REF!
Name ___UFP123: #REF!
Name ___UFP123: #REF!
Name ___UFP123: #REF!
Name ___UFP123: #REF!
Name ___UFP123: #REF!
Name __DAT2: #REF!
Name __DAT2: #REF!
Name __DAT2: #REF!
Name __DAT2: #REF!
Name __DAT2: #REF!
Name __DAT3: #REF!
Name __DAT3: #REF!
Name __DAT3: #REF!
Name __DAT3: #REF!
Name __DAT3: #REF!
Name __DAT4: #REF!
Name __DAT4: #REF!
Name __DAT4: #REF!
Name __DAT4: #REF!
Name __DAT4: #REF!
Name __DAT5: #REF!
Name __DAT5: #REF!
Name __DAT5: #REF!
Name __DAT5: #REF!
Name __DAT5: #REF!
Name __DAT6: #REF!
Name __DAT6: #REF!
Name __DAT6: #REF!
Name __DAT6: #REF!
Name __DAT6: #REF!
Name __DAT7: #REF!
Name __DAT7: #REF!
Name __DAT7: #REF!
Name __DAT7: #REF!
Name __DAT7: #REF!
Name __DAT8: #REF!
Name __DAT8: #REF!
Name __DAT8: #REF!
Name __DAT8: #REF!
Name __DAT8: #REF!
Name __DAT9: #REF!
Name __DAT9: #REF!
Name __DAT9: #REF!
Name __DAT9: #REF!
Name __DAT9: #REF!
Name __UFP123: #REF!
Name __UFP123: #REF!
Name __UFP123: #REF!
Name __UFP123: #REF!
Name __UFP123: #REF!
Name _007: #REF!
Name _007: #REF!

Sheet 营销BI分析体系
A2: 管理分析体系 | B2: 一期-★★★ | C2: 一期-★★★ | D2: 二期 | E2: 二期 | F2: 二期 | G2: 一期-★★ | H2: 一期-★★★ | I2: 二期 | J2: 一期-★★ | K2: 一期-★★
A4: 核心价值 | B4: 一保一拓三提升
B5: 营销
B6: 营收保障 | C6: 业务拓展 | D6: 运营效率提升 | H6: 客户提升 | J6: 组织能力提升
B7: 扩大营业收入 | C7: 强化业务拓展跟进 | D7: 扩大品牌认知 | E7: 提升市场运作效率 | F7: 严控费用 | G7: 提升运营效率 | H7: 提升经销商能力及效率 | I7: 优化客户结构？ | J7: 提升营销人效 | K7: 增强团队能力建设
A9: 分析主题域
B10: 收入分析 | C10: 业务拓展分析 | D10: 品牌分析 | E10: 市场分析 | F10: 费用分析 | G10: 运营效率分析 | H10: 经销商分析 | I10: 客户分析？ | J10: 人效分析 | K10: 团队能力分析
A12: 分析主题 | I12: 客户分层（A+ABC)，分行业，分产出
B13: 营业收入分析 | C13: 签约分析 | D13: 品牌指数分析 | E13: 二级覆盖度 | F13: 招待费分析 | G13: 销售预测准确率分析 | H13: 渠道结构分析 | I13: 客户结构分析？ | J13: 人员效率分析 | K13: 职级分析
B14: 销量分析 | C14: 商机分析 | D14: 专项曝光分析 | E14: 活动成效分析 | F14: 差旅费分析 | G14: 物流效率分析 | H14: 二级分析 | I14: 客户复购率分析？
B15: 配比分析 | C15: 样机分析 | D15: 用户案例分析 | F15: 广宣费分析 | G15: 分仓效率分析 | H15: 返利分析 | I15: 客户流失分析？(FML）
B16: 价格分析 | C16: 接单分析 | F16: 运输费分析 | G16: 库存周转分析 | H16: 库存分析 | I16: 定制项目投入产出分析？
B17: 订单分析 | C17: 线索分析 | F17: 服务费分析 | H17: 赋能分析 | I17: 客户成单周期分析？
I18: 订单分析？价格？
A21: 指标体系
A23: 核心指标(高层) | B23: 总裁/副总裁
A24: 每个主题<=3 | B24: 市场份额 | C24: 签约达成率 | D24: 品牌指数排名 | E24: 二级覆盖率 | F24: 费率 | G24: 销售预测准确率 | H24: 渠道结构、分销比 | I24: 客户结构 | J24: 营销人均收入 | K24: BG总人数
B25: 收入达成率、同比增长率 | C25: 商机达成率、转化率 | E25: 市场活动投入产出比 | F25: 费用同比增长率 | G25: 库存周转天数、超期库存占比 | H25: 二级承载率、有效率、单商产能 | J25: 营销人均利润 | K25: 营销人数，占比
B26: 毛利率 | C26: 接单达成 | G26: 交付周期 | H26: 核心库存周转天数
A28: 一级指标(中层) | B28: 部门/BU负责人
B29: 营业收入 | C29: 签约达成率 | D29: 品牌指数排名 | E29: 二级覆盖率 | F29: 费率、达成率、同比 | G29: 销售预测准确率 | H29: 渠道结构、分销比 | I29: 客户结构 | J29: 营销人均收入 | K29: 营销人数
B30: 收入达成率及排名、同比 | C30: 商机达成率、转化率、缺口 | D30: 专项曝光度 | E30: 市场活动投入产出比 | F30: 招待费占比、达成率、同比 | G30: 物流时效 | H30: 二级承载率、有效率、单商产能 | I30: 客户复购率 | J30: 营销人均利润 | K30: 营销人数占比
B31: 整机销量 | C31: 接单达成 | D31: 用户案例证言数量 | E31: 留资成本 | F31: 差旅费占比、达成率、同比 | G31: 分仓出货占比 | H31: 返利余额、可使用月份数 | I31: 客户流失率 | J31: 营销人均人力成本 | K31: 营销人数同比增长率
B32: 整机销量同比 | C32: 线索有效率 | F32: 广宣费占比、达成率、同比 | G32: 库存量 | H32: 核心库存量 | I32: 定制项目投入产出比 | J32: 营销人均招待费 | K32: 职级人数占比
B33: 周边配比 | C33: 线索及时率 | F33: 运输费占比、达成率、同比 | G33: 交付周期 | H33: 核心库存周转天数 | I33: 客户成单周期 | J33: 营销人均差旅费
B34: 低价占比 | C34: 样机申请率 | F34: 服务费占比、达成率、同比 | G34: 库存周转天数 | H34: 赋能覆盖率 | I34: 订单均价
B35: 订单平均金额 | C35: 样机在外量 | F35: 整机平均运输费
C36: 样机转销率 | F36: 整机平均安装费
C37: 样机逾期率
A41: 二级指标(执行层) | B41: 各区域省份负责人等
B42: 营业收入 | C42: 签约达成率、缺口 | D42: 品牌指数排名 | E42: 二级覆盖率 | F42: 费率、达成率、同比 | G42: 销售预测准确率 | H42: 渠道结构、分销比 | I42: 客户结构 | J42: 营销人均收入 | K42: 营销人数
B43: 收入达成率及排名、同比 | C43: 商机达成率、转化率、缺口 | D43: 专项曝光度 | E43: 市场活动数量 | F43: 招待费占比、达成率、同比 | G43: 物流时效 | H43: 二级承载率、有效率、单商产能 | I43: 客户复购率 | J43: 营销人均利润 | K43: 营销人数占比
B44: 整机销量 | C44: 接单达成 | D44: 用户案例证言数量 | E44: 市场活动投入产出比 | F44: 差旅费占比、达成率、同比 | G44: 分仓出货占比 | H44: 返利余额、可使用月份数 | I44: 客户流失率 | J44: 营销人均人力成本 | K44: 营销人数同比增长率
B45: 整机销量同比 | C45: 线索有效率 | E45: 留资成本 | F45: 广宣费占比、达成率、同比 | G45: 库存量 | H45: 核心库存量 | I45: 定制项目投入产出比 | J45: 营销人均招待费 | K45: 职级人数占比
B46: 低价占比 | C46: 样机在外量 | F46: 运输费占比、达成率、同比 | G46: 交付周期 | H46: 核心库存周转天数 | I46: 客户成单周期 | J46: 营销人均差旅费
B47: 订单平均金额 | C47: 样机转销率 | F47: 服务费占比、达成率、同比 | G47: 库存周转天数 | H47: 赋能覆盖率 | I47: 订单均价
C48: 样机逾期率 | F48: 整机平均运输费
F49: 整机平均安装费
A52: 维度
A53: 管理维度 | B53: 高层 | C53: 中层 | D53: 执行层： | E53: 品牌 | F53: 市场 | G53: 渠管 | H53: 商务 | I53: 计划 | J53: 物流 | K53: 客服等
A54: 地域维度 | B54: BU | C54: 区域 | D54: 省份/办事处 | E54: 人员
A55: 产品维度 | B55: 产品线 | C55: 代系 | D55: 系列 | E55: 尺寸
A56: 发货维度 | B56: 营业收入 | C56: IN-销售额 | D56: IN-发货额 | E56: OUT | F56: 营业收入不含税，其他含税
A57: 时间维度 | B57: 同比 | C57: 环比 | D57: 预实比 | E57: 均值 | F57: 趋势： | G57: 年 | H57: 季 | I57: 月 | J57: 周 | K57: 日
A60: 管理驾驶舱
A64: 管理报表
A67: 企服
A68: 一期 | B68: 核心指标 | C68: 一级指标 | D68: 二级指标 | E68: 合计 | F68: 不重复 | G68: ★★★ | H68: ★★ | I68: ★ | J68: 相同 | K68: 不同
A69: 营收保障 | B69: =COUNTIFS('指标体系-企服'!$AI:$AI,$A69,'指标体系-企服'!$F:$F,B$68) -> 3 | C69: =COUNTIFS('指标体系-企服'!$AI:$AI,$A69,'指标体系-企服'!$F:$F,C$68) -> 9 | D69: =COUNTIFS('指标体系-企服'!$AI:$AI,$A69,'指标体系-企服'!$F:$F,D$68) -> 7 | E69: =SUM(B69:D69) -> 19 | F69: =COUNTIFS('指标体系-企服'!$AI:$AI,$A69,'指标体系-企服'!$AH:$AH,"否") -> 10 | G69: =COUNTIFS('指标体系-企服'!$AI:$AI,$A69,'指标体系-企服'!$AA:$AA,G$68,'指标体系-企服'!$AH:$AH,"否") -> 6 | H69: =COUNTIFS('指标体系-企服'!$AI:$AI,$A69,'指标体系-企服'!$AA:$AA,H$68,'指标体系-企服'!$AH:$AH,"否") -> 4 | I69: =COUNTIFS('指标体系-企服'!$AI:$AI,$A69,'指标体系-企服'!$AA:$AA,I$68,'指标体系-企服'!$AH:$AH,"否") -> 0 | J69: =COUNTIFS('指标体系-企服'!$AI:$AI,$A69,'指标体系-企服'!$AG:$AG,"true",'指标体系-企服'!$AH:$AH,"否") -> 10 | K69: =COUNTIFS('指标体系-企服'!$AI:$AI,$A69,'指标体系-企服'!$AG:$AG,"否",'指标体系-企服'!$AH:$AH,"否") -> 0
A70: 业务拓展 | B70: =COUNTIFS('指标体系-企服'!$AI:$AI,$A70,'指标体系-企服'!$F:$F,B$68) -> 4 | C70: =COUNTIFS('指标体系-企服'!$AI:$AI,$A70,'指标体系-企服'!$F:$F,C$68) -> 10 | D70: =COUNTIFS('指标体系-企服'!$AI:$AI,$A70,'指标体系-企服'!$F:$F,D$68) -> 9 | E70: =SUM(B70:D70) -> 23 | F70: =COUNTIFS('指标体系-企服'!$AI:$AI,$A70,'指标体系-企服'!$AH:$AH,"否") -> 10 | G70: =COUNTIFS('指标体系-企服'!$AI:$AI,$A70,'指标体系-企服'!$AA:$AA,G$68,'指标体系-企服'!$AH:$AH,"否") -> 10 | H70: =COUNTIFS('指标体系-企服'!$AI:$AI,$A70,'指标体系-企服'!$AA:$AA,H$68,'指标体系-企服'!$AH:$AH,"否") -> 0 | I70: =COUNTIFS('指标体系-企服'!$AI:$AI,$A70,'指标体系-企服'!$AA:$AA,I$68,'指标体系-企服'!$AH:$AH,"否") -> 0 | J70: =COUNTIFS('指标体系-企服'!$AI:$AI,$A70,'指标体系-企服'!$AG:$AG,"true",'指标体系-企服'!$AH:$AH,"否") -> 7 | K70: =COUNTIFS('指标体系-企服'!$AI:$AI,$A70,'指标体系-企服'!$AG:$AG,"否",'指标体系-企服'!$AH:$AH,"否") -> 3
A71: 运营效率提升 | B71: =COUNTIFS('指标体系-企服'!$AI:$AI,$A71,'指标体系-企服'!$F:$F,B$68) -> 2 | C71: =COUNTIFS('指标体系-企服'!$AI:$AI,$A71,'指标体系-企服'!$F:$F,C$68) -> 3 | D71: =COUNTIFS('指标体系-企服'!$AI:$AI,$A71,'指标体系-企服'!$F:$F,D$68) -> 3 | E71: =SUM(B71:D71) -> 8 | F71: =COUNTIFS('指标体系-企服'!$AI:$AI,$A71,'指标体系-企服'!$AH:$AH,"否") -> 4 | G71: =COUNTIFS('指标体系-企服'!$AI:$AI,$A71,'指标体系-企服'!$AA:$AA,G$68,'指标体系-企服'!$AH:$AH,"否") -> 0 | H71: =COUNTIFS('指标体系-企服'!$AI:$AI,$A71,'指标体系-企服'!$AA:$AA,H$68,'指标体系-企服'!$AH:$AH,"否") -> 4 | I71: =COUNTIFS('指标体系-企服'!$AI:$AI,$A71,'指标体系-企服'!$AA:$AA,I$68,'指标体系-企服'!$AH:$AH,"否") -> 0 | J71: =COUNTIFS('指标体系-企服'!$AI:$AI,$A71,'指标体系-企服'!$AG:$AG,"true",'指标体系-企服'!$AH:$AH,"否") -> 3 | K71: =COUNTIFS('指标体系-企服'!$AI:$AI,$A71,'指标体系-企服'!$AG:$AG,"否",'指标体系-企服'!$AH:$AH,"否") -> 1
A72: 客户提升 | B72: =COUNTIFS('指标体系-企服'!$AI:$AI,$A72,'指标体系-企服'!$F:$F,B$68) -> 6 | C72: =COUNTIFS('指标体系-企服'!$AI:$AI,$A72,'指标体系-企服'!$F:$F,C$68) -> 7 | D72: =COUNTIFS('指标体系-企服'!$AI:$AI,$A72,'指标体系-企服'!$F:$F,D$68) -> 7 | E72: =SUM(B72:D72) -> 20 | F72: =COUNTIFS('指标体系-企服'!$AI:$AI,$A72,'指标体系-企服'!$AH:$AH,"否") -> 7 | G72: =COUNTIFS('指标体系-企服'!$AI:$AI,$A72,'指标体系-企服'!$AA:$AA,G$68,'指标体系-企服'!$AH:$AH,"否") -> 0 | H72: =COUNTIFS('指标体系-企服'!$AI:$AI,$A72,'指标体系-企服'!$AA:$AA,H$68,'指标体系-企服'!$AH:$AH,"否") -> 7 | I72: =COUNTIFS('指标体系-企服'!$AI:$AI,$A72,'指标体系-企服'!$AA:$AA,I$68,'指标体系-企服'!$AH:$AH,"否") -> 0 | J72: =COUNTIFS('指标体系-企服'!$AI:$AI,$A72,'指标体系-企服'!$AG:$AG,"true",'指标体系-企服'!$AH:$AH,"否") -> 4 | K72: =COUNTIFS('指标体系-企服'!$AI:$AI,$A72,'指标体系-企服'!$AG:$AG,"否",'指标体系-企服'!$AH:$AH,"否") -> 3
A73: 组织能力提升 | B73: =COUNTIFS('指标体系-企服'!$AI:$AI,$A73,'指标体系-企服'!$F:$F,B$68) -> 5 | C73: =COUNTIFS('指标体系-企服'!$AI:$AI,$A73,'指标体系-企服'!$F:$F,C$68) -> 9 | D73: =COUNTIFS('指标体系-企服'!$AI:$AI,$A73,'指标体系-企服'!$F:$F,D$68) -> 9 | E73: =SUM(B73:D73) -> 23 | F73: =COUNTIFS('指标体系-企服'!$AI:$AI,$A73,'指标体系-企服'!$AH:$AH,"否") -> 10 | G73: =COUNTIFS('指标体系-企服'!$AI:$AI,$A73,'指标体系-企服'!$AA:$AA,G$68,'指标体系-企服'!$AH:$AH,"否") -> 0 | H73: =COUNTIFS('指标体系-企服'!$AI:$AI,$A73,'指标体系-企服'!$AA:$AA,H$68,'指标体系-企服'!$AH:$AH,"否") -> 0 | I73: =COUNTIFS('指标体系-企服'!$AI:$AI,$A73,'指标体系-企服'!$AA:$AA,I$68,'指标体系-企服'!$AH:$AH,"否") -> 10 | J73: =COUNTIFS('指标体系-企服'!$AI:$AI,$A73,'指标体系-企服'!$AG:$AG,"true",'指标体系-企服'!$AH:$AH,"否") -> 10 | K73: =COUNTIFS('指标体系-企服'!$AI:$AI,$A73,'指标体系-企服'!$AG:$AG,"否",'指标体系-企服'!$AH:$AH,"否") -> 0
A74: 合计 | B74: =SUM(B69:B73) -> 20 | C74: =SUM(C69:C73) -> 38 | D74: =SUM(D69:D73) -> 35 | E74: =SUM(E69:E73) -> 93 | F74: =SUM(F69:F73) -> 41 | G74: =SUM(G69:G73) -> 16 | H74: =SUM(H69:H73) -> 15 | I74: =SUM(I69:I73) -> 10 | ... K74: =SUM(K69:K73) -> 7
A75: 单位：个 | E75: 龚芬芬 | F75: 潘敏君 | G75: 曾丽
E76: =COUNTIF(指标体系!$AJ:$AJ,E$75) -> 24 | F76: =COUNTIF(指标体系!$AJ:$AJ,F$75) -> 25 | G76: =COUNTIF(指标体系!$AJ:$AJ,G$75) -> 14
A77: 教育
A78: 一期 | B78: 核心指标 | C78: 一级指标 | D78: 二级指标 | E78: 合计 | F78: 不重复 | G78: ★★★ | H78: ★★ | I78: ★ | J78: 相同 | K78: 不同
A79: 营收保障 | B79: =COUNTIFS('指标体系-教育'!$AI:$AI,$A79,'指标体系-教育'!$F:$F,B$68) -> 3 | C79: =COUNTIFS('指标体系-教育'!$AI:$AI,$A79,'指标体系-教育'!$F:$F,C$68) -> 11 | D79: =COUNTIFS('指标体系-教育'!$AI:$AI,$A79,'指标体系-教育'!$F:$F,D$68) -> 9 | E79: =SUM(B79:D79) -> 23 | F79: =COUNTIFS('指标体系-教育'!$AI:$AI,$A79,'指标体系-教育'!$AH:$AH,"否") -> 12 | G79: =COUNTIFS('指标体系-教育'!$AI:$AI,$A79,'指标体系-教育'!$AA:$AA,G$68,'指标体系-教育'!$AH:$AH,"否") -> 9 | H79: =COUNTIFS('指标体系-教育'!$AI:$AI,$A79,'指标体系-教育'!$AA:$AA,H$68,'指标体系-教育'!$AH:$AH,"否") -> 3 | I79: =COUNTIFS('指标体系-教育'!$AI:$AI,$A79,'指标体系-教育'!$AA:$AA,I$68,'指标体系-教育'!$AH:$AH,"否") -> 0 | J79: =COUNTIFS('指标体系-教育'!$AI:$AI,$A79,'指标体系-教育'!$AG:$AG,"true",'指标体系-教育'!$AH:$AH,"否") -> 10 | K79: =COUNTIFS('指标体系-教育'!$AI:$AI,$A79,'指标体系-教育'!$AG:$AG,"否",'指标体系-教育'!$AH:$AH,"否") -> 2
A80: 业务拓展 | B80: =COUNTIFS('指标体系-教育'!$AI:$AI,$A80,'指标体系-教育'!$F:$F,B$68) -> 11 | C80: =COUNTIFS('指标体系-教育'!$AI:$AI,$A80,'指标体系-教育'!$F:$F,C$68) -> 8 | D80: =COUNTIFS('指标体系-教育'!$AI:$AI,$A80,'指标体系-教育'!$F:$F,D$68) -> 11 | E80: =SUM(B80:D80) -> 30 | F80: =COUNTIFS('指标体系-教育'!$AI:$AI,$A80,'指标体系-教育'!$AH:$AH,"否") -> 11 | G80: =COUNTIFS('指标体系-教育'!$AI:$AI,$A80,'指标体系-教育'!$AA:$AA,G$68,'指标体系-教育'!$AH:$AH,"否") -> 6 | H80: =COUNTIFS('指标体系-教育'!$AI:$AI,$A80,'指标体系-教育'!$AA:$AA,H$68,'指标体系-教育'!$AH:$AH,"否") -> 5 | I80: =COUNTIFS('指标体系-教育'!$AI:$AI,$A80,'指标体系-教育'!$AA:$AA,I$68,'指标体系-教育'!$AH:$AH,"否") -> 0 | J80: =COUNTIFS('指标体系-教育'!$AI:$AI,$A80,'指标体系-教育'!$AG:$AG,"true",'指标体系-教育'!$AH:$AH,"否") -> 7 | K80: =COUNTIFS('指标体系-教育'!$AI:$AI,$A80,'指标体系-教育'!$AG:$AG,"否",'指标体系-教育'!$AH:$AH,"否") -> 4
A81: 运营效率提升 | B81: =COUNTIFS('指标体系-教育'!$AI:$AI,$A81,'指标体系-教育'!$F:$F,B$68) -> 3 | C81: =COUNTIFS('指标体系-教育'!$AI:$AI,$A81,'指标体系-教育'!$F:$F,C$68) -> 4 | D81: =COUNTIFS('指标体系-教育'!$AI:$AI,$A81,'指标体系-教育'!$F:$F,D$68) -> 1 | E81: =SUM(B81:D81) -> 8 | F81: =COUNTIFS('指标体系-教育'!$AI:$AI,$A81,'指标体系-教育'!$AH:$AH,"否") -> 4 | G81: =COUNTIFS('指标体系-教育'!$AI:$AI,$A81,'指标体系-教育'!$AA:$AA,G$68,'指标体系-教育'!$AH:$AH,"否") -> 3 | H81: =COUNTIFS('指标体系-教育'!$AI:$AI,$A81,'指标体系-教育'!$AA:$AA,H$68,'指标体系-教育'!$AH:$AH,"否") -> 1 | I81: =COUNTIFS('指标体系-教育'!$AI:$AI,$A81,'指标体系-教育'!$AA:$AA,I$68,'指标体系-教育'!$AH:$AH,"否") -> 0 | J81: =COUNTIFS('指标体系-教育'!$AI:$AI,$A81,'指标体系-教育'!$AG:$AG,"true",'指标体系-教育'!$AH:$AH,"否") -> 3 | K81: =COUNTIFS('指标体系-教育'!$AI:$AI,$A81,'指标体系-教育'!$AG:$AG,"否",'指标体系-教育'!$AH:$AH,"否") -> 1
A82: 客户提升 | B82: =COUNTIFS('指标体系-教育'!$AI:$AI,$A82,'指标体系-教育'!$F:$F,B$68) -> 4 | C82: =COUNTIFS('指标体系-教育'!$AI:$AI,$A82,'指标体系-教育'!$F:$F,C$68) -> 4 | D82: =COUNTIFS('指标体系-教育'!$AI:$AI,$A82,'指标体系-教育'!$F:$F,D$68) -> 2 | E82: =SUM(B82:D82) -> 10 | F82: =COUNTIFS('指标体系-教育'!$AI:$AI,$A82,'指标体系-教育'!$AH:$AH,"否") -> 4 | G82: =COUNTIFS('指标体系-教育'!$AI:$AI,$A82,'指标体系-教育'!$AA:$AA,G$68,'指标体系-教育'!$AH:$AH,"否") -> 0 | H82: =COUNTIFS('指标体系-教育'!$AI:$AI,$A82,'指标体系-教育'!$AA:$AA,H$68,'指标体系-教育'!$AH:$AH,"否") -> 4 | I82: =COUNTIFS('指标体系-教育'!$AI:$AI,$A82,'指标体系-教育'!$AA:$AA,I$68,'指标体系-教育'!$AH:$AH,"否") -> 0 | J82: =COUNTIFS('指标体系-教育'!$AI:$AI,$A82,'指标体系-教育'!$AG:$AG,"true",'指标体系-教育'!$AH:$AH,"否") -> 4 | K82: =COUNTIFS('指标体系-教育'!$AI:$AI,$A82,'指标体系-教育'!$AG:$AG,"否",'指标体系-教育'!$AH:$AH,"否") -> 0
A83: 组织能力提升 | B83: =COUNTIFS('指标体系-教育'!$AI:$AI,$A83,'指标体系-教育'!$F:$F,B$68) -> 5 | C83: =COUNTIFS('指标体系-教育'!$AI:$AI,$A83,'指标体系-教育'!$F:$F,C$68) -> 10 | D83: =COUNTIFS('指标体系-教育'!$AI:$AI,$A83,'指标体系-教育'!$F:$F,D$68) -> 11 | E83: =SUM(B83:D83) -> 26 | F83: =COUNTIFS('指标体系-教育'!$AI:$AI,$A83,'指标体系-教育'!$AH:$AH,"否") -> 15 | G83: =COUNTIFS('指标体系-教育'!$AI:$AI,$A83,'指标体系-教育'!$AA:$AA,G$68,'指标体系-教育'!$AH:$AH,"否") -> 3 | H83: =COUNTIFS('指标体系-教育'!$AI:$AI,$A83,'指标体系-教育'!$AA:$AA,H$68,'指标体系-教育'!$AH:$AH,"否") -> 10 | I83: =COUNTIFS('指标体系-教育'!$AI:$AI,$A83,'指标体系-教育'!$AA:$AA,I$68,'指标体系-教育'!$AH:$AH,"否") -> 2 | J83: =COUNTIFS('指标体系-教育'!$AI:$AI,$A83,'指标体系-教育'!$AG:$AG,"true",'指标体系-教育'!$AH:$AH,"否") -> 10 | K83: =COUNTIFS('指标体系-教育'!$AI:$AI,$A83,'指标体系-教育'!$AG:$AG,"否",'指标体系-教育'!$AH:$AH,"否") -> 5
A84: 合计 | B84: =SUM(B79:B83) -> 26 | C84: =SUM(C79:C83) -> 37 | D84: =SUM(D79:D83) -> 34 | E84: =SUM(E79:E83) -> 97 | F84: =SUM(F79:F83) -> 46 | G84: =SUM(G79:G83) -> 21 | H84: =SUM(H79:H83) -> 23 | I84: =SUM(I79:I83) -> 2 | ... K84: =SUM(K79:K83) -> 12
A85: 单位：个 | E85: 陈亚婕 | F85: 郭梓樱
E86: =COUNTIF(指标体系!$AK:$AK,E85) -> 51 | F86: =COUNTIF(指标体系!$AK:$AK,F85) -> 29
A87: 合并
A88: 一期 | B88: 核心指标 | C88: 一级指标 | D88: 二级指标 | E88: 合计 | F88: 不重复 | G88: ★★★ | H88: ★★ | I88: ★ | J88: 对接人 | K88: 数量
A89: 营收保障 | B89: =COUNTIFS('指标体系-企服'!$AI:$AI,$A89,'指标体系-企服'!$F:$F,B$68)+COUNTIFS('指标体系-教育'!$AI:$AI,$A89,'指标体系-教育'!$F:$F,B$68,'指标体系-教育'!$AG:$AG,"否") -> 3 | C89: =COUNTIFS('指标体系-企服'!$AI:$AI,$A89,'指标体系-企服'!$F:$F,C$68)+COUNTIFS('指标体系-教育'!$AI:$AI,$A89,'指标体系-教育'!$F:$F,C$68,'指标体系-教育'!$AG:$AG,"否") -> 11 | D89: =COUNTIFS('指标体系-企服'!$AI:$AI,$A89,'指标体系-企服'!$F:$F,D$68)+COUNTIFS('指标体系-教育'!$AI:$AI,$A89,'指标体系-教育'!$F:$F,D$68,'指标体系-教育'!$AG:$AG,"否") -> 9 | E89: =SUM(B89:D89) -> 23 | F89: =COUNTIFS('指标体系-企服'!$AI:$AI,$A89,'指标体系-企服'!$AH:$AH,"否")+COUNTIFS('指标体系-教育'!$AI:$AI,$A89,'指标体系-教育'!$AH:$AH,"否",'指标体系-教育'!$AG:$AG,"否") -> 12 | G89: =COUNTIFS('指标体系-企服'!$AI:$AI,$A89,'指标体系-企服'!$AA:$AA,G$68,'指标体系-企服'!$AH:$AH,"否")+COUNTIFS('指标体系-教育'!$AI:$AI,$A89,'指标体系-教育'!$AA:$AA,G$68,'指标体系-教育'!$AH:$AH,"否",'指标体系-教育'!$AG:$AG,"否") -> 8 | H89: =COUNTIFS('指标体系-企服'!$AI:$AI,$A89,'指标体系-企服'!$AA:$AA,H$68,'指标体系-企服'!$AH:$AH,"否")+COUNTIFS('指标体系-教育'!$AI:$AI,$A89,'指标体系-教育'!$AA:$AA,H$68,'指标体系-教育'!$AH:$AH,"否",'指标体系-教育'!$AG:$AG,"否") -> 4 | I89: =COUNTIFS('指标体系-企服'!$AI:$AI,$A89,'指标体系-企服'!$AA:$AA,I$68,'指标体系-企服'!$AH:$AH,"否")+COUNTIFS('指标体系-教育'!$AI:$AI,$A89,'指标体系-教育'!$AA:$AA,I$68,'指标体系-教育'!$AH:$AH,"否",'指标体系-教育'!$AG:$AG,"否") -> 0 | J89: 龚芬芬 | K89: =COUNTIF(指标体系!AI:AI,营销BI分析体系!J89) -> 19
A90: 业务拓展 | B90: =COUNTIFS('指标体系-企服'!$AI:$AI,$A90,'指标体系-企服'!$F:$F,B$68)+COUNTIFS('指标体系-教育'!$AI:$AI,$A90,'指标体系-教育'!$F:$F,B$68,'指标体系-教育'!$AG:$AG,"否") -> 8 | C90: =COUNTIFS('指标体系-企服'!$AI:$AI,$A90,'指标体系-企服'!$F:$F,C$68)+COUNTIFS('指标体系-教育'!$AI:$AI,$A90,'指标体系-教育'!$F:$F,C$68,'指标体系-教育'!$AG:$AG,"否") -> 12 | D90: =COUNTIFS('指标体系-企服'!$AI:$AI,$A90,'指标体系-企服'!$F:$F,D$68)+COUNTIFS('指标体系-教育'!$AI:$AI,$A90,'指标体系-教育'!$F:$F,D$68,'指标体系-教育'!$AG:$AG,"否") -> 11 | E90: =SUM(B90:D90) -> 31 | F90: =COUNTIFS('指标体系-企服'!$AI:$AI,$A90,'指标体系-企服'!$AH:$AH,"否")+COUNTIFS('指标体系-教育'!$AI:$AI,$A90,'指标体系-教育'!$AH:$AH,"否",'指标体系-教育'!$AG:$AG,"否") -> 14 | G90: =COUNTIFS('指标体系-企服'!$AI:$AI,$A90,'指标体系-企服'!$AA:$AA,G$68,'指标体系-企服'!$AH:$AH,"否")+COUNTIFS('指标体系-教育'!$AI:$AI,$A90,'指标体系-教育'!$AA:$AA,G$68,'指标体系-教育'!$AH:$AH,"否",'指标体系-教育'!$AG:$AG,"否") -> 13 | H90: =COUNTIFS('指标体系-企服'!$AI:$AI,$A90,'指标体系-企服'!$AA:$AA,H$68,'指标体系-企服'!$AH:$AH,"否")+COUNTIFS('指标体系-教育'!$AI:$AI,$A90,'指标体系-教育'!$AA:$AA,H$68,'指标体系-教育'!$AH:$AH,"否",'指标体系-教育'!$AG:$AG,"否") -> 1 | I90: =COUNTIFS('指标体系-企服'!$AI:$AI,$A90,'指标体系-企服'!$AA:$AA,I$68,'指标体系-企服'!$AH:$AH,"否")+COUNTIFS('指标体系-教育'!$AI:$AI,$A90,'指标体系-教育'!$AA:$AA,I$68,'指标体系-教育'!$AH:$AH,"否",'指标体系-教育'!$AG:$AG,"否") -> 0 | J90: 潘敏君 | K90: =COUNTIF(指标体系!AI:AI,营销BI分析体系!J90) -> 21
A91: 运营效率提升 | B91: =COUNTIFS('指标体系-企服'!$AI:$AI,$A91,'指标体系-企服'!$F:$F,B$68)+COUNTIFS('指标体系-教育'!$AI:$AI,$A91,'指标体系-教育'!$F:$F,B$68,'指标体系-教育'!$AG:$AG,"否") -> 3 | C91: =COUNTIFS('指标体系-企服'!$AI:$AI,$A91,'指标体系-企服'!$F:$F,C$68)+COUNTIFS('指标体系-教育'!$AI:$AI,$A91,'指标体系-教育'!$F:$F,C$68,'指标体系-教育'!$AG:$AG,"否") -> 4 | D91: =COUNTIFS('指标体系-企服'!$AI:$AI,$A91,'指标体系-企服'!$F:$F,D$68)+COUNTIFS('指标体系-教育'!$AI:$AI,$A91,'指标体系-教育'!$F:$F,D$68,'指标体系-教育'!$AG:$AG,"否") -> 3 | E91: =SUM(B91:D91) -> 10 | F91: =COUNTIFS('指标体系-企服'!$AI:$AI,$A91,'指标体系-企服'!$AH:$AH,"否")+COUNTIFS('指标体系-教育'!$AI:$AI,$A91,'指标体系-教育'!$AH:$AH,"否",'指标体系-教育'!$AG:$AG,"否") -> 5 | G91: =COUNTIFS('指标体系-企服'!$AI:$AI,$A91,'指标体系-企服'!$AA:$AA,G$68,'指标体系-企服'!$AH:$AH,"否")+COUNTIFS('指标体系-教育'!$AI:$AI,$A91,'指标体系-教育'!$AA:$AA,G$68,'指标体系-教育'!$AH:$AH,"否",'指标体系-教育'!$AG:$AG,"否") -> 1 | H91: =COUNTIFS('指标体系-企服'!$AI:$AI,$A91,'指标体系-企服'!$AA:$AA,H$68,'指标体系-企服'!$AH:$AH,"否")+COUNTIFS('指标体系-教育'!$AI:$AI,$A91,'指标体系-教育'!$AA:$AA,H$68,'指标体系-教育'!$AH:$AH,"否",'指标体系-教育'!$AG:$AG,"否") -> 4 | I91: =COUNTIFS('指标体系-企服'!$AI:$AI,$A91,'指标体系-企服'!$AA:$AA,I$68,'指标体系-企服'!$AH:$AH,"否")+COUNTIFS('指标体系-教育'!$AI:$AI,$A91,'指标体系-教育'!$AA:$AA,I$68,'指标体系-教育'!$AH:$AH,"否",'指标体系-教育'!$AG:$AG,"否") -> 0 | J91: 曾丽 | K91: =COUNTIF(指标体系!AI:AI,营销BI分析体系!J91) -> 14
A92: 客户提升 | B92: =COUNTIFS('指标体系-企服'!$AI:$AI,$A92,'指标体系-企服'!$F:$F,B$68)+COUNTIFS('指标体系-教育'!$AI:$AI,$A92,'指标体系-教育'!$F:$F,B$68,'指标体系-教育'!$AG:$AG,"否") -> 6 | C92: =COUNTIFS('指标体系-企服'!$AI:$AI,$A92,'指标体系-企服'!$F:$F,C$68)+COUNTIFS('指标体系-教育'!$AI:$AI,$A92,'指标体系-教育'!$F:$F,C$68,'指标体系-教育'!$AG:$AG,"否") -> 7 | D92: =COUNTIFS('指标体系-企服'!$AI:$AI,$A92,'指标体系-企服'!$F:$F,D$68)+COUNTIFS('指标体系-教育'!$AI:$AI,$A92,'指标体系-教育'!$F:$F,D$68,'指标体系-教育'!$AG:$AG,"否") -> 7 | E92: =SUM(B92:D92) -> 20 | F92: =COUNTIFS('指标体系-企服'!$AI:$AI,$A92,'指标体系-企服'!$AH:$AH,"否")+COUNTIFS('指标体系-教育'!$AI:$AI,$A92,'指标体系-教育'!$AH:$AH,"否",'指标体系-教育'!$AG:$AG,"否") -> 7 | G92: =COUNTIFS('指标体系-企服'!$AI:$AI,$A92,'指标体系-企服'!$AA:$AA,G$68,'指标体系-企服'!$AH:$AH,"否")+COUNTIFS('指标体系-教育'!$AI:$AI,$A92,'指标体系-教育'!$AA:$AA,G$68,'指标体系-教育'!$AH:$AH,"否",'指标体系-教育'!$AG:$AG,"否") -> 0 | H92: =COUNTIFS('指标体系-企服'!$AI:$AI,$A92,'指标体系-企服'!$AA:$AA,H$68,'指标体系-企服'!$AH:$AH,"否")+COUNTIFS('指标体系-教育'!$AI:$AI,$A92,'指标体系-教育'!$AA:$AA,H$68,'指标体系-教育'!$AH:$AH,"否",'指标体系-教育'!$AG:$AG,"否") -> 7 | I92: =COUNTIFS('指标体系-企服'!$AI:$AI,$A92,'指标体系-企服'!$AA:$AA,I$68,'指标体系-企服'!$AH:$AH,"否")+COUNTIFS('指标体系-教育'!$AI:$AI,$A92,'指标体系-教育'!$AA:$AA,I$68,'指标体系-教育'!$AH:$AH,"否",'指标体系-教育'!$AG:$AG,"否") -> 0 | J92: 陈亚婕 | K92: =COUNTIF(指标体系!AI:AI,营销BI分析体系!J92) -> 40
A93: 组织能力提升 | B93: =COUNTIFS('指标体系-企服'!$AI:$AI,$A93,'指标体系-企服'!$F:$F,B$68)+COUNTIFS('指标体系-教育'!$AI:$AI,$A93,'指标体系-教育'!$F:$F,B$68,'指标体系-教育'!$AG:$AG,"否") -> 7 | C93: =COUNTIFS('指标体系-企服'!$AI:$AI,$A93,'指标体系-企服'!$F:$F,C$68)+COUNTIFS('指标体系-教育'!$AI:$AI,$A93,'指标体系-教育'!$F:$F,C$68,'指标体系-教育'!$AG:$AG,"否") -> 10 | D93: =COUNTIFS('指标体系-企服'!$AI:$AI,$A93,'指标体系-企服'!$F:$F,D$68)+COUNTIFS('指标体系-教育'!$AI:$AI,$A93,'指标体系-教育'!$F:$F,D$68,'指标体系-教育'!$AG:$AG,"否") -> 11 | E93: =SUM(B93:D93) -> 28 | F93: =COUNTIFS('指标体系-企服'!$AI:$AI,$A93,'指标体系-企服'!$AH:$AH,"否")+COUNTIFS('指标体系-教育'!$AI:$AI,$A93,'指标体系-教育'!$AH:$AH,"否",'指标体系-教育'!$AG:$AG,"否") -> 15 | G93: =COUNTIFS('指标体系-企服'!$AI:$AI,$A93,'指标体系-企服'!$AA:$AA,G$68,'指标体系-企服'!$AH:$AH,"否")+COUNTIFS('指标体系-教育'!$AI:$AI,$A93,'指标体系-教育'!$AA:$AA,G$68,'指标体系-教育'!$AH:$AH,"否",'指标体系-教育'!$AG:$AG,"否") -> 3 | H93: =COUNTIFS('指标体系-企服'!$AI:$AI,$A93,'指标体系-企服'!$AA:$AA,H$68,'指标体系-企服'!$AH:$AH,"否")+COUNTIFS('指标体系-教育'!$AI:$AI,$A93,'指标体系-教育'!$AA:$AA,H$68,'指标体系-教育'!$AH:$AH,"否",'指标体系-教育'!$AG:$AG,"否") -> 2 | I93: =COUNTIFS('指标体系-企服'!$AI:$AI,$A93,'指标体系-企服'!$AA:$AA,I$68,'指标体系-企服'!$AH:$AH,"否")+COUNTIFS('指标体系-教育'!$AI:$AI,$A93,'指标体系-教育'!$AA:$AA,I$68,'指标体系-教育'!$AH:$AH,"否",'指标体系-教育'!$AG:$AG,"否") -> 10 | J93: 郭梓樱 | K93: =COUNTIF(指标体系!AI:AI,营销BI分析体系!J93) -> 21
A94: 合计 | B94: =SUM(B89:B93) -> 27 | C94: =SUM(C89:C93) -> 44 | D94: =SUM(D89:D93) -> 41 | E94: =SUM(E89:E93) -> 112 | F94: =SUM(F89:F93) -> 53 | G94: =SUM(G89:G93) -> 25 | H94: =SUM(H89:H93) -> 18 | I94: =SUM(I89:I93) -> 10 | J94: 合计 | K94: =SUM(K89:K93) -> 115
A95: 单位：个 | G95: =G94/$F$94 -> 0.47169811 | H95: =H94/$F$94 -> 0.33962264 | I95: =I94/$F$94 -> 0.18867925

Sheet 教育BI规划
A1: 分析内容 | E1: 主要分析维度 | O1: 频度 | P1: 紧急度 | Q1: 管理层级 | R1: 其他备注 | AA1: 日 | AB1: 周 | AC1: 月 | AD1: 季 | AE1: 半年 | AF1: 年
A2: 营销端价值链 | B2: 模块 | C2: 主题 | D2: 指标 | E2: 期间 | F2: 事业部 | G2: 项目 | H2: 产品线 | I2: 产品型号 | J2: 系列 | K2: 尺寸 | L2: 区域 | M2: 客户 | N2: 办事处 | AA2: BG | AB2: BU/一级部门 | AC2: 部门内 | AD2: 区域 | AE2: 办事处
B3: 商业计划 | C3: 产品规划 | D3: 产品企划命中率 | E3: √ | F3: √ | G3: √ | I3: √ | O3: 月 | P3: 一般 | Q3: BG | R3: 已立项可集成 | AA3: 紧急 | AB3: 一般 | AC3: 可延后
D4: 关键里程碑达成率 | E4: √ | F4: √ | G4: √ | I4: √ | J4: √ | K4: √ | O4: 周 | P4: 一般 | Q4: BG | R4: 集成已有BI
D5: 量产后销售进度达成率 | E5: √ | F5: √ | G5: √ | I5: √ | O5: 月 | P5: 一般 | Q5: BG | R5: 已立项可集成
C6: 销售目标 | D6: 预算达成 | E6: √ | F6: √ | H6: √ | J6: √ | K6: √ | L6: √ | N6: √ | O6: 月 | P6: 紧急 | Q6: BG
D7: 结构达成 | E7: √ | F7: √ | H7: √ | I7: √ | J7: √ | K7: √ | L7: √ | N7: √ | O7: 月 | P7: 紧急 | Q7: BG
D8: 预测达成 | E8: √ | F8: √ | L8: √ | O8: 周 | P8: 紧急 | Q8: BG
B9: 商机管理 | C9: 商机项目管理 | D9: 商机项目数量/金额（分阶段） | E9: √ | F9: √ | G9: √ | H9: √ | I9: √ | L9: √ | M9: √ | O9: 周 | P9: 紧急 | Q9: BG
D10: 商机转化率 | E10: √ | F10: √ | G10: √ | I10: √ | L10: √ | N10: √ | O10: 月 | P10: 紧急 | Q10: BG
D11: 线索中标量/金额 | E11: √ | F11: √ | G11: √ | I11: √ | L11: √ | N11: √ | O11: 日 | P11: 紧急 | Q11: BG
D12: 订单转化率金额 | E12: √ | F12: √ | G12: √ | I12: √ | L12: √ | N12: √ | O12: 日 | P12: 紧急 | Q12: BG
D13: 收入转化率/金额 | E13: √ | F13: √ | G13: √ | I13: √ | L13: √ | N13: √ | O13: 日 | P13: 紧急 | Q13: BG
D14: 中标转化订单周期 | E14: √ | F14: √ | G14: √ | L14: √ | M14: √ | N14: √ | O14: 周 | P14: 紧急 | Q14: BG
D15: 订单转化收入周期 | E15: √ | F15: √ | G15: √ | L15: √ | M15: √ | N15: √ | O15: 周 | P15: 紧急 | Q15: BG
C16: 订单管理 | D16: 订单数量/金额/单平均 | E16: √ | F16: √ | H16: √ | I16: √ | J16: √ | K16: √ | L16: √ | M16: √ | O16: 日 | P16: 紧急 | Q16: BG
D17: 订单未出货 | E17: √ | F17: √ | H17: √ | I17: √ | J17: √ | K17: √ | L17: √ | M17: √ | O17: 周 | P17: 紧急 | Q17: BG
D18: 合同配置效率 | E18: √ | F18: √ | H18: √ | I18: √ | J18: √ | K18: √ | L18: √ | M18: √ | O18: 月 | P18: 一般 | Q18: BU/一级部门
B19: 客户管理 | C19: 大客户销售管理 | D19: 客户份额占比 | E19: √ | F19: √ | H19: √ | I19: √ | J19: √ | K19: √ | L19: √ | M19: √ | N19: 延后 | O19: 月 | P19: 可延后 | Q19: BG
D20: 客户业绩贡献率 | E20: √ | F20: √ | H20: √ | I20: √ | J20: √ | K20: √ | L20: √ | M20: √ | N20: 延后 | O20: 月 | P20: 可延后 | Q20: BG
C21: 渠道管理 | D21: 渠道数量（新增及活跃数） | E21: √ | F21: √ | L21: √ | O21: 月 | P21: 紧急 | Q21: BG | R21: 已有BI优化
D22: 渠道业绩贡献（甄别有效渠道） | E22: √ | F22: √ | L22: √ | O22: 月 | P22: 紧急 | Q22: BG
D23: 电商平台 | E23: √ | F23: √ | L23: √ | N23: 延后 | O23: 日 | P23: 可延后 | Q23: BG
B24: 销售运营 | C24: 人均效率 | D24: 人均营收 | E24: √ | F24: √ | L24: √ | N24: √ | O24: 周 | P24: 紧急 | Q24: BG
D25: 人均净利 | E25: √ | F25: √ | L25: √ | N25: √ | O25: 月 | P25: 紧急 | Q25: BG
D26: 人均接单额 | E26: √ | F26: √ | L26: √ | N26: √ | O26: 周 | P26: 紧急 | Q26: BG
C27: 费用管理 | D27: 人力成本 | E27: √ | F27: √ | L27: √ | N27: √ | O27: 月 | P27: 紧急 | Q27: BG
D28: 差旅费投入产出 | E28: √ | F28: √ | G28: √ | L28: √ | M28: √ | N28: √ | O28: 月 | P28: 紧急 | Q28: BG
D29: 招待费投入产出 | E29: √ | F29: √ | G29: √ | L29: √ | M29: √ | N29: √ | O29: 月 | P29: 紧急 | Q29: BG
D30: 广宣费投入产出 | E30: √ | F30: √ | G30: √ | L30: √ | M30: √ | N30: √ | O30: 周 | P30: 紧急 | Q30: BG
D31: 物流运输费用 | E31: √ | F31: √ | I31: √ | J31: √ | K31: √ | O31: 月 | P31: 紧急 | Q31: BG
C32: 销售政策管理 | D32: 销售政策执行情况 | E32: √ | F32: √ | H32: √ | I32: √ | J32: √ | K32: √ | L32: √ | M32: √ | N32: √ | O32: 月 | P32: 紧急 | Q32: BG
D33: 政策性资源返利管理 | E33: √ | F33: √ | G33: √ | N33: √ | O33: 月 | P33: 紧急 | Q33: BG
B34: 盈利能力 | C34: 价格管理 | D34: 低于底价出货 | E34: √ | F34: √ | G34: √ | H34: √ | I34: √ | J34: √ | K34: √ | L34: √ | M34: √ | N34: √ | O34: 月 | P34: 紧急 | Q34: BG | R34: 已有BI优化
D35: 单价趋势（系列、机型） | E35: √ | F35: √ | H35: √ | I35: √ | J35: √ | K35: √ | L35: √ | M35: √ | N35: √ | O35: 月 | P35: 紧急 | Q35: BG
C36: 产品盈利能力 | D36: 收入 | E36: √ | F36: √ | H36: √ | I36: √ | J36: √ | K36: √ | L36: √ | M36: √ | N36: √ | O36: 日 | P36: 紧急 | Q36: BG
D37: 毛利额/毛利率 | E37: √ | F37: √ | H37: √ | I37: √ | J37: √ | K37: √ | L37: √ | M37: √ | N37: √ | O37: 月 | P37: 紧急 | Q37: BG
B38: 库存管理 | C38: 样机管理 | D38: 样机结存数量/金额 | E38: √ | F38: √ | H38: √ | I38: √ | J38: √ | K38: √ | L38: √ | N38: √ | O38: 月 | P38: 一般 | Q38: BG | R38: 已有BI优化
D39: 样机分用途及超期预警 | E39: √ | F39: √ | H39: √ | I39: √ | J39: √ | K39: √ | L39: √ | N39: √ | O39: 月 | P39: 紧急 | Q39: BG
D40: 样机盘点及管理报表 | E40: √ | F40: √ | H40: √ | I40: √ | J40: √ | K40: √ | L40: √ | N40: √ | O40: 月 | P40: 紧急 | Q40: BG
D41: 样机处置明细表 | E41: √ | F41: √ | H41: √ | I41: √ | J41: √ | K41: √ | L41: √ | N41: √ | O41: 月 | P41: 紧急 | Q41: BG
D42: 退市明细表 | E42: √ | F42: √ | H42: √ | I42: √ | J42: √ | K42: √ | L42: √ | N42: √ | O42: 月 | P42: 紧急 | Q42: BG
D43: 呆滞情况表/呆滞率 | E43: √ | F43: √ | H43: √ | I43: √ | J43: √ | K43: √ | L43: √ | N43: √ | O43: 月 | P43: 紧急 | Q43: BG | R43: 已有BI优化
C44: 成品库存管理 | D44: 结存数量/金额 | E44: √ | F44: √ | H44: √ | I44: √ | J44: √ | K44: √ | L44: √ | O44: 日 | P44: 紧急 | Q44: BG | R44: 已有BI优化
D45: 可发货及不良报表（分子库） | E45: √ | F45: √ | H45: √ | I45: √ | J45: √ | K45: √ | L45: √ | O45: 日 | P45: 紧急 | Q45: BG
D46: 存货资金占用 | E46: √ | F46: √ | H46: √ | I46: √ | J46: √ | K46: √ | L46: √ | O46: 日 | P46: 紧急 | Q46: BG
D47: 退市明细表 | E47: √ | F47: √ | H47: √ | I47: √ | J47: √ | K47: √ | L47: √ | O47: 周 | P47: 紧急 | Q47: BG
D48: 呆滞明细表/呆滞率 | E48: √ | F48: √ | H48: √ | I48: √ | J48: √ | K48: √ | L48: √ | O48: 日 | P48: 紧急 | Q48: BG | R48: 已有BI优化
D49: 周转天数（分子库） | E49: √ | F49: √ | H49: √ | I49: √ | J49: √ | K49: √ | L49: √ | O49: 日 | P49: 紧急 | Q49: BG

Sheet 指标体系-企服
B1: 一期 | C1: 部门价值填在此列 | AE1: 若无参考方法论可不填写
A2: 指标领域 | B2: 核心价值 | C2: 关键驱动因素 | D2: 分析主题域 | E2: 分析主题 | F2: 指标等级 | G2: 指标名称 | H2: 定义 | I2: 公式 | J2: 计算口径 | K2: 维度 | W2: 度量单位 | X2: 统计频率 | Y2: 统计精度 | Z2: 数据来源 | AA2: 优先级 | AB2: 指标用途 | AC2: 考核角色 | AD2: 要求角色 | AE2: 对应SCOR模型
K3: 期间 | L3: 事业部 | M3: 项目 | N3: 产品线 | O3: 产品型号 | P3: 系列 | Q3: 尺寸 | R3: 区域 | S3: 客户 | T3: 办事处 | U3: 仓位 | V3: 人员 | AF3: 对接人 | AG3: 是否相同 | AH3: 是否重复 | AI3: 核心价值
B4: 1.营收保障 | AE4: Reliability(可靠性)
A5: 营销 | B5: 扩大营业收入 | D5: 收入分析 | E5: 营业收入分析 | F5: 核心指标 | G5: 收入达成率 | H5: 完成收入目标的比例 | I5: 营业收入/收入目标 | J5: 1.BG 2.营业收入即不含税销售额 | K5: √ | L5: √ | N5: √ | O5: √ | P5: √ | Q5: √ | R5: √ | S5: √ | T5: √ | V5: √ | W5: % | X5: 日/周/月/季/年 | Y5: 两位小数点 | Z5: EBS/导入 | AA5: ★★★ | AB5: 内部管理 | AD5: 总裁/副总裁 | AF5: 潘敏君 | AG5: =VLOOKUP(G5,'指标体系-教育'!G:G,1,0)=G5 -> TRUE | AI5: 营收保障
A6: 营销 | B6: 扩大营业收入 | D6: 收入分析 | E6: 营业收入分析 | F6: 核心指标 | G6: 收入同比增长率 | H6: 收入同比增长比例 | I6: 本期营业收入/同期营业收入 | J6: BG | W6: % | X6: 月/季/年 | Y6: 两位小数点 | Z6: EBS | AA6: ★★★ | AB6: 内部管理 | AD6: 总裁/副总裁 | AF6: 潘敏君 | AG6: =VLOOKUP(G6,'指标体系-教育'!G:G,1,0)=G6 -> TRUE | AI6: =AI5 -> 营收保障
A7: 营销 | B7: 扩大营业收入 | D7: 收入分析 | E7: 营业收入分析 | F7: 核心指标 | G7: 毛利率 | H7: 毛利额占收入比例 | I7: 毛利额/营业收入 | J7: BG | K7: √ | L7: √ | N7: √ | O7: √ | P7: √ | Q7: √ | R7: √ | S7: √ | T7: √ | V7: √ | W7: % | X7: 月/季/年 | Y7: 两位小数点 | Z7: EBS | AA7: ★★★ | AB7: 内部管理 | AD7: 总裁/副总裁 | AF7: 潘敏君 | AG7: =VLOOKUP(G7,'指标体系-教育'!G:G,1,0)=G7 -> TRUE | AH7: 否 | AI7: =AI6 -> 营收保障
A8: 营销 | B8: 扩大营业收入 | D8: 收入分析 | E8: 营业收入分析 | F8: 一级指标 | G8: 营业收入 | H8: 营业收入 | I8: 营业收入 | J8: BG、分BU | K8: √ | L8: √ | N8: √ | O8: √ | P8: √ | Q8: √ | R8: √ | S8: √ | T8: √ | V8: √ | W8: 万元 | X8: 日/周/月/季/年 | Y8: 无小数点 | Z8: EBS | AA8: ★★★ | AB8: 内部管理 | AD8: 部门/BU负责人 | AF8: 潘敏君 | AG8: =VLOOKUP(G8,'指标体系-教育'!G:G,1,0)=G8 -> TRUE | AH8: 否 | AI8: =AI7 -> 营收保障
A9: 营销 | B9: 扩大营业收入 | D9: 收入分析 | E9: 营业收入分析 | F9: 一级指标 | G9: 收入达成率及排名 | H9: 完成收入目标的比例 | I9: 营业收入/收入目标 | J9: BG、分BU | W9: % | X9: 日/周/月/季/年 | Y9: 两位小数点 | Z9: EBS/导入 | AA9: ★★★ | AB9: 内部管理 | AD9: 部门/BU负责人 | AF9: 潘敏君 | AG9: =VLOOKUP(G9,'指标体系-教育'!G:G,1,0)=G9 -> TRUE | AH9: 否 | AI9: =AI8 -> 营收保障
A10: 营销 | B10: 扩大营业收入 | D10: 收入分析 | E10: 营业收入分析 | F10: 一级指标 | G10: 收入同比增长率 | H10: 收入同比增长比例 | I10: 本期营业收入/同期营业收入 | J10: BG、分BU | W10: % | X10: 月/季/年 | Y10: 两位小数点 | Z10: EBS | AA10: ★★★ | AB10: 内部管理 | AD10: 部门/BU负责人 | AF10: 潘敏君 | AG10: =VLOOKUP(G10,'指标体系-教育'!G:G,1,0)=G10 -> TRUE | AH10: 否 | AI10: =AI9 -> 营收保障
A11: 营销 | B11: 扩大营业收入 | D11: 收入分析 | E11: 销量分析 | F11: 一级指标 | G11: 整机销量 | H11: 整机销量 | I11: 整机销量 | J11: BG、分BU | K11: √ | L11: √ | N11: √ | O11: √ | P11: √ | Q11: √ | R11: √ | S11: √ | T11: √ | V11: √ | W11: 台 | X11: 日/周/月/季/年 | Y11: 无小数点 | Z11: EBS | AA11: ★★★ | AB11: 内部管理 | AD11: 部门/BU负责人 | AF11: 潘敏君 | AG11: =VLOOKUP(G11,'指标体系-教育'!G:G,1,0)=G11 -> TRUE | AH11: 否 | AI11: =AI10 -> 营收保障
A12: 营销 | B12: 扩大营业收入 | D12: 收入分析 | E12: 销量分析 | F12: 一级指标 | G12: 整机销量同比增长率 | H12: 整机销量同比增长比例 | I12: 本期整机销量/同期整机销量 | J12: BG、分BU | W12: % | X12: 月/季/年 | Y12: 两位小数点 | Z12: EBS | AA12: ★★★ | AB12: 内部管理 | AD12: 部门/BU负责人 | AF12: 潘敏君 | AG12: =VLOOKUP(G12,'指标体系-教育'!G:G,1,0)=G12 -> TRUE | AH12: 否 | AI12: =AI11 -> 营收保障
A13: 营销 | B13: 扩大营业收入 | D13: 收入分析 | E13: 配比分析 | F13: 一级指标 | G13: 周边配比 | H13: 周边收入占整体(整机+周边)收入比例 | I13: 周边营业收入/整体营业收入 | J13: BG、分BU | K13: √ | L13: √ | N13: √ | O13: √ | P13: √ | W13: % | X13: 月/季/年 | Y13: 两位小数点 | Z13: EBS | AA13: ★★ | AB13: 内部管理 | AD13: 部门/BU负责人 | AF13: 龚芬芬 | AG13: =VLOOKUP(G13,'指标体系-教育'!G:G,1,0)=G13 -> TRUE | AH13: 否 | AI13: =AI12 -> 营收保障
A14: 营销 | B14: 扩大营业收入 | D14: 收入分析 | E14: 配比分析 | F14: 一级指标 | G14: 主要周边销量配比 | H14: XX销量占对应整机销量比例 | I14: XX销量/对应整机销量 | J14: BG、分BU | K14: √ | L14: √ | N14: √ | O14: √ | P14: √ | W14: % | X14: 月/季/年 | Y14: 两位小数点 | Z14: EBS | AA14: ★★ | AB14: 内部管理 | AD14: 部门/BU负责人 | AF14: 龚芬芬 | AG14: =VLOOKUP(G14,'指标体系-教育'!G:G,1,0)=G14 -> TRUE | AH14: 否 | AI14: =AI13 -> 营收保障
A15: 营销 | B15: 扩大营业收入 | D15: 收入分析 | E15: 价格分析 | F15: 一级指标 | G15: 低价量占比 | H15: 低价单销量占整机销量比例 | I15: 低价单整机销量/整机销量 | J15: 1.BG、分BU 2.低价：低于核心价 | K15: √ | L15: √ | R15: √ | S15: √ | T15: √ | V15: √ | W15: % | X15: 月/季/年 | Y15: 两位小数点 | Z15: SCRM/EBS | AA15: ★★ | AB15: 内部管理 | AD15: 部门/BU负责人 | AF15: 龚芬芬 | AG15: =VLOOKUP(G15,'指标体系-教育'!G:G,1,0)=G15 -> TRUE | AH15: 否 | AI15: =AI14 -> 营收保障
A16: 营销 | B16: 扩大营业收入 | D16: 收入分析 | E16: 订单分析 | F16: 一级指标 | G16: 订单平均金额 | H16: 平均每个订单含税销售额 | I16: 含税销售额/订单数量 | J16: 1.BG、分BU 2.销售额即IN-销售额，含税 | K16: √ | L16: √ | R16: √ | S16: √ | T16: √ | V16: √ | W16: 万元 | X16: 日/周/月/季/年 | Y16: 无小数点 | Z16: EBS | AA16: ★★ | AB16: 内部管理 | AD16: 部门/BU负责人 | AF16: 龚芬芬 | AG16: =VLOOKUP(G16,'指标体系-教育'!G:G,1,0)=G16 -> TRUE | AH16: 否 | AI16: =AI15 -> 营收保障
A17: 营销 | B17: 扩大营业收入 | D17: 收入分析 | E17: 营业收入分析 | F17: 二级指标 | G17: 营业收入 | H17: 营业收入 | I17: 营业收入 | J17: BG、分BU、分区域、分办事处、分人员 | K17: √ | L17: √ | N17: √ | O17: √ | P17: √ | Q17: √ | R17: √ | S17: √ | T17: √ | V17: √ | W17: 万元 | X17: 日/周/月/季/年 | Y17: 无小数点 | Z17: EBS | AA17: ★★★ | AB17: 内部管理 | AD17: 区域/办事处负责人 | AF17: 潘敏君 | AG17: =VLOOKUP(G17,'指标体系-教育'!G:G,1,0)=G17 -> TRUE | AI17: =AI16 -> 营收保障
A18: 营销 | B18: 扩大营业收入 | D18: 收入分析 | E18: 营业收入分析 | F18: 二级指标 | G18: 收入达成率及排名 | H18: 完成收入目标的比例 | I18: 营业收入/收入目标 | J18: BG、分BU、分区域、分办事处、分人员 | W18: % | X18: 日/周/月/季/年 | Y18: 两位小数点 | Z18: EBS/导入 | AA18: ★★★ | AB18: 内部管理 | AD18: 区域/办事处负责人 | AF18: 潘敏君 | AG18: =VLOOKUP(G18,'指标体系-教育'!G:G,1,0)=G18 -> TRUE | AI18: =AI17 -> 营收保障
A19: 营销 | B19: 扩大营业收入 | D19: 收入分析 | E19: 营业收入分析 | F19: 二级指标 | G19: 收入同比增长率 | H19: 收入同比增长比例 | I19: 本期营业收入/同期营业收入 | J19: BG、分BU、分区域、分办事处、分人员 | W19: % | X19: 月/季/年 | Y19: 两位小数点 | Z19: EBS | AA19: ★★★ | AB19: 内部管理 | AD19: 区域/办事处负责人 | AF19: 潘敏君 | AG19: =VLOOKUP(G19,'指标体系-教育'!G:G,1,0)=G19 -> TRUE | AI19: =AI18 -> 营收保障
A20: 营销 | B20: 扩大营业收入 | D20: 收入分析 | E20: 销量分析 | F20: 二级指标 | G20: 整机销量 | H20: 整机销量 | I20: 整机销量 | J20: BG、分BU、分区域、分办事处、分人员 | K20: √ | L20: √ | N20: √ | O20: √ | P20: √ | Q20: √ | R20: √ | S20: √ | T20: √ | V20: √ | W20: 台 | X20: 日/周/月/季/年 | Y20: 无小数点 | Z20: EBS | AA20: ★★★ | AB20: 内部管理 | AD20: 区域/办事处负责人 | AF20: 潘敏君 | AG20: =VLOOKUP(G20,'指标体系-教育'!G:G,1,0)=G20 -> TRUE | AI20: =AI19 -> 营收保障
A21: 营销 | B21: 扩大营业收入 | D21: 收入分析 | E21: 销量分析 | F21: 二级指标 | G21: 整机销量同比增长率 | H21: 整机销量同比增长比例 | I21: 本期整机销量/同期整机销量 | J21: BG、分BU、分区域、分办事处、分人员 | W21: % | X21: 月/季/年 | Y21: 两位小数点 | Z21: EBS | AA21: ★★★ | AB21: 内部管理 | AD21: 区域/办事处负责人 | AF21: 潘敏君 | AG21: =VLOOKUP(G21,'指标体系-教育'!G:G,1,0)=G21 -> TRUE | AI21: =AI20 -> 营收保障
A22: 营销 | B22: 扩大营业收入 | D22: 收入分析 | E22: 价格分析 | F22: 二级指标 | G22: 低价量占比 | H22: 低价单销量占整机销量比例 | I22: 低价单整机销量/整机销量 | J22: 1.BG、分BU、分区域、分办事处、分人员 2.低价：低于核心价 | K22: √ | L22: √ | R22: √ | S22: √ | T22: √ | V22: √ | W22: % | X22: 月/季/年 | Y22: 两位小数点 | Z22: EBS/门户系统 | AA22: ★★ | AB22: 内部管理 | AD22: 区域/办事处负责人 | AF22: 龚芬芬 | AG22: =VLOOKUP(G22,'指标体系-教育'!G:G,1,0)=G22 -> TRUE | AI22: =AI21 -> 营收保障
A23: 营销 | B23: 扩大营业收入 | D23: 收入分析 | E23: 订单分析 | F23: 二级指标 | G23: 订单平均金额 | H23: 平均每个订单含税销售额 | I23: 含税销售额/订单数量 | J23: 1.BG、分BU、分区域、分办事处、分人员 2.销售额即IN-销售额，含税 | K23: √ | L23: √ | R23: √ | S23: √ | T23: √ | V23: √ | W23: 万元 | X23: 日/周/月/季/年 | Y23: 无小数点 | Z23: EBS | AA23: ★★ | AB23: 内部管理 | AD23: 区域/办事处负责人 | AF23: 龚芬芬 | AG23: =VLOOKUP(G23,'指标体系-教育'!G:G,1,0)=G23 -> TRUE | AI23: =AI22 -> 营收保障
B24: 2.业务拓展
A25: 营销 | B25: 强化业务拓展跟进 | D25: 业务拓展分析 | E25: 签约分析 | F25: 核心指标 | G25: 签约达成率 | H25: 完成签约数量目标的比例 | I25: 签约数量/签约数量目标 | J25: 渠道平台 | K25: √ | L25: √ | R25: √ | S25: √ | T25: √ | V25: √ | W25: % | X25: 日/周/月/季/年 | Y25: 两位小数点 | Z25: SCRM/导入 | AA25: ★★★ | AB25: 内部管理 | AD25: 总裁/副总裁 | AF25: 龚芬芬 | AG25: =VLOOKUP(G25,'指标体系-教育'!G:G,1,0)=G25 -> TRUE | AI25: 业务拓展
A26: 营销 | B26: 强化业务拓展跟进 | D26: 业务拓展分析 | E26: 商机分析 | F26: 核心指标 | G26: 商机达成率 | H26: 完成商机目标的比例 | I26: 商机额/商机目标 | J26: 1.渠道平台 2.商机额=商机量*核心价，含税 | K26: √ | L26: √ | N26: √ | O26: √ | P26: √ | Q26: √ | R26: √ | S26: √ | T26: √ | V26: √ | W26: % | X26: 日/周/月/季/年 | Y26: 两位小数点 | Z26: SCRM/导入 | AA26: ★★★ | AB26: 内部管理 | AD26: 总裁/副总裁 | AF26: 龚芬芬 | AG26: 否 | AI26: =AI25 -> 业务拓展
A27: 营销 | B27: 强化业务拓展跟进 | D27: 业务拓展分析 | E27: 商机分析 | F27: 核心指标 | G27: 商机转化率 | H27: 商机转化为销售的比例 | I27: 销售额/商机额 | J27: 1.渠道平台 2.商机额销售额均含税 | K27: √ | L27: √ | N27: √ | O27: √ | P27: √ | Q27: √ | R27: √ | S27: √ | T27: √ | V27: √ | W27: % | X27: 日/周/月/季/年 | Y27: 两位小数点 | Z27: SCRM/CRM | AA27: ★★★ | AB27: 内部管理 | AD27: 总裁/副总裁 | AF27: 龚芬芬 | AG27: =VLOOKUP(G27,'指标体系-教育'!G:G,1,0)=G27 -> TRUE | AI27: =AI26 -> 业务拓展
A28: 营销 | B28: 强化业务拓展跟进 | D28: 业务拓展分析 | E28: 接单分析 | F28: 核心指标 | G28: 接单达成率 | H28: 完成接单目标的比例 | I28: 接单量/接单目标 | J28: BG | K28: √ | L28: √ | R28: √ | S28: √ | T28: √ | V28: √ | W28: % | X28: 日/周/月/季/年 | Y28: 两位小数点 | Z28: SCRM/CRM | AA28: ★★★ | AB28: 内部管理 | AD28: 总裁/副总裁 | AF28: 龚芬芬 | AG28: 否 | AI28: =AI27 -> 业务拓展
A29: 营销 | B29: 强化业务拓展跟进 | D29: 业务拓展分析 | E29: 签约分析 | F29: 一级指标 | G29: 签约达成率 | H29: 完成签约数量目标的比例 | I29: 签约数量/签约数量目标 | J29: 渠道平台 | K29: √ | L29: √ | R29: √ | S29: √ | T29: √ | V29: √ | W29: % | X29: 日/周/月/季/年 | Y29: 两位小数点 | Z29: SCRM/导入 | AA29: ★★★ | AB29: 内部管理 | AD29: 部门/BU负责人 | AF29: 龚芬芬 | AG29: =VLOOKUP(G29,'指标体系-教育'!G:G,1,0)=G29 -> TRUE | AH29: 否 | AI29: =AI28 -> 业务拓展
A30: 营销 | B30: 强化业务拓展跟进 | D30: 业务拓展分析 | E30: 商机分析 | F30: 一级指标 | G30: 商机达成率 | H30: 完成商机目标的比例 | I30: 商机额/商机目标 | J30: 1.渠道平台 2.商机额=商机量*核心价，含税 | K30: √ | L30: √ | N30: √ | O30: √ | P30: √ | Q30: √ | R30: √ | S30: √ | T30: √ | V30: √ | W30: % | X30: 日/周/月/季/年 | Y30: 两位小数点 | Z30: SCRM/导入 | AA30: ★★★ | AB30: 内部管理 | AD30: 部门/BU负责人 | AF30: 龚芬芬 | AG30: 否 | AH30: 否 | AI30: =AI29 -> 业务拓展
A31: 营销 | B31: 强化业务拓展跟进 | D31: 业务拓展分析 | E31: 商机分析 | F31: 一级指标 | G31: 商机转化率 | H31: 商机转化为销售的比例 | I31: 销售额/商机额 | J31: 1.渠道平台 2.商机额销售额均含税 | K31: √ | L31: √ | N31: √ | O31: √ | P31: √ | Q31: √ | R31: √ | S31: √ | T31: √ | V31: √ | W31: % | X31: 日/周/月/季/年 | Y31: 两位小数点 | Z31: SCRM/CRM | AA31: ★★★ | AB31: 内部管理 | AD31: 部门/BU负责人 | AF31: 龚芬芬 | AG31: =VLOOKUP(G31,'指标体系-教育'!G:G,1,0)=G31 -> TRUE | AH31: 否 | AI31: =AI30 -> 业务拓展
A32: 营销 | B32: 强化业务拓展跟进 | D32: 业务拓展分析 | E32: 样机分析 | F32: 一级指标 | G32: 样机申请率 | H32: 样机申请量占额度比例 | I32: 样机申请量/样机额度 | J32: BG、分BU | K32: √ | L32: √ | N32: √ | O32: √ | P32: √ | Q32: √ | R32: √ | S32: √ | T32: √ | V32: √ | W32: % | X32: 日/周/月/季/年 | Y32: 两位小数点 | Z32: CRM/导入 | AA32: ★★★ | AB32: 内部管理 | AD32: 部门/BU负责人 | AF32: 龚芬芬 | AG32: 否 | AH32: 否 | AI32: =AI31 -> 业务拓展
A33: 营销 | B33: 强化业务拓展跟进 | D33: 业务拓展分析 | E33: 样机分析 | F33: 一级指标 | G33: 样机转销率 | H33: 样机转销量占申请比例 | I33: 样机转销量/样机申请量 | J33: BG、分BU | K33: √ | L33: √ | N33: √ | O33: √ | P33: √ | Q33: √ | R33: √ | S33: √ | T33: √ | V33: √ | W33: % | X33: 日/周/月/季/年 | Y33: 两位小数点 | Z33: CRM | AA33: ★★★ | AB33: 内部管理 | AD33: 部门/BU负责人 | AF33: 龚芬芬 | AG33: =VLOOKUP(G33,'指标体系-教育'!G:G,1,0)=G33 -> TRUE | AH33: 否 | AI33: =AI32 -> 业务拓展
A34: 营销 | B34: 强化业务拓展跟进 | D34: 业务拓展分析 | E34: 样机分析 | F34: 一级指标 | G34: 样机在外量 | H34: 样机未处理数量 | I34: 样机未处理数量 | J34: BG、分BU | K34: √ | L34: √ | N34: √ | O34: √ | P34: √ | Q34: √ | R34: √ | S34: √ | T34: √ | V34: √ | W34: 台 | X34: 日/周/月/季/年 | Y34: 无小数点 | Z34: CRM | AA34: ★★★ | AB34: 内部管理 | AD34: 部门/BU负责人 | AF34: 龚芬芬 | AG34: =VLOOKUP(G34,'指标体系-教育'!G:G,1,0)=G34 -> TRUE | AH34: 否 | AI34: =AI33 -> 业务拓展
A35: 营销 | B35: 强化业务拓展跟进 | D35: 业务拓展分析 | E35: 样机分析 | F35: 一级指标 | G35: 样机逾期率 | H35: 样机逾期量占在外量比例 | I35: 样机逾期量/样机在外量 | J35: BG、分BU | K35: √ | L35: √ | N35: √ | O35: √ | P35: √ | Q35: √ | R35: √ | S35: √ | T35: √ | V35: √ | W35: % | X35: 日/周/月/季/年 | Y35: 两位小数点 | Z35: CRM | AA35: ★★★ | AB35: 内部管理 | AD35: 部门/BU负责人 | AF35: 龚芬芬 | AG35: =VLOOKUP(G35,'指标体系-教育'!G:G,1,0)=G35 -> TRUE | AH35: 否 | AI35: =AI34 -> 业务拓展
A36: 营销 | B36: 强化业务拓展跟进 | D36: 业务拓展分析 | E36: 线索分析 | F36: 一级指标 | G36: 线索有效率 | H36: 有效线索数量占总线索数量比例 | I36: 有效线索量/总线索量 | J36: BG、分线上线下 | K36: √ | L36: √ | R36: √ | T36: √ | V36: √ | W36: % | X36: 日/周/月/季/年 | Y36: 两位小数点 | Z36: SCRM | AA36: ★★★ | AB36: 内部管理 | AD36: 部门/BU负责人 | AF36: 龚芬芬 | AG36: =VLOOKUP(G36,'指标体系-教育'!G:G,1,0)=G36 -> TRUE | AH36: 否 | AI36: =AI35 -> 业务拓展
A37: 营销 | B37: 强化业务拓展跟进 | D37: 业务拓展分析 | E37: 线索分析 | F37: 一级指标 | G37: 线索及时率 | H37: 及时处理线索数量占总线索数量比例 | I37: 及时线索量/总线索量 | J37: BG、分线上线下 | K37: √ | L37: √ | R37: √ | T37: √ | V37: √ | W37: % | X37: 日/周/月/季/年 | Y37: 两位小数点 | Z37: SCRM | AA37: ★★★ | AB37: 内部管理 | AD37: 部门/BU负责人 | AF37: 龚芬芬 | AG37: =VLOOKUP(G37,'指标体系-教育'!G:G,1,0)=G37 -> TRUE | AH37: 否 | AI37: =AI36 -> 业务拓展
A38: 营销 | B38: 强化业务拓展跟进 | D38: 业务拓展分析 | E38: 接单分析 | F38: 一级指标 | G38: 接单达成率 | H38: 完成接单目标的比例 | I38: 接单量/接单目标 | J38: BG、分BU | K38: √ | L38: √ | R38: √ | S38: √ | T38: √ | V38: √ | W38: % | X38: 日/周/月/季/年 | Y38: 两位小数点 | Z38: SCRM/CRM | AA38: ★★★ | AB38: 内部管理 | AD38: 部门/BU负责人 | AF38: 龚芬芬 | AG38: 否 | AH38: 否 | AI38: =AI37 -> 业务拓展
A39: 营销 | B39: 强化业务拓展跟进 | D39: 业务拓展分析 | E39: 签约分析 | F39: 二级指标 | G39: 签约达成率 | H39: 完成签约数量目标的比例 | I39: 签约数量/签约数量目标 | J39: 渠道平台、分区域、分办事处 | K39: √ | L39: √ | R39: √ | S39: √ | T39: √ | V39: √ | W39: % | X39: 日/周/月/季/年 | Y39: 两位小数点 | Z39: SCRM/导入 | AA39: ★★★ | AB39: 内部管理 | AD39: 区域/办事处负责人 | AF39: 龚芬芬 | AG39: =VLOOKUP(G39,'指标体系-教育'!G:G,1,0)=G39 -> TRUE | AI39: =AI38 -> 业务拓展
A40: 营销 | B40: 强化业务拓展跟进 | D40: 业务拓展分析 | E40: 商机分析 | F40: 二级指标 | G40: 商机达成率 | H40: 完成商机目标的比例 | I40: 商机额/商机目标 | J40: 1.渠道平台、分区域、分办事处 2.商机额=商机量*核心价，含税 | K40: √ | L40: √ | N40: √ | O40: √ | P40: √ | Q40: √ | R40: √ | S40: √ | T40: √ | V40: √ | W40: % | X40: 日/周/月/季/年 | Y40: 两位小数点 | Z40: SCRM/导入 | AA40: ★★★ | AB40: 内部管理 | AD40: 区域/办事处负责人 | AF40: 龚芬芬 | AG40: 否 | AI40: =AI39 -> 业务拓展
A41: 营销 | B41: 强化业务拓展跟进 | D41: 业务拓展分析 | E41: 商机分析 | F41: 二级指标 | G41: 商机转化率 | H41: 商机转化为销售的比例 | I41: 销售额/商机额 | J41: 1.渠道平台、分区域、分办事处 2.商机额销售额均含税 | K41: √ | L41: √ | N41: √ | O41: √ | P41: √ | Q41: √ | R41: √ | S41: √ | T41: √ | V41: √ | W41: % | X41: 日/周/月/季/年 | Y41: 两位小数点 | Z41: SCRM/CRM | AA41: ★★★ | AB41: 内部管理 | AD41: 区域/办事处负责人 | AF41: 龚芬芬 | AG41: =VLOOKUP(G41,'指标体系-教育'!G:G,1,0)=G41 -> TRUE | AI41: =AI40 -> 业务拓展
A42: 营销 | B42: 强化业务拓展跟进 | D42: 业务拓展分析 | E42: 样机分析 | F42: 二级指标 | G42: 样机转销率 | H42: 样机转销量占申请比例 | I42: 样机转销量/样机申请量 | J42: BG、分BU、分区域、分办事处 | K42: √ | L42: √ | N42: √ | O42: √ | P42: √ | Q42: √ | R42: √ | S42: √ | T42: √ | V42: √ | W42: % | X42: 日/周/月/季/年 | Y42: 两位小数点 | Z42: CRM | AA42: ★★★ | AB42: 内部管理 | AD42: 区域/办事处负责人 | AF42: 龚芬芬 | AG42: =VLOOKUP(G42,'指标体系-教育'!G:G,1,0)=G42 -> TRUE | AI42: =AI41 -> 业务拓展
A43: 营销 | B43: 强化业务拓展跟进 | D43: 业务拓展分析 | E43: 样机分析 | F43: 二级指标 | G43: 样机在外量 | H43: 样机未处理数量 | I43: 样机未处理数量 | J43: BG、分BU、分区域、分办事处 | K43: √ | L43: √ | N43: √ | O43: √ | P43: √ | Q43: √ | R43: √ | S43: √ | T43: √ | V43: √ | W43: 台 | X43: 日/周/月/季/年 | Y43: 无小数点 | Z43: CRM | AA43: ★★★ | AB43: 内部管理 | AD43: 区域/办事处负责人 | AF43: 龚芬芬 | AG43: =VLOOKUP(G43,'指标体系-教育'!G:G,1,0)=G43 -> TRUE | AI43: =AI42 -> 业务拓展
A44: 营销 | B44: 强化业务拓展跟进 | D44: 业务拓展分析 | E44: 样机分析 | F44: 二级指标 | G44: 样机逾期率 | H44: 样机逾期量占在外量比例 | I44: 样机逾期量/样机在外量 | J44: BG、分BU、分区域、分办事处 | K44: √ | L44: √ | N44: √ | O44: √ | P44: √ | Q44: √ | R44: √ | S44: √ | T44: √ | V44: √ | W44: % | X44: 日/周/月/季/年 | Y44: 两位小数点 | Z44: CRM | AA44: ★★★ | AB44: 内部管理 | AD44: 区域/办事处负责人 | AF44: 龚芬芬 | AG44: =VLOOKUP(G44,'指标体系-教育'!G:G,1,0)=G44 -> TRUE | AI44: =AI43 -> 业务拓展
A45: 营销 | B45: 强化业务拓展跟进 | D45: 业务拓展分析 | E45: 线索分析 | F45: 二级指标 | G45: 线索有效率 | H45: 有效线索数量占总线索数量比例 | I45: 有效线索量/总线索量 | J45: BG、分线上线下、分区域、分办事处 | K45: √ | L45: √ | N45: √ | O45: √ | P45: √ | Q45: √ | R45: √ | S45: √ | T45: √ | V45: √ | W45: % | X45: 日/周/月/季/年 | Y45: 两位小数点 | Z45: SCRM | AA45: ★★★ | AB45: 内部管理 | AD45: 区域/办事处负责人 | AF45: 龚芬芬 | AG45: =VLOOKUP(G45,'指标体系-教育'!G:G,1,0)=G45 -> TRUE | AI45: =AI44 -> 业务拓展
A46: 营销 | B46: 强化业务拓展跟进 | D46: 业务拓展分析 | E46: 线索分析 | F46: 二级指标 | G46: 线索及时率 | H46: 及时处理线索数量占总线索数量比例 | I46: 及时线索量/总线索量 | J46: BG、分线上线下、分区域、分办事处 | K46: √ | L46: √ | R46: √ | T46: √ | V46: √ | W46: % | X46: 日/周/月/季/年 | Y46: 两位小数点 | Z46: SCRM | AA46: ★★★ | AB46: 内部管理 | AD46: 区域/办事处负责人 | AF46: 龚芬芬 | AG46: =VLOOKUP(G46,'指标体系-教育'!G:G,1,0)=G46 -> TRUE | AI46: =AI45 -> 业务拓展
A47: 营销 | B47: 强化业务拓展跟进 | D47: 业务拓展分析 | E47: 接单分析 | F47: 二级指标 | G47: 接单达成率 | H47: 完成接单目标的比例 | I47: 接单量/接单目标 | J47: BG、分BU、分区域、分办事处 | K47: √ | L47: √ | R47: √ | S47: √ | T47: √ | V47: √ | W47: % | X47: 日/周/月/季/年 | Y47: 两位小数点 | Z47: SCRM/CRM | AA47: ★★★ | AB47: 内部管理 | AD47: 区域/办事处负责人 | AF47: 龚芬芬 | AG47: 否 | AI47: =AI46 -> 业务拓展
B48: 3.运营效率提升
A49: 营销 | B49: 提升运营效率 | D49: 运营效率分析 | E49: 库存周转分析 | F49: 核心指标 | G49: 库存周转天数 | H49: 库存周转天数 | I49: 当期天数*（期初存货金额+期末库存金额）/（2*当期销售成本） | J49: 含整机和周边 | K49: √ | N49: √ | P49: √ | Q49: √ | U49: √ | W49: 天 | X49: 周/月/季/年 | Y49: 无小数点 | Z49: EBS | AA49: ★★ | AB49: 内部管理 | AD49: 总裁/副总裁 | AF49: 潘敏君 | AG49: =VLOOKUP(G49,'指标体系-教育'!G:G,1,0)=G49 -> TRUE | AI49: 运营效率提升
A50: 营销 | B50: 提升运营效率 | D50: 运营效率分析 | E50: 库存周转分析 | F50: 核心指标 | G50: 超期库存占比 | H50: 2个月以上库存数量、金额占比 | I50: 2个月以上库存数量、金额/该产品总库存数量、金额 | J50: 分数量、金额 | K50: √ | N50: √ | P50: √ | Q50: √ | W50: % | X50: 日/周/月/季/年 | Y50: 无小数点 | Z50: EBS | AA50: ★★ | AB50: 内部管理 | AD50: 总裁/副总裁 | AF50: 潘敏君 | AG50: =VLOOKUP(G50,'指标体系-教育'!G:G,1,0)=G50 -> TRUE | AH50: 否 | AI50: =AI49 -> 运营效率提升
A51: 营销 | B51: 提升运营效率 | D51: 运营效率分析 | E51: 分仓效率分析 | F51: 一级指标 | G51: 分仓出货占比 | H51: 各物流仓出货占比 | I51: 各物流仓出货成本/（物流仓+工厂出货成本） | J51: 含整机和周边 | K51: √ | U51: √ | W51: % | X51: 日/周/月/季/年 | Y51: 无小数点 | Z51: EBS | AA51: ★★ | AB51: 内部管理 | AD51: 部门/BU负责人 | AF51: 潘敏君 | AG51: =VLOOKUP(G51,'指标体系-教育'!G:G,1,0)=G51 -> TRUE | AH51: 否 | AI51: =AI50 -> 运营效率提升
A52: 营销 | B52: 提升运营效率 | D52: 运营效率分析 | E52: 库存周转分析 | F52: 一级指标 | G52: 库存量 | H52: 库存量 | I52: 库存量 | J52: 整机 | K52: √ | N52: √ | O52: √ | P52: √ | Q52: √ | U52: √ | W52: 台 | X52: 日/周/月/季/年 | Y52: 无小数点 | Z52: EBS | AA52: ★★ | AB52: 内部管理 | AD52: 部门/BU负责人 | AF52: 潘敏君 | AG52: 否 | AH52: 否 | AI52: =AI51 -> 运营效率提升
A53: 营销 | B53: 提升运营效率 | D53: 运营效率分析 | E53: 库存周转分析 | F53: 一级指标 | G53: 库存周转天数 | H53: 库存周转天数 | I53: 当期天数*（期初存货金额+期末库存金额）/（2*当期销售成本） | J53: 含整机和周边 | K53: √ | N53: √ | O53: √ | P53: √ | Q53: √ | U53: √ | W53: 天 | X53: 周/月/季/年 | Y53: 无小数点 | Z53: EBS | AA53: ★★ | AB53: 内部管理 | AD53: 部门/BU负责人 | AF53: 潘敏君 | AG53: =VLOOKUP(G53,'指标体系-教育'!G:G,1,0)=G53 -> TRUE | AH53: 否 | AI53: =AI52 -> 运营效率提升
A54: 营销 | B54: 提升运营效率 | D54: 运营效率分析 | E54: 分仓效率分析 | F54: 二级指标 | G54: 分仓出货占比 | H54: 各物流仓出货占比 | I54: 各物流仓出货成本/（物流仓+工厂出货成本） | J54: 含整机和周边 | K54: √ | U54: √ | W54: % | X54: 日/周/月/季/年 | Y54: 无小数点 | Z54: EBS | AA54: ★★ | AB54: 内部管理 | AD54: 区域/办事处负责人 | AF54: 潘敏君 | AG54: =VLOOKUP(G54,'指标体系-教育'!G:G,1,0)=G54 -> TRUE | AI54: =AI53 -> 运营效率提升
A55: 营销 | B55: 提升运营效率 | D55: 运营效率分析 | E55: 库存周转分析 | F55: 二级指标 | G55: 库存量 | H55: 库存量 | I55: 库存量 | J55: 整机 | K55: √ | N55: √ | O55: √ | P55: √ | Q55: √ | U55: √ | W55: 台 | X55: 日/周/月/季/年 | Y55: 无小数点 | Z55: EBS | AA55: ★★ | AB55: 内部管理 | AD55: 区域/办事处负责人 | AF55: 潘敏君 | AG55: 否 | AI55: =AI54 -> 运营效率提升
A56: 营销 | B56: 提升运营效率 | D56: 运营效率分析 | E56: 库存周转分析 | F56: 二级指标 | G56: 库存周转天数 | H56: 库存周转天数 | I56: 当期天数*（期初存货金额+期末库存金额）/（2*当期销售成本） | J56: 含整机和周边 | K56: √ | N56: √ | O56: √ | P56: √ | Q56: √ | U56: √ | W56: 天 | X56: 周/月/季/年 | Y56: 无小数点 | Z56: EBS | AA56: ★★ | AB56: 内部管理 | AD56: 区域/办事处负责人 | AF56: 潘敏君 | AG56: =VLOOKUP(G56,'指标体系-教育'!G:G,1,0)=G56 -> TRUE | AI56: =AI55 -> 运营效率提升
B57: 4.客户提升
A58: 营销 | B58: 提升经销商能力及效率 | D58: 经销商分析 | E58: 渠道结构分析 | F58: 核心指标 | G58: 渠道核心占比 | H58: 渠道核心经销商发货额占渠道发货额比例 | I58: 渠道核心发货额/渠道发货额 | J58: 1.渠道平台 2.发货额(扣除返利前)，含税 | K58: √ | L58: √ | R58: √ | S58: √ | T58: √ | W58: % | X58: 月/季/年 | Y58: 两位小数点 | Z58: CRM | AA58: ★★ | AB58: 内部管理 | AD58: 总裁/副总裁 | AF58: 龚芬芬 | AG58: =VLOOKUP(G58,'指标体系-教育'!G:G,1,0)=G58 -> TRUE | AI58: 客户提升
A59: 营销 | B59: 提升经销商能力及效率 | D59: 经销商分析 | E59: 渠道结构分析 | F59: 核心指标 | G59: 渠道分销率 | H59: 二级销售额占总OUT发货额比例 | I59: 二级OUT/总OUT发货额 | J59: 1.渠道平台 2.OUT发货额，含税 | K59: √ | R59: √ | S59: √ | T59: √ | W59: % | X59: 月/季/年 | Y59: 两位小数点 | Z59: CRM | AA59: ★★ | AB59: 内部管理 | AD59: 总裁/副总裁 | AF59: 龚芬芬 | AG59: =VLOOKUP(G59,'指标体系-教育'!G:G,1,0)=G59 -> TRUE | AI59: =AI58 -> 客户提升
A60: 营销 | B60: 提升经销商能力及效率 | D60: 经销商分析 | E60: 二级分析 | F60: 核心指标 | G60: 二级有效率 | H60: 有效二级数量占总二级数量比例 | I60: 有效二级数量/总二级数量 | J60: 有效标准：已签约+ 1-2线：单商产能>=2.3w，出货月份数占比>=60% 3-5线：单商产能>=1.7w，出货月份数占比>=50% 6线：单商产能>=0.3w，出货月份数占比>=30% | K60: √ | R60: √ | S60: √ | T60: √ | W60: % | X60: 月/季/年 | Y60: 两位小数点 | Z60: CRM | AA60: ★★ | AB60: 内部管理 | AD60: 总裁/副总裁 | AF60: 龚芬芬 | AG60: 否 | AI60: =AI59 -> 客户提升
A61: 营销 | B61: 提升经销商能力及效率 | D61: 经销商分析 | E61: 二级分析 | F61: 核心指标 | G61: 二级承载率 | H61: 有效二级OUT占核代IN发货额比例 | I61: 有效二级OUT/核代OUT发货额 | J61: 1.渠道平台 2.OUT发货额、IN发货额，含税 | K61: √ | R61: √ | S61: √ | T61: √ | W61: % | X61: 月/季/年 | Y61: 两位小数点 | Z61: CRM | AA61: ★★ | AB61: 内部管理 | AD61: 总裁/副总裁 | AF61: 龚芬芬 | AG61: 否 | AI61: =AI60 -> 客户提升
A62: 营销 | B62: 提升经销商能力及效率 | D62: 经销商分析 | E62: 二级分析 | F62: 核心指标 | G62: 二级单商产能 | H62: 二级OUT发货额与签约月份数的比值 | I62: 二级OUT/签约月份数 | J62: 1.渠道平台 2.OUT发货额，含税 | K62: √ | R62: √ | S62: √ | T62: √ | W62: 万元 | X62: 月/季/年 | Y62: 两位小数点 | Z62: CRM | AA62: ★★ | AB62: 内部管理 | AD62: 总裁/副总裁 | AF62: 龚芬芬 | AG62: 否 | AI62: =AI61 -> 客户提升
A63: 营销 | B63: 提升经销商能力及效率 | D63: 经销商分析 | E63: 库存分析 | F63: 核心指标 | G63: 核心库存周转天数 | H63: 核心库存周转天数 | I63: 当期天数*（核心期初产品金额+核心期末产品金额）/（2*核心当期SO金额） | J63: 含整机和周边 | K63: √ | O63: √ | P63: √ | R63: √ | S63: √ | W63: 天 | X63: 周/月/季/年 | Y63: 无小数点 | Z63: CRM | AA63: ★★ | AB63: 内部管理 | AD63: 总裁/副总裁 | AF63: 潘敏君 | AG63: =VLOOKUP(G63,'指标体系-教育'!G:G,1,0)=G63 -> TRUE | AI63: =AI62 -> 客户提升
A64: 营销 | B64: 提升经销商能力及效率 | D64: 经销商分析 | E64: 渠道结构分析 | F64: 一级指标 | G64: 渠道核心占比 | H64: 渠道核心经销商发货额占渠道发货额比例 | I64: 渠道核心发货额/渠道发货额 | J64: 1.渠道平台 2.发货额(扣除返利前)，含税 | K64: √ | L64: √ | R64: √ | S64: √ | T64: √ | W64: % | X64: 月/季/年 | Y64: 两位小数点 | Z64: CRM | AA64: ★★ | AB64: 内部管理 | AD64: 部门/BU负责人 | AF64: 龚芬芬 | AG64: =VLOOKUP(G64,'指标体系-教育'!G:G,1,0)=G64 -> TRUE | AH64: 否 | AI64: =AI63 -> 客户提升
A65: 营销 | B65: 提升经销商能力及效率 | D65: 经销商分析 | E65: 渠道结构分析 | F65: 一级指标 | G65: 渠道分销率 | H65: 二级销售额占总OUT发货额比例 | I65: 二级OUT/总OUT发货额 | J65: 1.渠道平台 2.OUT发货额，含税 | K65: √ | R65: √ | S65: √ | T65: √ | W65: % | X65: 月/季/年 | Y65: 两位小数点 | Z65: CRM | AA65: ★★ | AD65: 部门/BU负责人 | AF65: 龚芬芬 | AG65: =VLOOKUP(G65,'指标体系-教育'!G:G,1,0)=G65 -> TRUE | AH65: 否 | AI65: =AI64 -> 客户提升
A66: 营销 | B66: 提升经销商能力及效率 | D66: 经销商分析 | E66: 二级分析 | F66: 一级指标 | G66: 二级有效率 | H66: 有效二级数量占总二级数量比例 | I66: 有效二级数量/总二级数量 | J66: 有效标准：已签约+ 1-2线：单商产能>=2.3w，出货月份数占比>=60% 3-5线：单商产能>=1.7w，出货月份数占比>=50% 6线：单商产能>=00.3w，出货月份数占比>=30% | K66: √ | R66: √ | S66: √ | T66: √ | W66: % | X66: 月/季/年 | Y66: 两位小数点 | Z66: CRM | AA66: ★★ | AD66: 部门/BU负责人 | AF66: 龚芬芬 | AG66: 否 | AH66: 否 | AI66: =AI65 -> 客户提升
A67: 营销 | B67: 提升经销商能力及效率 | D67: 经销商分析 | E67: 二级分析 | F67: 一级指标 | G67: 二级承载率 | H67: 有效二级OUT占核代IN发货额比例 | I67: 有效二级OUT/核代IN发货额 | J67: 1.渠道平台 2.OUT发货额、IN发货额，含税 | K67: √ | R67: √ | S67: √ | T67: √ | W67: % | X67: 月/季/年 | Y67: 两位小数点 | Z67: CRM | AA67: ★★ | AD67: 部门/BU负责人 | AF67: 龚芬芬 | AG67: 否 | AH67: 否 | AI67: =AI66 -> 客户提升
A68: 营销 | B68: 提升经销商能力及效率 | D68: 经销商分析 | E68: 二级分析 | F68: 一级指标 | G68: 二级单商产能 | H68: 二级OUT发货额与签约月份数的比值 | I68: 二级OUT/签约月份数 | J68: 1.渠道平台 2.OUT发货额，含税 | K68: √ | R68: √ | S68: √ | T68: √ | W68: 万元 | X68: 月/季/年 | Y68: 两位小数点 | Z68: CRM | AA68: ★★ | AD68: 部门/BU负责人 | AF68: 龚芬芬 | AG68: 否 | AH68: 否 | AI68: =AI67 -> 客户提升
A69: 营销 | B69: 提升经销商能力及效率 | D69: 经销商分析 | E69: 库存分析 | F69: 一级指标 | G69: 核心库存量 | H69: 核心库存数量 | I69: 核心库存量 | J69: 整机 | K69: √ | O69: √ | P69: √ | Q69: √ | R69: √ | S69: √ | W69: 台 | X69: 周/月/季/年 | Y69: 无小数点 | Z69: CRM | AA69: ★★ | AD69: 部门/BU负责人 | AF69: 潘敏君 | AG69: =VLOOKUP(G69,'指标体系-教育'!G:G,1,0)=G69 -> TRUE | AH69: 否 | AI69: =AI68 -> 客户提升
A70: 营销 | B70: 提升经销商能力及效率 | D70: 经销商分析 | E70: 库存分析 | F70: 一级指标 | G70: 核心库存周转天数 | H70: 核心库存周转天数 | I70: 当期天数*（核心期初产品金额+核心期末产品金额）/（2*核心当期SO金额） | J70: 含整机和周边 | K70: √ | O70: √ | P70: √ | Q70: √ | R70: √ | S70: √ | W70: 天 | X70: 周/月/季/年 | Y70: 无小数点 | Z70: CRM | AA70: ★★ | AD70: 部门/BU负责人 | AF70: 潘敏君 | AG70: =VLOOKUP(G70,'指标体系-教育'!G:G,1,0)=G70 -> TRUE | AH70: 否 | AI70: =AI69 -> 客户提升
A71: 营销 | B71: 提升经销商能力及效率 | D71: 经销商分析 | E71: 渠道结构分析 | F71: 二级指标 | G71: 渠道核心占比 | H71: 渠道核心经销商发货额占渠道发货额比例 | I71: 渠道核心发货额/渠道发货额 | J71: 1.渠道平台、分区域、分办事处 2.发货额(扣除返利前)，含税 | K71: √ | L71: √ | R71: √ | S71: √ | T71: √ | W71: % | X71: 月/季/年 | Y71: 两位小数点 | Z71: CRM | AA71: ★★ | AB71: 内部管理 | AD71: 区域/办事处负责人 | AF71: 龚芬芬 | AG71: =VLOOKUP(G71,'指标体系-教育'!G:G,1,0)=G71 -> TRUE | AI71: =AI70 -> 客户提升
A72: 营销 | B72: 提升经销商能力及效率 | D72: 经销商分析 | E72: 渠道结构分析 | F72: 二级指标 | G72: 渠道分销率 | H72: 二级销售额占总OUT发货额比例 | I72: 二级OUT/总OUT发货额 | J72: 1.渠道平台、分区域、分办事处 2.OUT发货额，含税 | K72: √ | R72: √ | S72: √ | T72: √ | W72: % | X72: 月/季/年 | Y72: 两位小数点 | Z72: CRM | AA72: ★★ | AD72: 区域/办事处负责人 | AF72: 龚芬芬 | AG72: =VLOOKUP(G72,'指标体系-教育'!G:G,1,0)=G72 -> TRUE | AI72: =AI71 -> 客户提升
A73: 营销 | B73: 提升经销商能力及效率 | D73: 经销商分析 | E73: 二级分析 | F73: 二级指标 | G73: 二级有效率 | H73: 有效二级数量占总二级数量比例 | I73: 有效二级数量/总二级数量 | J73: 有效标准：已签约+ 1-2线：单商产能>=2.3w，出货月份数占比>=60% 3-5线：单商产能>=1.7w，出货月份数占比>=50% 6线：单商产能>=00.3w，出货月份数占比>=30% | K73: √ | R73: √ | S73: √ | T73: √ | W73: % | X73: 月/季/年 | Y73: 两位小数点 | Z73: CRM | AA73: ★★ | AD73: 区域/办事处负责人 | AF73: 龚芬芬 | AG73: 否 | AI73: =AI72 -> 客户提升
A74: 营销 | B74: 提升经销商能力及效率 | D74: 经销商分析 | E74: 二级分析 | F74: 二级指标 | G74: 二级承载率 | H74: 有效二级OUT占核代IN发货额比例 | I74: 有效二级OUT/核代IN发货额 | J74: 1.渠道平台、分区域、分办事处 2.OUT发货额、IN发货额，含税 | K74: √ | R74: √ | S74: √ | T74: √ | W74: % | X74: 月/季/年 | Y74: 两位小数点 | Z74: CRM | AA74: ★★ | AD74: 区域/办事处负责人 | AF74: 龚芬芬 | AG74: 否 | AI74: =AI73 -> 客户提升
A75: 营销 | B75: 提升经销商能力及效率 | D75: 经销商分析 | E75: 二级分析 | F75: 二级指标 | G75: 二级单商产能 | H75: 二级OUT发货额与签约月份数的比值 | I75: 二级OUT/签约月份数 | J75: 1.渠道平台、分区域、分办事处 2.OUT发货额，含税 | K75: √ | R75: √ | S75: √ | T75: √ | W75: 万元 | X75: 月/季/年 | Y75: 两位小数点 | Z75: CRM | AA75: ★★ | AD75: 区域/办事处负责人 | AF75: 龚芬芬 | AG75: 否 | AI75: =AI74 -> 客户提升
A76: 营销 | B76: 提升经销商能力及效率 | D76: 经销商分析 | E76: 库存分析 | F76: 二级指标 | G76: 核心库存量 | H76: 核心库存数量 | I76: 核心库存量 | J76: 整机 | K76: √ | O76: √ | P76: √ | Q76: √ | R76: √ | S76: √ | W76: 台 | X76: 周/月/季/年 | Y76: 无小数点 | Z76: CRM | AA76: ★★ | AD76: 区域/办事处负责人 | AF76: 潘敏君 | AG76: =VLOOKUP(G76,'指标体系-教育'!G:G,1,0)=G76 -> TRUE | AI76: =AI75 -> 客户提升
A77: 营销 | B77: 提升经销商能力及效率 | D77: 经销商分析 | E77: 库存分析 | F77: 二级指标 | G77: 核心库存周转天数 | H77: 核心库存周转天数 | I77: 当期天数*（核心期初产品金额+核心期末产品金额）/（2*核心当期SO金额） | J77: 含整机和周边 | K77: √ | O77: √ | P77: √ | Q77: √ | R77: √ | S77: √ | W77: 天 | X77: 周/月/季/年 | Y77: 无小数点 | Z77: CRM | AA77: ★★ | AD77: 区域/办事处负责人 | AF77: 潘敏君 | AG77: =VLOOKUP(G77,'指标体系-教育'!G:G,1,0)=G77 -> TRUE | AI77: =AI76 -> 客户提升
B78: 5.组织能力提升
A79: 营销 | B79: 提升营销人效 | D79: 人效分析 | E79: 人员效率分析 | F79: 核心指标 | G79: 营销人均收入 | H79: 营业收入与营销人数的比 | I79: 营业收入/营销人数 | J79: BG营销人数 | K79: √ | L79: √ | R79: √ | T79: √ | W79: 万元 | X79: 月/季/年 | Y79: 两位小数点 | Z79: EBS/人力系统 | AA79: ★ | AB79: 内部管理 | AD79: 总裁/副总裁 | AF79: 曾丽 | AG79: =VLOOKUP(G79,'指标体系-教育'!G:G,1,0)=G79 -> TRUE | AI79: 组织能力提升
A80: 营销 | B80: 提升营销人效 | D80: 人效分析 | E80: 人员效率分析 | F80: 核心指标 | G80: 营销人均利润 | H80: 毛利额与营销人数的比 | I80: 毛利额/营销人数 | J80: BG营销人数 | K80: √ | L80: √ | R80: √ | T80: √ | W80: 万元 | X80: 月/季/年 | Y80: 两位小数点 | Z80: EBS/人力系统 | AA80: ★ | AB80: 内部管理 | AD80: 总裁/副总裁 | AF80: 曾丽 | AG80: =VLOOKUP(G80,'指标体系-教育'!G:G,1,0)=G80 -> TRUE | AI80: =AI79 -> 组织能力提升
A81: 营销 | B81: 提升营销人效 | D81: 人效分析 | E81: 人员效率分析 | F81: 一级指标 | G81: 营销人均收入 | H81: 营业收入与营销人数的比 | I81: 营业收入/营销人数 | J81: BG、BU营销人数 | K81: √ | L81: √ | R81: √ | T81: √ | W81: 万元 | X81: 月/季/年 | Y81: 两位小数点 | Z81: EBS/人力系统 | AA81: ★ | AB81: 内部管理 | AD81: 部门/BU负责人 | AF81: 曾丽 | AG81: =VLOOKUP(G81,'指标体系-教育'!G:G,1,0)=G81 -> TRUE | AH81: 否 | AI81: =AI80 -> 组织能力提升
A82: 营销 | B82: 提升营销人效 | D82: 人效分析 | E82: 人员效率分析 | F82: 一级指标 | G82: 营销人均利润 | H82: 毛利额与营销人数的比 | I82: 毛利额/营销人数 | J82: BG、BU营销人数 | K82: √ | L82: √ | R82: √ | T82: √ | W82: 万元 | X82: 月/季/年 | Y82: 两位小数点 | Z82: EBS/人力系统 | AA82: ★ | AB82: 内部管理 | AD82: 部门/BU负责人 | AF82: 曾丽 | AG82: =VLOOKUP(G82,'指标体系-教育'!G:G,1,0)=G82 -> TRUE | AH82: 否 | AI82: =AI81 -> 组织能力提升
A83: 营销 | B83: 提升营销人效 | D83: 人效分析 | E83: 人员效率分析 | F83: 一级指标 | G83: 营销人均人力成本 | H83: 营业成本与营销人数的比 | I83: 营业成本/营销人数 | J83: BG、BU营销人数 | K83: √ | L83: √ | R83: √ | T83: √ | W83: 万元 | X83: 月/季/年 | Y83: 两位小数点 | Z83: EBS/人力系统 | AA83: ★ | AB83: 内部管理 | AD83: 部门/BU负责人 | AF83: 曾丽 | AG83: =VLOOKUP(G83,'指标体系-教育'!G:G,1,0)=G83 -> TRUE | AH83: 否 | AI83: =AI82 -> 组织能力提升
A84: 营销 | B84: 提升营销人效 | D84: 人效分析 | E84: 人员效率分析 | F84: 一级指标 | G84: 营销人均招待费 | H84: 招待费与营销人数的比 | I84: 招待费/营销人数 | J84: BG、BU营销人数 | K84: √ | L84: √ | R84: √ | T84: √ | W84: 万元 | X84: 月/季/年 | Y84: 两位小数点 | Z84: EBS/人力系统 | AA84: ★ | AB84: 内部管理 | AD84: 部门/BU负责人 | AF84: 曾丽 | AG84: =VLOOKUP(G84,'指标体系-教育'!G:G,1,0)=G84 -> TRUE | AH84: 否 | AI84: =AI83 -> 组织能力提升
A85: 营销 | B85: 提升营销人效 | D85: 人效分析 | E85: 人员效率分析 | F85: 一级指标 | G85: 营销人均差旅费 | H85: 差旅费与营销人数的比 | I85: 差旅费/营销人数 | J85: BG、BU营销人数 | K85: √ | L85: √ | R85: √ | T85: √ | W85: 万元 | X85: 月/季/年 | Y85: 两位小数点 | Z85: EBS/人力系统 | AA85: ★ | AB85: 内部管理 | AD85: 部门/BU负责人 | AF85: 曾丽 | AG85: =VLOOKUP(G85,'指标体系-教育'!G:G,1,0)=G85 -> TRUE | AH85: 否 | AI85: =AI84 -> 组织能力提升
A86: 营销 | B86: 提升营销人效 | D86: 人效分析 | E86: 人员效率分析 | F86: 二级指标 | G86: 营销人均收入 | H86: 营业收入与营销人数的比 | I86: 营业收入/营销人数 | J86: BG、BU、区域、办事处营销人数 | K86: √ | L86: √ | R86: √ | T86: √ | W86: 万元 | X86: 月/季/年 | Y86: 两位小数点 | Z86: EBS/人力系统 | AA86: ★ | AB86: 内部管理 | AD86: 区域/办事处负责人 | AF86: 曾丽 | AG86: =VLOOKUP(G86,'指标体系-教育'!G:G,1,0)=G86 -> TRUE | AI86: =AI85 -> 组织能力提升
A87: 营销 | B87: 提升营销人效 | D87: 人效分析 | E87: 人员效率分析 | F87: 二级指标 | G87: 营销人均利润 | H87: 毛利额与营销人数的比 | I87: 毛利额/营销人数 | J87: BG、BU、区域、办事处营销人数 | K87: √ | L87: √ | R87: √ | T87: √ | W87: 万元 | X87: 月/季/年 | Y87: 两位小数点 | Z87: EBS/人力系统 | AA87: ★ | AB87: 内部管理 | AD87: 区域/办事处负责人 | AF87: 曾丽 | AG87: =VLOOKUP(G87,'指标体系-教育'!G:G,1,0)=G87 -> TRUE | AI87: =AI86 -> 组织能力提升
A88: 营销 | B88: 提升营销人效 | D88: 人效分析 | E88: 人员效率分析 | F88: 二级指标 | G88: 营销人均人力成本 | H88: 营业成本与营销人数的比 | I88: 营业成本/营销人数 | J88: BG、BU、区域、办事处营销人数 | K88: √ | L88: √ | R88: √ | T88: √ | W88: 万元 | X88: 月/季/年 | Y88: 两位小数点 | Z88: EBS/人力系统 | AA88: ★ | AB88: 内部管理 | AD88: 区域/办事处负责人 | AF88: 曾丽 | AG88: =VLOOKUP(G88,'指标体系-教育'!G:G,1,0)=G88 -> TRUE | AI88: =AI87 -> 组织能力提升
A89: 营销 | B89: 提升营销人效 | D89: 人效分析 | E89: 人员效率分析 | F89: 二级指标 | G89: 营销人均招待费 | H89: 招待费与营销人数的比 | I89: 招待费/营销人数 | J89: BG、BU、区域、办事处营销人数 | K89: √ | L89: √ | R89: √ | T89: √ | W89: 万元 | X89: 月/季/年 | Y89: 两位小数点 | Z89: EBS/人力系统 | AA89: ★ | AB89: 内部管理 | AD89: 区域/办事处负责人 | AF89: 曾丽 | AG89: =VLOOKUP(G89,'指标体系-教育'!G:G,1,0)=G89 -> TRUE | AI89: =AI88 -> 组织能力提升
A90: 营销 | B90: 提升营销人效 | D90: 人效分析 | E90: 人员效率分析 | F90: 二级指标 | G90: 营销人均差旅费 | H90: 差旅费与营销人数的比 | I90: 差旅费/营销人数 | J90: BG、BU、区域、办事处营销人数 | K90: √ | L90: √ | R90: √ | T90: √ | W90: 万元 | X90: 月/季/年 | Y90: 两位小数点 | Z90: EBS/人力系统 | AA90: ★ | AB90: 内部管理 | AD90: 区域/办事处负责人 | AF90: 曾丽 | AG90: =VLOOKUP(G90,'指标体系-教育'!G:G,1,0)=G90 -> TRUE | AI90: =AI89 -> 组织能力提升
A91: 营销 | B91: 提升营销人效 | D91: 人效分析 | E91: 职级分析 | F91: 核心指标 | G91: 总人数 | H91: 总人数 | I91: 总人数 | J91: BG | K91: √ | L91: √ | R91: √ | T91: √ | W91: 人 | X91: 月/季/年 | Y91: 无小数点 | Z91: 人力系统 | AA91: ★ | AB91: 内部管理 | AD91: 总裁/副总裁 | AF91: 曾丽 | AG91: =VLOOKUP(G91,'指标体系-教育'!G:G,1,0)=G91 -> TRUE | AH91: 否 | AI91: =AI90 -> 组织能力提升
A92: 营销 | B92: 提升营销人效 | D92: 人效分析 | E92: 职级分析 | F92: 核心指标 | G92: 营销人数 | H92: 营销人数 | I92: 营销人数 | J92: BG | K92: √ | L92: √ | R92: √ | T92: √ | W92: 人 | X92: 月/季/年 | Y92: 无小数点 | Z92: 人力系统 | AA92: ★ | AB92: 内部管理 | AD92: 总裁/副总裁 | AF92: 曾丽 | AG92: =VLOOKUP(G92,'指标体系-教育'!G:G,1,0)=G92 -> TRUE | AI92: =AI91 -> 组织能力提升
A93: 营销 | B93: 提升营销人效 | D93: 人效分析 | E93: 职级分析 | F93: 核心指标 | G93: 营销人数占比 | H93: 营销人数占总人数比例 | I93: 营销人数/总人数 | J93: BG | W93: % | X93: 月/季/年 | Y93: 两位小数点 | Z93: 人力系统 | AA93: ★ | AB93: 内部管理 | AD93: 总裁/副总裁 | AF93: 曾丽 | AG93: =VLOOKUP(G93,'指标体系-教育'!G:G,1,0)=G93 -> TRUE | AI93: =AI92 -> 组织能力提升
A94: 营销 | B94: 提升营销人效 | D94: 人效分析 | E94: 职级分析 | F94: 一级指标 | G94: 营销人数 | H94: 营销人数 | I94: 营销人数 | J94: BU营销人数 | K94: √ | L94: √ | R94: √ | T94: √ | W94: 人 | X94: 月/季/年 | Y94: 无小数点 | Z94: 人力系统 | AA94: ★ | AB94: 内部管理 | AD94: 部门/BU负责人 | AF94: 曾丽 | AG94: =VLOOKUP(G94,'指标体系-教育'!G:G,1,0)=G94 -> TRUE | AH94: 否 | AI94: =AI93 -> 组织能力提升
A95: 营销 | B95: 提升营销人效 | D95: 人效分析 | E95: 职级分析 | F95: 一级指标 | G95: 营销人数占比 | H95: 营销人数占总人数比例 | I95: 营销人数/总人数 | J95: BU营销人数 | W95: % | X95: 月/季/年 | Y95: 两位小数点 | Z95: 人力系统 | AA95: ★ | AB95: 内部管理 | AD95: 部门/BU负责人 | AF95: 曾丽 | AG95: =VLOOKUP(G95,'指标体系-教育'!G:G,1,0)=G95 -> TRUE | AH95: 否 | AI95: =AI94 -> 组织能力提升
A96: 营销 | B96: 提升营销人效 | D96: 人效分析 | E96: 职级分析 | F96: 一级指标 | G96: 营销人数同比增长率 | H96: 营销人数同比增长比例 | I96: 本期营销人数/同期营销人数 | J96: BU营销人数 | W96: % | X96: 月/季/年 | Y96: 两位小数点 | Z96: 人力系统 | AA96: ★ | AB96: 内部管理 | AD96: 部门/BU负责人 | AF96: 曾丽 | AG96: =VLOOKUP(G96,'指标体系-教育'!G:G,1,0)=G96 -> TRUE | AH96: 否 | AI96: =AI95 -> 组织能力提升
A97: 营销 | B97: 提升营销人效 | D97: 人效分析 | E97: 职级分析 | F97: 一级指标 | G97: 职级人数占比 | H97: 职级人数占总人数比例 | I97: 职级人数/总人数 | J97: BU职级人数 | K97: √ | L97: √ | R97: √ | T97: √ | W97: % | X97: 月/季/年 | Y97: 两位小数点 | Z97: 人力系统 | AA97: ★ | AB97: 内部管理 | AD97: 部门/BU负责人 | AF97: 曾丽 | AG97: =VLOOKUP(G97,'指标体系-教育'!G:G,1,0)=G97 -> TRUE | AH97: 否 | AI97: =AI96 -> 组织能力提升
A98: 营销 | B98: 提升营销人效 | D98: 人效分析 | E98: 职级分析 | F98: 二级指标 | G98: 营销人数 | H98: 营销人数 | I98: 营销人数 | J98: BU营销人数 | K98: √ | L98: √ | R98: √ | T98: √ | W98: 人 | X98: 月/季/年 | Y98: 无小数点 | Z98: 人力系统 | AA98: ★ | AB98: 内部管理 | AD98: 区域/办事处负责人 | AF98: 曾丽 | AG98: =VLOOKUP(G98,'指标体系-教育'!G:G,1,0)=G98 -> TRUE | AI98: =AI97 -> 组织能力提升
A99: 营销 | B99: 提升营销人效 | D99: 人效分析 | E99: 职级分析 | F99: 二级指标 | G99: 营销人数占比 | H99: 营销人数占总人数比例 | I99: 营销人数/总人数 | J99: BU营销人数 | W99: % | X99: 月/季/年 | Y99: 两位小数点 | Z99: 人力系统 | AA99: ★ | AB99: 内部管理 | AD99: 区域/办事处负责人 | AF99: 曾丽 | AG99: =VLOOKUP(G99,'指标体系-教育'!G:G,1,0)=G99 -> TRUE | AI99: =AI98 -> 组织能力提升
A100: 营销 | B100: 提升营销人效 | D100: 人效分析 | E100: 职级分析 | F100: 二级指标 | G100: 营销人数同比 | H100: 营销人数同比增长比例 | I100: 本期营销人数/同期营销人数 | J100: BU营销人数 | W100: % | X100: 月/季/年 | Y100: 两位小数点 | Z100: 人力系统 | AA100: ★ | AB100: 内部管理 | AD100: 区域/办事处负责人 | AF100: 曾丽 | AG100: =VLOOKUP(G100,'指标体系-教育'!G:G,1,0)=G100 -> #N/A | AI100: =AI99 -> 组织能力提升
...

Sheet 指标体系-教育
B1: 一期 | C1: 部门价值填在此列 | AE1: 若无参考方法论可不填写
A2: 指标领域 | B2: 核心价值 | C2: 关键驱动因素 | D2: 分析主题域 | E2: 分析主题 | F2: 指标等级 | G2: 指标名称 | H2: 定义 | I2: 公式 | J2: 计算口径 | K2: 维度 | W2: 度量单位 | X2: 统计频率 | Y2: 统计精度 | Z2: 数据来源 | AA2: 优先级 | AB2: 指标用途 | AC2: 考核角色 | AD2: 要求角色 | AE2: 对应SCOR模型
K3: 期间 | L3: 事业部 | M3: 项目 | N3: 产品线 | O3: 产品型号 | P3: 系列 | Q3: 尺寸 | R3: 区域 | S3: 客户 | T3: 办事处 | U3: 仓位 | V3: 销售人员 | AF3: 对接人 | AG3: 是否相同 | AH3: 是否重复 | AI3: 核心价值
B4: 1.营收保障 | AE4: Reliability(可靠性)
A5: 营销 | B5: 扩大营业收入 | D5: 收入分析 | E5: 营业收入分析 | F5: 核心指标 | G5: 收入达成率 | H5: 完成收入预算、预测的比例 | I5: 营业收入/收入预算、预测 | J5: 1.BG 2、教务在闪畅收入 3.营业收入即不含税销售额 | K5: √ | L5: √ | M5: √ | N5: √ | O5: √ | P5: √ | Q5: √ | R5: √ | T5: √ | W5: % | X5: 日/周/月/季/年 | Y5: 一位小数点 | Z5: CRM/EDS/导入 | AA5: ★★★ | AB5: 内部管理 | AD5: 总裁/副总裁 | AF5: 陈亚婕 | AG5: =VLOOKUP(G5,'指标体系-企服'!G:G,1,0)=G5 -> TRUE | AI5: 营收保障
A6: 营销 | B6: 扩大营业收入 | D6: 收入分析 | E6: 营业收入分析 | F6: 核心指标 | G6: 收入同比增长率 | H6: 收入同比增长比例 | I6: 本期营业收入/同期营业收入 | J6: BG | K6: √ | L6: √ | N6: √ | O6: √ | P6: √ | Q6: √ | R6: √ | S6: √ | T6: √ | W6: % | X6: 月/季/年 | Y6: 一位小数点 | Z6: CRM/EDS | AA6: ★★★ | AB6: 内部管理 | AD6: 总裁/副总裁 | AF6: 陈亚婕 | AG6: =VLOOKUP(G6,'指标体系-企服'!G:G,1,0)=G6 -> TRUE | AH6: 否 | AI6: =AI5 -> 营收保障
A7: 营销 | B7: 扩大营业收入 | D7: 收入分析 | E7: 营业收入分析 | F7: 核心指标 | G7: 毛利率 | H7: 毛利额占收入比例 | I7: 毛利额/营业收入 | J7: BG | K7: √ | L7: √ | M7: √ | N7: √ | O7: √ | P7: √ | Q7: √ | R7: √ | S7: √ | T7: √ | W7: % | X7: 月/季/年 | Y7: 一位小数点 | Z7: CRM/EDS | AA7: ★★★ | AB7: 内部管理 | AD7: 总裁/副总裁 | AF7: 陈亚婕 | AG7: =VLOOKUP(G7,'指标体系-企服'!G:G,1,0)=G7 -> TRUE | AH7: 否 | AI7: =AI6 -> 营收保障
A8: 营销 | B8: 扩大营业收入 | D8: 收入分析 | E8: 营业收入分析 | F8: 一级指标 | G8: 营业收入 | H8: 营业收入 | I8: 营业收入 | J8: BG、分BU | K8: √ | L8: √ | M8: √ | N8: √ | O8: √ | P8: √ | Q8: √ | R8: √ | S8: √ | T8: √ | W8: 万元 | X8: 日/周/月/季/年 | Y8: 无小数点 | Z8: CRM/EDS | AA8: ★★★ | AB8: 内部管理 | AD8: 部门/BU负责人 | AF8: 陈亚婕 | AG8: =VLOOKUP(G8,'指标体系-企服'!G:G,1,0)=G8 -> TRUE | AH8: 否 | AI8: =AI7 -> 营收保障
A9: 营销 | B9: 扩大营业收入 | D9: 收入分析 | E9: 营业收入分析 | F9: 一级指标 | G9: 收入达成率及排名 | H9: 完成收入预算、预测的比例 | I9: 营业收入/收入预算、预测 | J9: BG、分BU | K9: √ | L9: √ | O9: √ | P9: √ | R9: √ | T9: √ | W9: % | X9: 日/周/月/季/年 | Y9: 一位小数点 | Z9: CRM/EDS/导入 | AA9: ★★★ | AB9: 内部管理 | AD9: 部门/BU负责人 | AF9: 陈亚婕 | AG9: =VLOOKUP(G9,'指标体系-企服'!G:G,1,0)=G9 -> TRUE | AH9: 否 | AI9: =AI8 -> 营收保障
A10: 营销 | B10: 扩大营业收入 | D10: 收入分析 | E10: 营业收入分析 | F10: 一级指标 | G10: 收入同比增长率 | H10: 收入同比增长比例 | I10: 本期营业收入/同期营业收入 | J10: BG、分BU | K10: √ | L10: √ | N10: √ | Q10: √ | R10: √ | S10: √ | T10: √ | W10: % | X10: 月/季/年 | Y10: 一位小数点 | Z10: CRM/EDS | AA10: ★★★ | AB10: 内部管理 | AD10: 部门/BU负责人 | AF10: 陈亚婕 | AG10: =VLOOKUP(G10,'指标体系-企服'!G:G,1,0)=G10 -> TRUE | AI10: =AI9 -> 营收保障
A11: 营销 | B11: 扩大营业收入 | D11: 收入分析 | E11: 销量分析 | F11: 一级指标 | G11: 整机销量 | H11: 整机销量 | I11: 整机销量 | J11: BG、分BU | K11: √ | L11: √ | M11: √ | N11: √ | O11: √ | P11: √ | Q11: √ | R11: √ | S11: √ | T11: √ | W11: 台 | X11: 日/周/月/季/年 | Y11: 无小数点 | Z11: CRM/EDS | AA11: ★★★ | AB11: 内部管理 | AD11: 部门/BU负责人 | AF11: 陈亚婕 | AG11: =VLOOKUP(G11,'指标体系-企服'!G:G,1,0)=G11 -> TRUE | AH11: 否 | AI11: =AI10 -> 营收保障
A12: 营销 | B12: 扩大营业收入 | D12: 收入分析 | E12: 销量分析 | F12: 一级指标 | G12: 整机销量同比增长率 | H12: 整机销量同比增长比例 | I12: 本期整机销量/同期整机销量 | J12: BG、分BU | K12: √ | L12: √ | N12: √ | O12: √ | P12: √ | Q12: √ | R12: √ | S12: √ | T12: √ | W12: % | X12: 月/季/年 | Y12: 一位小数点 | Z12: CRM/EDS | AA12: ★★★ | AB12: 内部管理 | AD12: 部门/BU负责人 | AF12: 陈亚婕 | AG12: =VLOOKUP(G12,'指标体系-企服'!G:G,1,0)=G12 -> TRUE | AH12: 否 | AI12: =AI11 -> 营收保障
A13: 营销 | B13: 扩大营业收入 | D13: 收入分析 | E13: 配比分析 | F13: 一级指标 | G13: 周边配比 | H13: 周边收入占整体(整机+周边)收入比例 | I13: 周边营业收入/整体营业收入 | J13: BG、分BU | K13: √ | L13: √ | N13: √ | O13: √ | P13: √ | Q13: √ | R13: √ | T13: √ | W13: % | X13: 月/季/年 | Y13: 一位小数点 | Z13: CRM/EDS | AA13: ★★ | AB13: 内部管理 | AD13: 部门/BU负责人 | AF13: 陈亚婕 | AG13: =VLOOKUP(G13,'指标体系-企服'!G:G,1,0)=G13 -> TRUE | AH13: 否 | AI13: =AI12 -> 营收保障
A14: 营销 | B14: 扩大营业收入 | D14: 收入分析 | E14: 配比分析 | F14: 一级指标 | G14: 主要周边销量配比 | H14: XX销量占对应整机销量比例 | I14: XX销量/对应整机销量 | J14: BG、分BU | K14: √ | L14: √ | N14: √ | O14: √ | P14: √ | Q14: √ | R14: √ | T14: √ | W14: % | X14: 月/季/年 | Y14: 一位小数点 | Z14: CRM/EDS | AA14: ★★ | AB14: 内部管理 | AD14: 部门/BU负责人 | AF14: 陈亚婕 | AG14: =VLOOKUP(G14,'指标体系-企服'!G:G,1,0)=G14 -> TRUE | AH14: 否 | AI14: =AI13 -> 营收保障
A15: 营销 | B15: 扩大营业收入 | D15: 收入分析 | E15: 价格分析 | F15: 一级指标 | G15: 低价量占比 | H15: 低价单销量占整机销量比例 | I15: 低价单整机销量/整机销量 | J15: 1.BG、分BU 2.低价：低于核心价 | K15: √ | L15: √ | N15: √ | O15: √ | R15: √ | S15: √ | T15: √ | V15: √ | W15: % | X15: 月/季/年 | Y15: 一位小数点 | Z15: CRM/EDS | AA15: ★★★ | AB15: 内部管理 | AD15: 部门/BU负责人 | AF15: 陈亚婕 | AG15: =VLOOKUP(G15,'指标体系-企服'!G:G,1,0)=G15 -> TRUE | AH15: 否 | AI15: =AI14 -> 营收保障
A16: 营销 | B16: 扩大营业收入 | D16: 收入分析 | E16: 价格分析 | F16: 一级指标 | G16: 低价金额占比 | H16: 低价单金额占全部金额比例 | I16: 低价单金额/全部营收 | J16: 1.BG、分BU 2.低价：低于核心价 | K16: √ | L16: √ | N16: √ | O16: √ | R16: √ | S16: √ | T16: √ | V16: √ | W16: % | X16: 月/季/年 | Y16: 一位小数点 | Z16: CRM/EDS | AA16: ★★★ | AB16: 内部管理 | AD16: 部门/BU负责人 | AF16: 陈亚婕 | AG16: 否 | AH16: 否 | AI16: =AI15 -> 营收保障
A17: 营销 | B17: 扩大营业收入 | D17: 收入分析 | E17: 价格分析 | F17: 一级指标 | G17: 平均单价 | H17: 产品平均单价 | I17: 营业收入/数量 | J17: 1.BG、分BU 2.低价：低于核心价 | K17: √ | L17: √ | M17: √ | N17: √ | O17: √ | P17: √ | Q17: √ | R17: √ | S17: √ | T17: √ | W17: % | X17: 月/季/年 | Y17: 一位小数点 | Z17: CRM/EDS | AA17: ★★★ | AB17: 内部管理 | AD17: 部门/BU负责人 | AF17: 陈亚婕 | AG17: 否 | AH17: 否 | AI17: =AI16 -> 营收保障
A18: 营销 | B18: 扩大营业收入 | D18: 收入分析 | E18: 订单分析 | F18: 一级指标 | G18: 订单平均金额 | H18: 平均每个订单的收入 | I18: 营业收入/订单数量 | J18: 1.BG、分BU、分区域、分办事处、分人员 2.销售额即IN-销售额，含税 | K18: √ | L18: √ | M18: √ | N18: √ | O18: √ | P18: √ | Q18: √ | R18: √ | S18: √ | T18: √ | W18: 万元 | X18: 日/周/月/季/年 | Y18: 无小数点 | Z18: CRM/EDS | AA18: ★★ | AB18: 内部管理 | AD18: 区域/办事处负责人 | AF18: 陈亚婕 | AG18: =VLOOKUP(G18,'指标体系-企服'!G:G,1,0)=G18 -> TRUE | AH18: 否 | AI18: =AI17 -> 营收保障
A19: 营销 | B19: 扩大营业收入 | D19: 收入分析 | E19: 营业收入分析 | F19: 二级指标 | G19: 营业收入 | H19: 营业收入 | I19: 营业收入 | J19: BG、分BU、分区域、分办事处、分人员 | K19: √ | L19: √ | M19: √ | N19: √ | O19: √ | P19: √ | Q19: √ | R19: √ | T19: √ | W19: 万元 | X19: 日/周/月/季/年 | Y19: 无小数点 | Z19: CRM/EDS | AA19: ★★★ | AB19: 内部管理 | AD19: 区域/办事处负责人 | AF19: 陈亚婕 | AG19: =VLOOKUP(G19,'指标体系-企服'!G:G,1,0)=G19 -> TRUE | AI19: =AI18 -> 营收保障
A20: 营销 | B20: 扩大营业收入 | D20: 收入分析 | E20: 营业收入分析 | F20: 二级指标 | G20: 收入达成率及排名 | H20: 完成收入目标的比例 | I20: 营业收入/收入目标 | J20: BG、分BU、分区域、分办事处、分人员 | K20: √ | L20: √ | N20: √ | O20: √ | P20: √ | Q20: √ | R20: √ | T20: √ | W20: % | X20: 日/周/月/季/年 | Y20: 一位小数点 | Z20: CRM/EDS/导入 | AA20: ★★★ | AB20: 内部管理 | AD20: 区域/办事处负责人 | AF20: 陈亚婕 | AG20: =VLOOKUP(G20,'指标体系-企服'!G:G,1,0)=G20 -> TRUE | AI20: =AI19 -> 营收保障
A21: 营销 | B21: 扩大营业收入 | D21: 收入分析 | E21: 营业收入分析 | F21: 二级指标 | G21: 收入同比增长率 | H21: 收入同比增长比例 | I21: 本期营业收入/同期营业收入 | J21: BG、分BU、分区域、分办事处、分人员 | K21: √ | L21: √ | N21: √ | O21: √ | P21: √ | Q21: √ | R21: √ | S21: √ | T21: √ | W21: % | X21: 月/季/年 | Y21: 一位小数点 | Z21: CRM/EDS | AA21: ★★★ | AB21: 内部管理 | AD21: 区域/办事处负责人 | AF21: 陈亚婕 | AG21: =VLOOKUP(G21,'指标体系-企服'!G:G,1,0)=G21 -> TRUE | AI21: =AI20 -> 营收保障
A22: 营销 | B22: 扩大营业收入 | D22: 收入分析 | E22: 销量分析 | F22: 二级指标 | G22: 整机销量 | H22: 整机销量 | I22: 整机销量 | J22: BG、分BU、分区域、分办事处、分人员 | K22: √ | L22: √ | M22: √ | N22: √ | O22: √ | P22: √ | Q22: √ | R22: √ | S22: √ | T22: √ | W22: 台 | X22: 日/周/月/季/年 | Y22: 无小数点 | Z22: CRM/EDS | AA22: ★★★ | AB22: 内部管理 | AD22: 区域/办事处负责人 | AF22: 陈亚婕 | AG22: =VLOOKUP(G22,'指标体系-企服'!G:G,1,0)=G22 -> TRUE | AI22: =AI21 -> 营收保障
A23: 营销 | B23: 扩大营业收入 | D23: 收入分析 | E23: 销量分析 | F23: 二级指标 | G23: 整机销量同比增长率 | H23: 整机销量同比增长比例 | I23: 本期整机销量/同期整机销量 | J23: BG、分BU、分区域、分办事处、分人员 | K23: √ | L23: √ | N23: √ | O23: √ | P23: √ | Q23: √ | R23: √ | S23: √ | T23: √ | W23: % | X23: 月/季/年 | Y23: 一位小数点 | Z23: CRM/EDS | AA23: ★★★ | AB23: 内部管理 | AD23: 区域/办事处负责人 | AF23: 陈亚婕 | AG23: =VLOOKUP(G23,'指标体系-企服'!G:G,1,0)=G23 -> TRUE | AI23: =AI22 -> 营收保障
A24: 营销 | B24: 扩大营业收入 | D24: 收入分析 | E24: 价格分析 | F24: 二级指标 | G24: 低价量占比 | H24: 低价单销量占整机销量比例 | I24: 低价单整机销量/整机销量 | J24: 1.BG、分BU、分区域、分办事处、分人员 2.低价：低于核心价 | K24: √ | L24: √ | N24: √ | O24: √ | R24: √ | S24: √ | T24: √ | V24: √ | W24: % | X24: 月/季/年 | Y24: 一位小数点 | Z24: CRM/EDS | AA24: ★★★ | AB24: 内部管理 | AD24: 区域/办事处负责人 | AF24: 陈亚婕 | AG24: =VLOOKUP(G24,'指标体系-企服'!G:G,1,0)=G24 -> TRUE | AI24: =AI23 -> 营收保障
A25: 营销 | B25: 扩大营业收入 | D25: 收入分析 | E25: 价格分析 | F25: 二级指标 | G25: 低价金额占比 | H25: 低价单金额占全部金额比例 | I25: 低价单金额/全部营收 | J25: 1.BG、分BU 2.低价：低于核心价 | K25: √ | L25: √ | N25: √ | O25: √ | R25: √ | S25: √ | T25: √ | V25: √ | W25: % | X25: 月/季/年 | Y25: 一位小数点 | Z25: CRM/EDS | AA25: ★★★ | AB25: 内部管理 | AD25: 部门/BU负责人 | AF25: 陈亚婕 | AG25: 否 | AI25: =AI24 -> 营收保障
A26: 营销 | B26: 扩大营业收入 | D26: 收入分析 | E26: 价格分析 | F26: 二级指标 | G26: 平均单价 | H26: 产品平均单价 | I26: 营业收入/数量 | J26: 1.BG、分BU 2.低价：低于核心价 | K26: √ | L26: √ | M26: √ | N26: √ | O26: √ | P26: √ | Q26: √ | R26: √ | S26: √ | T26: √ | W26: % | X26: 月/季/年 | Y26: 一位小数点 | Z26: CRM/EDS | AA26: ★★★ | AB26: 内部管理 | AD26: 部门/BU负责人 | AF26: 陈亚婕 | AG26: 否 | AI26: =AI25 -> 营收保障
A27: 营销 | B27: 扩大营业收入 | D27: 收入分析 | E27: 订单分析 | F27: 二级指标 | G27: 订单平均金额 | H27: 平均每个订单的收入 | I27: 营业收入/订单数量 | J27: 1.BG、分BU、分区域、分办事处、分人员 2.销售额即IN-销售额，含税 | K27: √ | L27: √ | M27: √ | N27: √ | O27: √ | P27: √ | Q27: √ | R27: √ | S27: √ | T27: √ | W27: 万元 | X27: 日/周/月/季/年 | Y27: 无小数点 | Z27: CRM/EDS | AA27: ★★ | AB27: 内部管理 | AD27: 区域/办事处负责人 | AF27: 陈亚婕 | AG27: =VLOOKUP(G27,'指标体系-企服'!G:G,1,0)=G27 -> TRUE | AI27: =AI26 -> 营收保障
B28: 2.业务拓展
A29: 营销 | B29: 强化业务拓展跟进 | D29: 业务拓展分析 | E29: 签约分析 | F29: 核心指标 | G29: 签约达成率 | H29: 完成签约数量目标的比例 | I29: 签约数量/签约数量目标 | J29: 教培事业部 | K29: √ | L29: √ | O29: √ | P29: √ | Q29: √ | R29: √ | S29: √ | T29: √ | W29: % | X29: 日/周/月/季/年 | Y29: 一位小数点 | Z29: SCRM/导入 | AA29: ★★ | AB29: 内部管理 | AD29: 总裁/副总裁 | AF29: 陈亚婕 | AG29: =VLOOKUP(G29,'指标体系-企服'!G:G,1,0)=G29 -> TRUE | AH29: 否 | AI29: 业务拓展
A30: 营销 | B30: 强化业务拓展跟进 | D30: 业务拓展分析 | E30: 商机分析 | F30: 核心指标 | G30: 商机项目数量/金额（分阶段） | H30: 商机项目数量/金额（分阶段） | J30: 1.BG 2.商机额销售额均不含税 | K30: √ | L30: √ | N30: √ | O30: √ | P30: √ | Q30: √ | R30: √ | S30: √ | T30: √ | V30: √ | W30: % | X30: 日/周/月/季/年 | Y30: 一位小数点 | Z30: SCRM | AA30: ★★★ | AB30: 内部管理 | AD30: 总裁/副总裁 | AF30: 陈亚婕 | AG30: 否 | AH30: 否 | AI30: =AI29 -> 业务拓展
A31: 营销 | B31: 强化业务拓展跟进 | D31: 业务拓展分析 | E31: 商机分析 | F31: 核心指标 | G31: 商机转化率 | H31: 线索转化为商机的比例 | I31: 线索中标量/金额 | J31: 1.营销平台 2.商机额销售额均含税 | K31: √ | L31: √ | N31: √ | O31: √ | P31: √ | Q31: √ | R31: √ | S31: √ | T31: √ | V31: √ | W31: % | X31: 日/周/月/季/年 | Y31: 一位小数点 | Z31: SCRM/CRM | AA31: ★★ | AB31: 内部管理 | AD31: 总裁/副总裁 | AF31: 陈亚婕 | AG31: =VLOOKUP(G31,'指标体系-企服'!G:G,1,0)=G31 -> TRUE | AH31: 否 | AI31: =AI30 -> 业务拓展
A32: 营销 | B32: 强化业务拓展跟进 | D32: 业务拓展分析 | E32: 商机分析 | F32: 核心指标 | G32: 商机转化率 | H32: 商机转化为订单的比例 | I32: 订单转化率金额 | J32: 1.营销平台 2.商机额销售额均含税 | K32: √ | L32: √ | N32: √ | O32: √ | P32: √ | Q32: √ | R32: √ | S32: √ | T32: √ | V32: √ | W32: % | X32: 日/周/月/季/年 | Y32: 一位小数点 | Z32: SCRM/CRM | AA32: ★★★ | AB32: 内部管理 | AD32: 总裁/副总裁 | AF32: 陈亚婕 | AG32: =VLOOKUP(G32,'指标体系-企服'!G:G,1,0)=G32 -> TRUE | AI32: =AI31 -> 业务拓展
A33: 营销 | B33: 强化业务拓展跟进 | D33: 业务拓展分析 | E33: 接单分析 | F33: 核心指标 | G33: 商机转化率 | H33: 订单转收入的比例 | I33: 收入转化率/金额 | J33: 1.营销平台 2.商机额销售额均含税 | K33: √ | L33: √ | N33: √ | R33: √ | S33: √ | T33: √ | V33: √ | W33: % | X33: 日/周/月/季/年 | Y33: 一位小数点 | Z33: SCRM/CRM | AA33: ★★★ | AB33: 内部管理 | AD33: 总裁/副总裁 | AF33: 陈亚婕 | AG33: =VLOOKUP(G33,'指标体系-企服'!G:G,1,0)=G33 -> TRUE | AI33: =AI32 -> 业务拓展
A34: 营销 | B34: 强化业务拓展跟进 | D34: 业务拓展分析 | E34: 接单分析 | F34: 核心指标 | G34: 接单收入 | H34: 订单数量/金额/单平均 | J34: BG、分BU | K34: √ | L34: √ | N34: √ | O34: √ | P34: √ | Q34: √ | R34: √ | S34: √ | T34: √ | V34: √ | W34: % | X34: 日/周/月/季/年 | Y34: 一位小数点 | Z34: SCRM/CRM | AA34: ★★★ | AB34: 内部管理 | AD34: 总裁/副总裁 | AF34: 陈亚婕 | AG34: 否 | AH34: 否 | AI34: =AI33 -> 业务拓展
A35: 营销 | B35: 强化业务拓展跟进 | D35: 业务拓展分析 | E35: 接单分析 | F35: 核心指标 | G35: 订单未出货 | H35: 订单未出货 | I35: 已接单未出货分时段 | J35: BG、分BU | K35: √ | L35: √ | N35: √ | O35: √ | P35: √ | Q35: √ | R35: √ | S35: √ | T35: √ | V35: √ | W35: % | X35: 日/周/月/季/年 | Y35: 一位小数点 | Z35: SCRM/CRM | AA35: ★★★ | AB35: 内部管理 | AD35: 总裁/副总裁 | AF35: 陈亚婕 | AG35: 否 | AH35: 否 | AI35: =AI34 -> 业务拓展
A36: 营销 | B36: 强化业务拓展跟进 | D36: 业务拓展分析 | E36: 接单分析 | F36: 核心指标 | G36: 合同配置效率 | J36: BG | K36: √ | L36: √ | N36: √ | R36: √ | S36: √ | T36: √ | W36: % | X36: 日/周/月/季/年 | Y36: 一位小数点 | Z36: SCRM/CRM | AA36: ★★ | AB36: 内部管理 | AD36: 总裁/副总裁 | AF36: 陈亚婕 | AG36: 否 | AH36: 否 | AI36: =AI35 -> 业务拓展
A37: 营销 | B37: 强化业务拓展跟进 | D37: 业务拓展分析 | E37: 签约分析 | F37: 一级指标 | G37: 签约达成率 | H37: 完成签约数量目标的比例 | I37: 签约数量/签约数量目标 | J37: 教培事业部 | K37: √ | L37: √ | R37: √ | S37: √ | T37: √ | W37: % | X37: 日/周/月/季/年 | Y37: 一位小数点 | Z37: SCRM/导入 | AA37: ★★ | AB37: 内部管理 | AD37: 部门/BU负责人 | AF37: 陈亚婕 | AG37: =VLOOKUP(G37,'指标体系-企服'!G:G,1,0)=G37 -> TRUE | AI37: =AI36 -> 业务拓展
A38: 营销 | B38: 强化业务拓展跟进 | D38: 业务拓展分析 | E38: 商机分析 | F38: 核心指标 | G38: 商机转化率 | H38: 线索转化为商机的比例 | I38: 线索中标量/金额 | J38: 1.营销平台 2.商机额销售额均含税 | K38: √ | L38: √ | N38: √ | O38: √ | P38: √ | Q38: √ | R38: √ | S38: √ | T38: √ | W38: % | X38: 日/周/月/季/年 | Y38: 一位小数点 | Z38: SCRM/CRM | AA38: ★★ | AB38: 内部管理 | AD38: 总裁/副总裁 | AF38: 陈亚婕 | AG38: =VLOOKUP(G38,'指标体系-企服'!G:G,1,0)=G38 -> TRUE | AI38: =AI37 -> 业务拓展
A39: 营销 | B39: 强化业务拓展跟进 | D39: 业务拓展分析 | E39: 商机分析 | F39: 核心指标 | G39: 商机转化率 | H39: 商机转化为订单的比例 | I39: 订单转化率金额 | J39: 1.营销平台 2.商机额销售额均含税 | K39: √ | L39: √ | N39: √ | O39: √ | P39: √ | Q39: √ | R39: √ | S39: √ | T39: √ | W39: % | X39: 日/周/月/季/年 | Y39: 一位小数点 | Z39: SCRM/CRM | AA39: ★★★ | AB39: 内部管理 | AD39: 总裁/副总裁 | AF39: 陈亚婕 | AG39: =VLOOKUP(G39,'指标体系-企服'!G:G,1,0)=G39 -> TRUE | AI39: =AI38 -> 业务拓展
A40: 营销 | B40: 强化业务拓展跟进 | D40: 业务拓展分析 | E40: 接单分析 | F40: 核心指标 | G40: 商机转化率 | H40: 订单转收入的比例 | I40: 收入转化率/金额 | J40: 1.营销平台 2.商机额销售额均含税 | K40: √ | L40: √ | N40: √ | R40: √ | S40: √ | T40: √ | V40: √ | W40: % | X40: 日/周/月/季/年 | Y40: 一位小数点 | Z40: SCRM/CRM | AA40: ★★★ | AB40: 内部管理 | AD40: 总裁/副总裁 | AF40: 陈亚婕 | AG40: =VLOOKUP(G40,'指标体系-企服'!G:G,1,0)=G40 -> TRUE | AI40: =AI39 -> 业务拓展
A41: 营销 | B41: 强化业务拓展跟进 | D41: 业务拓展分析 | E41: 样机分析 | F41: 一级指标 | G41: 样机转销率 | H41: 样机转销量占申请比例 | I41: 样机转销量/样机申请量 | J41: BG、分BU | K41: √ | L41: √ | N41: √ | O41: √ | P41: √ | Q41: √ | R41: √ | S41: √ | T41: √ | W41: % | X41: 日/周/月/季/年 | Y41: 一位小数点 | Z41: CRM | AA41: ★★★ | AB41: 内部管理 | AD41: 部门/BU负责人 | AF41: 郭梓樱 | AG41: =VLOOKUP(G41,'指标体系-企服'!G:G,1,0)=G41 -> TRUE | AH41: 否 | AI41: =AI40 -> 业务拓展
A42: 营销 | B42: 强化业务拓展跟进 | D42: 业务拓展分析 | E42: 样机分析 | F42: 一级指标 | G42: 样机在外量 | H42: 样机未处理数量 | I42: 样机未处理数量 | J42: BG、分BU | K42: √ | L42: √ | N42: √ | O42: √ | P42: √ | Q42: √ | R42: √ | S42: √ | T42: √ | W42: 台 | X42: 日/周/月/季/年 | Y42: 无小数点 | Z42: CRM | AA42: ★★★ | AB42: 内部管理 | AD42: 部门/BU负责人 | AF42: 郭梓樱 | AG42: =VLOOKUP(G42,'指标体系-企服'!G:G,1,0)=G42 -> TRUE | AH42: 否 | AI42: =AI41 -> 业务拓展
A43: 营销 | B43: 强化业务拓展跟进 | D43: 业务拓展分析 | E43: 样机分析 | F43: 一级指标 | G43: 样机逾期率 | H43: 样机逾期量占在外量比例 | I43: 样机逾期量/样机在外量 | J43: BG、分BU | K43: √ | L43: √ | N43: √ | O43: √ | P43: √ | Q43: √ | R43: √ | S43: √ | T43: √ | W43: % | X43: 日/周/月/季/年 | Y43: 一位小数点 | Z43: CRM | AA43: ★★★ | AB43: 内部管理 | AD43: 部门/BU负责人 | AF43: 郭梓樱 | AG43: =VLOOKUP(G43,'指标体系-企服'!G:G,1,0)=G43 -> TRUE | AH43: 否 | AI43: =AI42 -> 业务拓展
A44: 营销 | B44: 强化业务拓展跟进 | D44: 业务拓展分析 | E44: 线索分析 | F44: 一级指标 | G44: 线索有效率 | H44: 有效线索数量占总线索数量比例 | I44: 有效线索量/总线索量 | J44: BG、分线上线下 | K44: √ | L44: √ | N44: √ | R44: √ | T44: √ | V44: √ | W44: % | X44: 日/周/月/季/年 | Y44: 一位小数点 | Z44: SCRM | AA44: ★★ | AB44: 内部管理 | AD44: 部门/BU负责人 | AF44: 陈亚婕 | AG44: =VLOOKUP(G44,'指标体系-企服'!G:G,1,0)=G44 -> TRUE | AH44: 否 | AI44: =AI43 -> 业务拓展
A45: 营销 | B45: 强化业务拓展跟进 | D45: 业务拓展分析 | E45: 线索分析 | F45: 一级指标 | G45: 线索及时率 | H45: 及时处理线索数量占总线索数量比例 | I45: 及时线索量/总线索量 | J45: BG、分线上线下 | K45: √ | L45: √ | N45: √ | R45: √ | T45: √ | V45: √ | W45: % | X45: 日/周/月/季/年 | Y45: 一位小数点 | Z45: SCRM | AA45: ★★ | AB45: 内部管理 | AD45: 部门/BU负责人 | AF45: 陈亚婕 | AG45: =VLOOKUP(G45,'指标体系-企服'!G:G,1,0)=G45 -> TRUE | AH45: 否 | AI45: =AI44 -> 业务拓展
A46: 营销 | B46: 强化业务拓展跟进 | D46: 业务拓展分析 | E46: 接单分析 | F46: 一级指标 | G46: 接单收入 | H46: 订单数量/金额/单平均 | J46: BG、分BU | K46: √ | L46: √ | N46: √ | O46: √ | P46: √ | Q46: √ | R46: √ | S46: √ | T46: √ | V46: √ | W46: % | X46: 日/周/月/季/年 | Y46: 一位小数点 | Z46: SCRM/CRM | AA46: ★★★ | AB46: 内部管理 | AD46: 总裁/副总裁 | AF46: 陈亚婕 | AG46: 否 | AI46: =AI45 -> 业务拓展
A47: 营销 | B47: 强化业务拓展跟进 | D47: 业务拓展分析 | E47: 接单分析 | F47: 一级指标 | G47: 订单未出货 | H47: 订单未出货 | I47: 已接单未出货分时段 | J47: BG、分BU | K47: √ | L47: √ | N47: √ | O47: √ | P47: √ | Q47: √ | R47: √ | S47: √ | T47: √ | V47: √ | W47: % | X47: 日/周/月/季/年 | Y47: 一位小数点 | Z47: SCRM/CRM | AA47: ★★★ | AB47: 内部管理 | AD47: 总裁/副总裁 | AF47: 陈亚婕 | AG47: 否 | AI47: =AI46 -> 业务拓展
A48: 营销 | B48: 强化业务拓展跟进 | D48: 业务拓展分析 | E48: 签约分析 | F48: 二级指标 | G48: 签约达成率 | H48: 完成签约数量目标的比例 | I48: 签约数量/签约数量目标 | J48: 渠道平台、分区域、分办事处 | K48: √ | L48: √ | N48: √ | O48: √ | P48: √ | Q48: √ | R48: √ | S48: √ | T48: √ | W48: % | X48: 日/周/月/季/年 | Y48: 一位小数点 | Z48: SCRM/导入 | AA48: ★★ | AB48: 内部管理 | AD48: 区域/办事处负责人 | AF48: 陈亚婕 | AG48: =VLOOKUP(G48,'指标体系-企服'!G:G,1,0)=G48 -> TRUE | AI48: =AI47 -> 业务拓展
A49: 营销 | B49: 强化业务拓展跟进 | D49: 业务拓展分析 | E49: 商机分析 | F49: 二级指标 | G49: 商机转化率 | H49: 线索转化为商机的比例 | I49: 线索中标量/金额 | J49: 1.营销平台 2.商机额销售额均含税 | K49: √ | L49: √ | N49: √ | O49: √ | P49: √ | Q49: √ | R49: √ | S49: √ | T49: √ | W49: % | X49: 日/周/月/季/年 | Y49: 一位小数点 | Z49: SCRM/CRM | AA49: ★★★ | AB49: 内部管理 | AD49: 总裁/副总裁 | AF49: 陈亚婕 | AG49: =VLOOKUP(G49,'指标体系-企服'!G:G,1,0)=G49 -> TRUE | AI49: =AI48 -> 业务拓展
A50: 营销 | B50: 强化业务拓展跟进 | D50: 业务拓展分析 | E50: 商机分析 | F50: 二级指标 | G50: 商机转化率 | H50: 商机转化为订单的比例 | I50: 订单转化率金额 | J50: 1.营销平台 2.商机额销售额均含税 | K50: √ | L50: √ | N50: √ | O50: √ | P50: √ | Q50: √ | R50: √ | S50: √ | T50: √ | W50: % | X50: 日/周/月/季/年 | Y50: 一位小数点 | Z50: SCRM/CRM | AA50: ★★★ | AB50: 内部管理 | AD50: 总裁/副总裁 | AF50: 陈亚婕 | AG50: =VLOOKUP(G50,'指标体系-企服'!G:G,1,0)=G50 -> TRUE | AI50: =AI49 -> 业务拓展
A51: 营销 | B51: 强化业务拓展跟进 | D51: 业务拓展分析 | E51: 接单分析 | F51: 二级指标 | G51: 商机转化率 | H51: 订单转收入的比例 | I51: 收入转化率/金额 | J51: 1.营销平台 2.商机额销售额均含税 | K51: √ | L51: √ | N51: √ | R51: √ | S51: √ | T51: √ | W51: % | X51: 日/周/月/季/年 | Y51: 一位小数点 | Z51: SCRM/CRM | AA51: ★★★ | AB51: 内部管理 | AD51: 总裁/副总裁 | AF51: 陈亚婕 | AG51: =VLOOKUP(G51,'指标体系-企服'!G:G,1,0)=G51 -> TRUE | AI51: =AI50 -> 业务拓展
A52: 营销 | B52: 强化业务拓展跟进 | D52: 业务拓展分析 | E52: 样机分析 | F52: 二级指标 | G52: 样机转销率 | H52: 样机转销量占申请比例 | I52: 样机转销量/样机申请量 | J52: BG、分BU、分区域、分办事处 | K52: √ | L52: √ | N52: √ | O52: √ | P52: √ | Q52: √ | R52: √ | S52: √ | T52: √ | W52: % | X52: 日/周/月/季/年 | Y52: 一位小数点 | Z52: CRM | AA52: ★★★ | AB52: 内部管理 | AD52: 区域/办事处负责人 | AF52: 郭梓樱 | AG52: =VLOOKUP(G52,'指标体系-企服'!G:G,1,0)=G52 -> TRUE | AI52: =AI51 -> 业务拓展
A53: 营销 | B53: 强化业务拓展跟进 | D53: 业务拓展分析 | E53: 样机分析 | F53: 二级指标 | G53: 样机在外量 | H53: 样机未处理数量 | I53: 样机未处理数量 | J53: BG、分BU、分区域、分办事处 | K53: √ | L53: √ | N53: √ | O53: √ | P53: √ | Q53: √ | R53: √ | S53: √ | T53: √ | W53: 台 | X53: 日/周/月/季/年 | Y53: 无小数点 | Z53: CRM | AA53: ★★★ | AB53: 内部管理 | AD53: 区域/办事处负责人 | AF53: 郭梓樱 | AG53: =VLOOKUP(G53,'指标体系-企服'!G:G,1,0)=G53 -> TRUE | AI53: =AI52 -> 业务拓展
A54: 营销 | B54: 强化业务拓展跟进 | D54: 业务拓展分析 | E54: 样机分析 | F54: 二级指标 | G54: 样机逾期率 | H54: 样机逾期量占在外量比例 | I54: 样机逾期量/样机在外量 | J54: BG、分BU、分区域、分办事处 | K54: √ | L54: √ | N54: √ | O54: √ | P54: √ | Q54: √ | R54: √ | S54: √ | T54: √ | W54: % | X54: 日/周/月/季/年 | Y54: 一位小数点 | Z54: CRM | AA54: ★★★ | AB54: 内部管理 | AD54: 区域/办事处负责人 | AF54: 郭梓樱 | AG54: =VLOOKUP(G54,'指标体系-企服'!G:G,1,0)=G54 -> TRUE | AI54: =AI53 -> 业务拓展
A55: 营销 | B55: 强化业务拓展跟进 | D55: 业务拓展分析 | E55: 线索分析 | F55: 二级指标 | G55: 线索有效率 | H55: 有效线索数量占总线索数量比例 | I55: 有效线索量/总线索量 | J55: BG、分线上线下、分区域、分办事处 | K55: √ | L55: √ | N55: √ | O55: √ | P55: √ | Q55: √ | R55: √ | S55: √ | T55: √ | V55: √ | W55: % | X55: 日/周/月/季/年 | Y55: 一位小数点 | Z55: SCRM | AA55: ★★ | AB55: 内部管理 | AD55: 区域/办事处负责人 | AF55: 陈亚婕 | AG55: =VLOOKUP(G55,'指标体系-企服'!G:G,1,0)=G55 -> TRUE | AI55: =AI54 -> 业务拓展
A56: 营销 | B56: 强化业务拓展跟进 | D56: 业务拓展分析 | E56: 线索分析 | F56: 二级指标 | G56: 线索及时率 | H56: 及时处理线索数量占总线索数量比例 | I56: 及时线索量/总线索量 | J56: BG、分线上线下、分区域、分办事处 | K56: √ | L56: √ | M56: √ | R56: √ | T56: √ | V56: √ | W56: % | X56: 日/周/月/季/年 | Y56: 一位小数点 | Z56: SCRM | AA56: ★★ | AB56: 内部管理 | AD56: 区域/办事处负责人 | AF56: 陈亚婕 | AG56: =VLOOKUP(G56,'指标体系-企服'!G:G,1,0)=G56 -> TRUE | AI56: =AI55 -> 业务拓展
A57: 营销 | B57: 强化业务拓展跟进 | D57: 业务拓展分析 | E57: 接单分析 | F57: 二级指标 | G57: 接单收入 | H57: 订单数量/金额/单平均 | J57: BG、分BU、分区域、分办事处 | K57: √ | L57: √ | N57: √ | O57: √ | P57: √ | Q57: √ | R57: √ | S57: √ | T57: √ | V57: √ | W57: % | X57: 日/周/月/季/年 | Y57: 一位小数点 | Z57: SCRM/CRM | AA57: ★★★ | AB57: 内部管理 | AD57: 总裁/副总裁 | AF57: 陈亚婕 | AG57: 否 | AI57: =AI56 -> 业务拓展
A58: 营销 | B58: 强化业务拓展跟进 | D58: 业务拓展分析 | E58: 接单分析 | F58: 二级指标 | G58: 订单未出货 | H58: 订单未出货 | I58: 已接单未出货分时段 | J58: BG、分BU、分区域、分办事处 | K58: √ | L58: √ | N58: √ | O58: √ | P58: √ | Q58: √ | R58: √ | S58: √ | T58: √ | V58: √ | W58: % | X58: 日/周/月/季/年 | Y58: 一位小数点 | Z58: SCRM/CRM | AA58: ★★★ | AB58: 内部管理 | AD58: 总裁/副总裁 | AF58: 陈亚婕 | AG58: 否 | AI58: =AI57 -> 业务拓展
B59: 3.运营效率提升
A60: 营销 | B60: 提升运营效率 | D60: 运营效率分析 | E60: 库存周转分析 | F60: 核心指标 | G60: 库存周转天数 | I60: 营业成本/平均库存 | J60: BG | K60: √ | L60: √ | N60: √ | O60: √ | P60: √ | Q60: √ | R60: √ | S60: √ | T60: √ | W60: % | X60: 日 | Y60: 一位小数点 | Z60: EBS/EDS | AA60: ★★★ | AB60: 内部管理 | AD60: 总裁/副总裁 | AF60: 郭梓樱 | AG60: =VLOOKUP(G60,'指标体系-企服'!G:G,1,0)=G60 -> TRUE | AH60: 否 | AI60: 运营效率提升
A61: 营销 | B61: 提升运营效率 | D61: 运营效率分析 | E61: 库存周转分析 | F61: 核心指标 | G61: 库存量（整机）、库存金额 | J61: BG(分子库、可发货、良与不良） | K61: √ | L61: √ | N61: √ | O61: √ | P61: √ | Q61: √ | R61: √ | S61: √ | T61: √ | X61: 日 | Y61: 无小数点 | Z61: EBS | AA61: ★★★ | AB61: 内部管理 | AD61: 总裁/副总裁 | AF61: 郭梓樱 | AG61: 否 | AH61: 否 | AI61: =AI60 -> 运营效率提升
A62: 营销 | B62: 提升运营效率 | D62: 运营效率分析 | E62: 库存周转分析 | F62: 核心指标 | G62: 超期库存占比 | I62: 2个月以上库存/库存金额 | J62: BG | K62: √ | L62: √ | N62: √ | O62: √ | P62: √ | Q62: √ | R62: √ | S62: √ | T62: √ | W62: % | X62: 日 | Y62: 一位小数点 | Z62: EBS | AA62: ★★★ | AB62: 内部管理 | AD62: 总裁/副总裁 | AF62: 郭梓樱 | AG62: =VLOOKUP(G62,'指标体系-企服'!G:G,1,0)=G62 -> TRUE | AH62: 否 | AI62: =AI61 -> 运营效率提升
A63: 营销 | B63: 提升运营效率 | D63: 运营效率分析 | E63: 分仓效率分析 | F63: 一级指标 | G63: 分仓出货占比 | J63: BG、分BU | K63: √ | L63: √ | N63: √ | O63: √ | P63: √ | Q63: √ | W63: % | Y63: 一位小数点 | AA63: ★★ | AB63: 内部管理 | AD63: 部门/BU负责人 | AF63: 郭梓樱 | AG63: =VLOOKUP(G63,'指标体系-企服'!G:G,1,0)=G63 -> TRUE | AH63: 否 | AI63: =AI62 -> 运营效率提升
A64: 营销 | B64: 提升运营效率 | D64: 运营效率分析 | E64: 库存周转分析 | F64: 一级指标 | G64: 库存量（整机）、库存金额 | J64: BG、分BU | K64: √ | L64: √ | N64: √ | O64: √ | P64: √ | Q64: √ | W64: % | Y64: 一位小数点 | AA64: ★★★ | AB64: 内部管理 | AD64: 部门/BU负责人 | AF64: 郭梓樱 | AG64: 否 | AI64: =AI63 -> 运营效率提升
A65: 营销 | B65: 提升运营效率 | D65: 运营效率分析 | E65: 库存周转分析 | F65: 一级指标 | G65: 超期库存占比 | I65: 2个月以上库存/库存金额 | J65: BG、分BU | K65: √ | L65: √ | N65: √ | O65: √ | P65: √ | Q65: √ | R65: √ | S65: √ | T65: √ | W65: % | X65: 日 | Y65: 一位小数点 | Z65: EBS | AA65: ★★★ | AB65: 内部管理 | AD65: 总裁/副总裁 | AF65: 郭梓樱 | AG65: =VLOOKUP(G65,'指标体系-企服'!G:G,1,0)=G65 -> TRUE | AI65: =AI64 -> 运营效率提升
A66: 营销 | B66: 提升运营效率 | D66: 运营效率分析 | E66: 库存周转分析 | F66: 一级指标 | G66: 库存周转天数 | I66: 营业成本/平均库存 | J66: BG、分BU | K66: √ | L66: √ | N66: √ | O66: √ | P66: √ | Q66: √ | W66: % | Y66: 一位小数点 | AA66: ★★★ | AB66: 内部管理 | AD66: 部门/BU负责人 | AF66: 郭梓樱 | AG66: =VLOOKUP(G66,'指标体系-企服'!G:G,1,0)=G66 -> TRUE | AI66: =AI65 -> 运营效率提升
A67: 营销 | B67: 提升运营效率 | D67: 运营效率分析 | E67: 分仓效率分析 | F67: 二级指标 | G67: 分仓出货占比 | J67: BG、分线上线下、分区域、分办事处 | K67: √ | L67: √ | N67: √ | O67: √ | P67: √ | Q67: √ | W67: % | Y67: 一位小数点 | AA67: ★★ | AB67: 内部管理 | AD67: 区域/办事处负责人 | AF67: 郭梓樱 | AG67: =VLOOKUP(G67,'指标体系-企服'!G:G,1,0)=G67 -> TRUE | AI67: =AI66 -> 运营效率提升
B68: 4.客户提升
A69: 营销 | B69: 提升经销商能力及效率 | D69: 经销商分析 | E69: 渠道结构分析 | F69: 核心指标 | G69: 渠道核心占比 | J69: 教培事业部 | K69: √ | L69: √ | P69: √ | Q69: √ | R69: √ | S69: √ | T69: √ | W69: % | Y69: 一位小数点 | AA69: ★★ | AB69: 内部管理 | AD69: 总裁/副总裁 | AF69: 陈亚婕 | AG69: =VLOOKUP(G69,'指标体系-企服'!G:G,1,0)=G69 -> TRUE | AH69: 否 | AI69: 客户提升
A70: 营销 | B70: 提升经销商能力及效率 | D70: 经销商分析 | E70: 渠道结构分析 | F70: 核心指标 | G70: 渠道分销率 | J70: 教培事业部 | K70: √ | L70: √ | P70: √ | Q70: √ | R70: √ | S70: √ | T70: √ | W70: % | Y70: 一位小数点 | AA70: ★★ | AB70: 内部管理 | AD70: 总裁/副总裁 | AF70: 陈亚婕 | AG70: =VLOOKUP(G70,'指标体系-企服'!G:G,1,0)=G70 -> TRUE | AH70: 否 | AI70: =AI69 -> 客户提升
A71: 营销 | B71: 提升经销商能力及效率 | D71: 经销商分析 | E71: 库存分析 | F71: 核心指标 | G71: 核心库存量 | J71: 教培事业部 | K71: √ | L71: √ | P71: √ | Q71: √ | R71: √ | S71: √ | T71: √ | W71: 台 | Y71: 无小数点 | AA71: ★★ | AD71: 部门/BU负责人 | AF71: 陈亚婕 | AG71: =VLOOKUP(G71,'指标体系-企服'!G:G,1,0)=G71 -> TRUE | AH71: 否 | AI71: =AI70 -> 客户提升
A72: 营销 | B72: 提升经销商能力及效率 | D72: 经销商分析 | E72: 库存分析 | F72: 核心指标 | G72: 核心库存周转天数 | J72: 教培事业部 | K72: √ | L72: √ | P72: √ | Q72: √ | R72: √ | S72: √ | T72: √ | W72: 天 | Y72: 无小数点 | AA72: ★★ | AB72: 内部管理 | AD72: 总裁/副总裁 | AF72: 陈亚婕 | AG72: =VLOOKUP(G72,'指标体系-企服'!G:G,1,0)=G72 -> TRUE | AH72: 否 | AI72: =AI71 -> 客户提升
A73: 营销 | B73: 提升经销商能力及效率 | D73: 经销商分析 | E73: 渠道结构分析 | F73: 一级指标 | G73: 渠道核心占比 | J73: 教培事业部 | K73: √ | L73: √ | P73: √ | Q73: √ | R73: √ | S73: √ | T73: √ | W73: % | Y73: 一位小数点 | AA73: ★★ | AB73: 内部管理 | AD73: 部门/BU负责人 | AF73: 陈亚婕 | AG73: =VLOOKUP(G73,'指标体系-企服'!G:G,1,0)=G73 -> TRUE | AI73: =AI72 -> 客户提升
A74: 营销 | B74: 提升经销商能力及效率 | D74: 经销商分析 | E74: 渠道结构分析 | F74: 一级指标 | G74: 渠道分销率 | J74: 教培事业部 | K74: √ | L74: √ | P74: √ | Q74: √ | R74: √ | S74: √ | T74: √ | W74: % | Y74: 一位小数点 | AA74: ★★ | AD74: 部门/BU负责人 | AF74: 陈亚婕 | AG74: =VLOOKUP(G74,'指标体系-企服'!G:G,1,0)=G74 -> TRUE | AI74: =AI73 -> 客户提升
A75: 营销 | B75: 提升经销商能力及效率 | D75: 经销商分析 | E75: 库存分析 | F75: 一级指标 | G75: 核心库存量 | J75: 教培事业部 | K75: √ | L75: √ | P75: √ | Q75: √ | R75: √ | S75: √ | T75: √ | W75: 台 | Y75: 无小数点 | AA75: ★★ | AD75: 部门/BU负责人 | AF75: 陈亚婕 | AG75: =VLOOKUP(G75,'指标体系-企服'!G:G,1,0)=G75 -> TRUE | AI75: =AI74 -> 客户提升
A76: 营销 | B76: 提升经销商能力及效率 | D76: 经销商分析 | E76: 库存分析 | F76: 一级指标 | G76: 核心库存周转天数 | J76: 教培事业部 | K76: √ | L76: √ | P76: √ | Q76: √ | R76: √ | S76: √ | T76: √ | W76: 万元 | Y76: 无小数点 | AA76: ★★ | AD76: 部门/BU负责人 | AF76: 陈亚婕 | AG76: =VLOOKUP(G76,'指标体系-企服'!G:G,1,0)=G76 -> TRUE | AI76: =AI75 -> 客户提升
A77: 营销 | B77: 提升经销商能力及效率 | D77: 经销商分析 | E77: 渠道结构分析 | F77: 二级指标 | G77: 渠道核心占比 | J77: 教培事业部 | K77: √ | L77: √ | P77: √ | Q77: √ | R77: √ | S77: √ | T77: √ | W77: % | Y77: 一位小数点 | AA77: ★★ | AB77: 内部管理 | AD77: 区域/办事处负责人 | AF77: 陈亚婕 | AG77: =VLOOKUP(G77,'指标体系-企服'!G:G,1,0)=G77 -> TRUE | AI77: =AI76 -> 客户提升
A78: 营销 | B78: 提升经销商能力及效率 | D78: 经销商分析 | E78: 渠道结构分析 | F78: 二级指标 | G78: 渠道分销率 | J78: 教培事业部 | K78: √ | L78: √ | P78: √ | Q78: √ | R78: √ | S78: √ | T78: √ | W78: % | Y78: 一位小数点 | AA78: ★★ | AD78: 区域/办事处负责人 | AF78: 陈亚婕 | AG78: =VLOOKUP(G78,'指标体系-企服'!G:G,1,0)=G78 -> TRUE | AI78: =AI77 -> 客户提升
B79: 5.组织能力提升
A80: 营销 | B80: 提升BG人效 | D80: 人效分析 | E80: 人员效率分析 | F80: 核心指标 | G80: 人均收入 | I80: 营业收入/平均人数 | J80: BG | K80: √ | L80: √ | N80: √ | R80: √ | T80: √ | W80: 万元 | Y80: 无小数点 | AA80: ★★★ | AB80: 内部管理 | AD80: 总裁/副总裁 | AF80: 郭梓樱 | AG80: 否 | AH80: 否 | AI80: 组织能力提升
A81: 营销 | B81: 提升BG人效 | D81: 人效分析 | E81: 人员效率分析 | F81: 一级指标 | G81: 人均人力成本 | I81: 人力成本/平均人数 | J81: BG | K81: √ | L81: √ | N81: √ | R81: √ | T81: √ | W81: 万元 | Y81: 无小数点 | AA81: ★★★ | AB81: 内部管理 | AD81: 部门/BU负责人 | AF81: 郭梓樱 | AG81: 否 | AH81: 否 | AI81: =AI80 -> 组织能力提升
A82: 营销 | B82: 提升BG人效 | D82: 人效分析 | E82: 人员效率分析 | F82: 核心指标 | G82: 人均利润 | I82: 净利润/人均人数 | J82: BG | K82: √ | L82: √ | N82: √ | R82: √ | T82: √ | W82: 万元 | Y82: 无小数点 | AA82: ★★★ | AB82: 内部管理 | AD82: 总裁/副总裁 | AF82: 郭梓樱 | AG82: 否 | AH82: 否 | AI82: =AI81 -> 组织能力提升
A83: 营销 | B83: 提升营销人效 | D83: 人效分析 | E83: 人员效率分析 | F83: 一级指标 | G83: 营销人均收入 | I83: 营业收入/平均人数 | J83: BG、分BU | K83: √ | L83: √ | N83: √ | R83: √ | T83: √ | W83: 万元 | Y83: 无小数点 | AA83: ★★ | AB83: 内部管理 | AD83: 部门/BU负责人 | AF83: 郭梓樱 | AG83: =VLOOKUP(G83,'指标体系-企服'!G:G,1,0)=G83 -> TRUE | AH83: 否 | AI83: =AI82 -> 组织能力提升
A84: 营销 | B84: 提升营销人效 | D84: 人效分析 | E84: 人员效率分析 | F84: 一级指标 | G84: 营销人均利润 | I84: 净利润/人均人数 | J84: BG、分BU | K84: √ | L84: √ | N84: √ | R84: √ | T84: √ | W84: 万元 | Y84: 无小数点 | AA84: ★★ | AB84: 内部管理 | AD84: 部门/BU负责人 | AF84: 郭梓樱 | AG84: =VLOOKUP(G84,'指标体系-企服'!G:G,1,0)=G84 -> TRUE | AH84: 否 | AI84: =AI83 -> 组织能力提升
A85: 营销 | B85: 提升营销人效 | D85: 人效分析 | E85: 人员效率分析 | F85: 一级指标 | G85: 营销人均人力成本 | I85: 人力成本/平均人数 | J85: BG、分BU | K85: √ | L85: √ | N85: √ | R85: √ | T85: √ | W85: 万元 | Y85: 无小数点 | AA85: ★★ | AB85: 内部管理 | AD85: 部门/BU负责人 | AF85: 郭梓樱 | AG85: =VLOOKUP(G85,'指标体系-企服'!G:G,1,0)=G85 -> TRUE | AH85: 否 | AI85: =AI84 -> 组织能力提升
A86: 营销 | B86: 提升营销人效 | D86: 人效分析 | E86: 人员效率分析 | F86: 一级指标 | G86: 营销人均招待费 | I86: 招待费/平均人数 | J86: BG、分BU | K86: √ | L86: √ | N86: √ | R86: √ | T86: √ | W86: 万元 | Y86: 无小数点 | AA86: ★★ | AB86: 内部管理 | AD86: 部门/BU负责人 | AF86: 郭梓樱 | AG86: =VLOOKUP(G86,'指标体系-企服'!G:G,1,0)=G86 -> TRUE | AH86: 否 | AI86: =AI85 -> 组织能力提升
A87: 营销 | B87: 提升营销人效 | D87: 人效分析 | E87: 人员效率分析 | F87: 一级指标 | G87: 营销人均差旅费 | I87: 差旅费/平均人数 | J87: BG、分BU | K87: √ | L87: √ | N87: √ | R87: √ | T87: √ | W87: 万元 | Y87: 无小数点 | AA87: ★★ | AB87: 内部管理 | AD87: 部门/BU负责人 | AF87: 郭梓樱 | AG87: =VLOOKUP(G87,'指标体系-企服'!G:G,1,0)=G87 -> TRUE | AH87: 否 | AI87: =AI86 -> 组织能力提升
A88: 营销 | B88: 提升营销人效 | D88: 人效分析 | E88: 人员效率分析 | F88: 二级指标 | G88: 营销人均收入 | I88: 营业收入/平均人数 | J88: 1.BG、分BU、分区域、分办事处、分人员 2.销售额即IN-销售额，含税 | K88: √ | L88: √ | N88: √ | R88: √ | T88: √ | W88: 万元 | Y88: 无小数点 | AA88: ★★ | AB88: 内部管理 | AD88: 区域/办事处负责人 | AF88: 郭梓樱 | AG88: =VLOOKUP(G88,'指标体系-企服'!G:G,1,0)=G88 -> TRUE | AI88: =AI87 -> 组织能力提升
A89: 营销 | B89: 提升营销人效 | D89: 人效分析 | E89: 人员效率分析 | F89: 二级指标 | G89: 营销人均利润 | I89: 净利润/人均人数 | J89: 1.BG、分BU、分区域、分办事处、分人员 2.销售额即IN-销售额，含税 | K89: √ | L89: √ | N89: √ | R89: √ | T89: √ | W89: 万元 | Y89: 无小数点 | AA89: ★★ | AB89: 内部管理 | AD89: 区域/办事处负责人 | AF89: 郭梓樱 | AG89: =VLOOKUP(G89,'指标体系-企服'!G:G,1,0)=G89 -> TRUE | AI89: =AI88 -> 组织能力提升
A90: 营销 | B90: 提升营销人效 | D90: 人效分析 | E90: 人员效率分析 | F90: 二级指标 | G90: 营销人均人力成本 | I90: 人力成本/平均人数 | J90: 1.BG、分BU、分区域、分办事处、分人员 2.销售额即IN-销售额，含税 | K90: √ | L90: √ | N90: √ | R90: √ | T90: √ | W90: 万元 | Y90: 无小数点 | AA90: ★★ | AB90: 内部管理 | AD90: 区域/办事处负责人 | AF90: 郭梓樱 | AG90: =VLOOKUP(G90,'指标体系-企服'!G:G,1,0)=G90 -> TRUE | AI90: =AI89 -> 组织能力提升
A91: 营销 | B91: 提升营销人效 | D91: 人效分析 | E91: 人员效率分析 | F91: 二级指标 | G91: 营销人均招待费 | I91: 招待费/平均人数 | J91: 1.BG、分BU、分区域、分办事处、分人员 2.销售额即IN-销售额，含税 | K91: √ | L91: √ | N91: √ | R91: √ | T91: √ | W91: 万元 | Y91: 无小数点 | AA91: ★★ | AB91: 内部管理 | AD91: 区域/办事处负责人 | AF91: 郭梓樱 | AG91: =VLOOKUP(G91,'指标体系-企服'!G:G,1,0)=G91 -> TRUE | AI91: =AI90 -> 组织能力提升
A92: 营销 | B92: 提升营销人效 | D92: 人效分析 | E92: 人员效率分析 | F92: 二级指标 | G92: 营销人均差旅费 | I92: 差旅费/平均人数 | J92: 1.BG、分BU、分区域、分办事处、分人员 2.销售额即IN-销售额，含税 | K92: √ | L92: √ | N92: √ | R92: √ | T92: √ | W92: 万元 | Y92: 无小数点 | AA92: ★★ | AB92: 内部管理 | AD92: 区域/办事处负责人 | AF92: 郭梓樱 | AG92: =VLOOKUP(G92,'指标体系-企服'!G:G,1,0)=G92 -> TRUE | AI92: =AI91 -> 组织能力提升
A93: 营销 | B93: 提升营销人效 | D93: 人效分析 | E93: 人员效率分析 | F93: 二级指标 | G93: 营销人均差旅费投入产出 | I93: 差旅费用/营业收入 | J93: 1.BG、分BU、分区域、分办事处、分人员 2.销售额即IN-销售额，含税 | K93: √ | L93: √ | N93: √ | R93: √ | T93: √ | W93: % | Y93: 一位小数点 | AA93: ★★ | AF93: 郭梓樱 | AG93: 否 | AH93: 否 | AI93: =AI92 -> 组织能力提升
A94: 营销 | B94: 提升营销人效 | D94: 人效分析 | E94: 人员效率分析 | F94: 二级指标 | G94: 营销人均招待投入产出 | I94: 招待费/营业收入 | J94: 1.BG、分BU、分区域、分办事处、分人员 2.销售额即IN-销售额，含税 | K94: √ | L94: √ | N94: √ | R94: √ | T94: √ | W94: % | Y94: 一位小数点 | AA94: ★★ | AB94: 内部管理 | AD94: 区域/办事处负责人 | AF94: 郭梓樱 | AG94: 否 | AH94: 否 | AI94: =AI93 -> 组织能力提升
A95: 营销 | B95: 提升营销人效 | D95: 人效分析 | E95: 职级分析 | F95: 核心指标 | G95: 总人数 | J95: BG | K95: √ | L95: √ | N95: √ | R95: √ | T95: √ | W95: 人 | Y95: 无小数点 | AA95: ★★ | AB95: 内部管理 | AD95: 总裁/副总裁 | AF95: 郭梓樱 | AG95: =VLOOKUP(G95,'指标体系-企服'!G:G,1,0)=G95 -> TRUE | AH95: 否 | AI95: =AI94 -> 组织能力提升
A96: 营销 | B96: 提升营销人效 | D96: 人效分析 | E96: 职级分析 | F96: 核心指标 | G96: 营销人数 | J96: BG | K96: √ | L96: √ | N96: √ | R96: √ | T96: √ | W96: 人 | Y96: 无小数点 | AA96: ★★ | AB96: 内部管理 | AD96: 总裁/副总裁 | AF96: 郭梓樱 | AG96: =VLOOKUP(G96,'指标体系-企服'!G:G,1,0)=G96 -> TRUE | AH96: 否 | AI96: =AI95 -> 组织能力提升
A97: 营销 | B97: 提升营销人效 | D97: 人效分析 | E97: 职级分析 | F97: 核心指标 | G97: 营销人数占比 | J97: BG | K97: √ | L97: √ | N97: √ | R97: √ | T97: √ | W97: % | Y97: 一位小数点 | AA97: ★★ | AB97: 内部管理 | AD97: 总裁/副总裁 | AF97: 郭梓樱 | AG97: =VLOOKUP(G97,'指标体系-企服'!G:G,1,0)=G97 -> TRUE | AH97: 否 | AI97: =AI96 -> 组织能力提升
A98: 营销 | B98: 提升营销人效 | D98: 人效分析 | E98: 职级分析 | F98: 一级指标 | G98: 营销人数 | J98: BG、分BU | K98: √ | L98: √ | N98: √ | R98: √ | T98: √ | W98: 人 | Y98: 无小数点 | AA98: ★ | AB98: 内部管理 | AD98: 部门/BU负责人 | AF98: 郭梓樱 | AG98: =VLOOKUP(G98,'指标体系-企服'!G:G,1,0)=G98 -> TRUE | AI98: =AI97 -> 组织能力提升
A99: 营销 | B99: 提升营销人效 | D99: 人效分析 | E99: 职级分析 | F99: 一级指标 | G99: 营销人数占比 | J99: BG、分BU | K99: √ | L99: √ | N99: √ | R99: √ | T99: √ | W99: % | Y99: 一位小数点 | AA99: ★ | AB99: 内部管理 | AD99: 部门/BU负责人 | AF99: 郭梓樱 | AG99: =VLOOKUP(G99,'指标体系-企服'!G:G,1,0)=G99 -> TRUE | AI99: =AI98 -> 组织能力提升
A100: 营销 | B100: 提升营销人效 | D100: 人效分析 | E100: 职级分析 | F100: 一级指标 | G100: 营销人数同比增长率 | J100: BG、分BU | K100: √ | L100: √ | N100: √ | R100: √ | T100: √ | W100: % | Y100: 一位小数点 | AA100: ★ | AB100: 内部管理 | AD100: 部门/BU负责人 | AF100: 郭梓樱 | AG100: =VLOOKUP(G100,'指标体系-企服'!G:G,1,0)=G100 -> TRUE | AH100: 否 | AI100: =AI99 -> 组织能力提升
...

Sheet 指标体系
B1: 一期 | C1: 部门价值填在此列 | G1: =COUNTA(G3:G588) -> 159 | J1: 统一字段名称并校准 | K1: 在√格中直接补充字段名称和规则，如K5【年份】【月份】 | AH1: 若无参考方法论可不填写
A2: 指标领域 | B2: 核心价值 | C2: 关键驱动因素 | D2: 分析主题域 | E2: 分析主题 | F2: 指标等级 | G2: 指标名称 | H2: 定义 | I2: 公式 | J2: 计算口径 (含数据来源具体字段) | K2: 维度来源-字段名称 | Z2: 度量单位 | AA2: 统计频率 | AB2: 统计精度 | AC2: 数据来源 | AD2: 优先级 | AE2: 指标用途 | AF2: 考核角色 | AG2: 要求角色 | AH2: 对应SCOR模型 | AI2: 合并 | AJ2: 企服 | AK2: 教育 | AO2: 所属BG | AQ2: 上线时间
K3: 期间 | L3: 事业部 | M3: 项目 | N3: 产品型号 | O3: 产品线 | P3: 系列 | Q3: 尺寸 | R3: 区域 | S3: 办事处 | T3: 客户 | U3: 客户分类 | V3: 人员 | W3: 仓位 | X3: 库龄 | Y3: 用途 | AI3: 对接人 | AL3: 是否相同 | AM3: 是否重复 | AN3: 核心价值 | AO3: 教育 | AP3: 企服
B4: 1.营收保障 | AH4: Reliability(可靠性) | AO4: 是 | AP4: 是 | AQ4: 一期
A5: 营销 | B5: 扩大营业收入 | D5: 收入分析 | E5: 营业收入分析 | F5: 核心指标 | G5: 综合毛利率 | H5: 毛利额占收入比例 | I5: 综合毛利额/综合营业收入 | J5: 综合毛利额=综合营业收入-综合营业成本 1、综合营业收入 EDS系统中收入明细成本表， 筛选【冲销标记】不为 'Y'，【交易类型】 包含 ('',‘跨BG内部交易’)的数据，按【业绩所属事业部】列中事业部对应所属BG统计,汇总【订单行折扣后不含税金额】列; 2、综合营业成本 EDS系统中收入明细成本表，筛选【冲销标记】不为 'Y'，【交易类型】 包含 ('',‘跨BG内部交易’)的数据的数据，按【业绩所属事业部】列中事业部对应所属BG统计,汇总【原始合计成本】列 企业服务数据处理特殊规则 1、办事处： 北京办事处且【下单客户】包含“%天津%”，则调整到“天津办事处” 1、期间：【总账日期】+日期维 获取所对应的年\月\季 2、事业部：【产品所属事业部】 3、产品型号：【主销售型号】字段值 4、产品线：【产品型号】+产品型号维 ，获取对应的‘产品线分类’字段值 5、系列：【产品型号】+产品型号维，获取对应的‘产品系列’字段值 6、尺寸：产品型号】+产品型号维，获取对应的‘屏尺寸（英寸）’字段值 7、区域：【销售】+组织架构维，获取对应的区域值 8、办事处：【销售】+组织架构，获取对应的办事处 9、客户：【下单客户】 10、客户分类： 企业服务：【下单客户】+客户维，获取对应对应‘经销商类型’字段值 未来教育：【下单客户】+客户维，获取对应的‘客户分类’字段值 11、人员：【销售】 | K5: √ | L5: √ | N5: √ | O5: √ | P5: √ | Q5: √ | R5: √ | S5: √ | T5: √ | U5: √ | V5: √ | Z5: % | AA5: 月/季/年 | AB5: 两位小数点 | AC5: PBCS | AD5: ★★★ | AE5: 内部管理 | AI5: 潘敏君 | AJ5: 潘敏君 | AK5: 陈亚婕 | AL5: =VLOOKUP(G5,'指标体系-教育'!G:G,1,0)=G5 -> #N/A | AM5: 否 | AN5: 营收保障 | AO5: 是 | AP5: 是 | AQ5: 一期
A6: 营销 | B6: 扩大营业收入 | D6: 收入分析 | E6: 营业收入分析 | F6: 核心指标 | G6: BOM毛利率 | H6: 毛利额占收入比例 | I6: BOM毛利额/BOM营业收入 | J6: BOM毛利额=BOM营业收入-BOM营业成本 1、BOM营业收入 EDS系统中收入明细成本表 筛选【冲销标记】不为 'Y'，【交易类型】列 包含 ('',‘跨BG内部交易’)，【收入分类】=主营业务收入，【数据来源】不包含 (“FIN_ADJ","MAG_ADJ")，【物料编码】不包含"空"&"009"开头&"0"的数据，按【业绩所属事业部】列中事业部对应所属BG统计,汇总【订单行折扣后不含税金额】列; 2、BOM营业成本 EDS系统中收入明细成本表，筛选【冲销标记】不为 'Y'，【交易类型】 包含 ('',‘跨BG内部交易’)的数据，【收入分类】=主营业务收入，【数据来源】不包含 (“FIN_ADJ","MAG_ADJ")，【物料编码】不包含"空"&"009"开头&"0"的数据，，按【业绩所属事业部】列中事业部对应所属BG统计,汇总【原始合计成本】列 | K6: √ | L6: √ | N6: √ | O6: √ | P6: √ | Q6: √ | R6: √ | S6: √ | T6: √ | U6: √ | V6: √ | Z6: % | AA6: 月/季/年 | AB6: 两位小数点 | AC6: PBCS | AD6: ★★★ | AE6: 内部管理 | AI6: 潘敏君 | AJ6: 潘敏君 | AK6: 陈亚婕 | AL6: =VLOOKUP(G6,'指标体系-教育'!G:G,1,0)=G6 -> #N/A | AM6: 否 | AN6: 营收保障 | AP6: 是 | AQ6: 一期
A7: 营销 | B7: 扩大营业收入 | D7: 收入分析 | E7: 营业收入分析 | F7: 核心指标 | G7: 综合毛利率预算偏差率 | H7: 综合毛利率与预算综合毛利率之差 | I7: 综合毛利率 -预算综合毛利率 | J7: 综合毛利率预算偏差率=综合毛利率 -预算综合毛利率 1、综合毛利率：取上述综合毛利率 2、预算综合毛利率：手工导入 维度： 1、期间：收入成本表【年份】【月份】按月/季/年 2、事业部：按收入成本表上的【产品所属事业部】 | K7: √ | L7: √ | Z7: % | AA7: 月/季/年 | AB7: 两位小数点 | AC7: PBCS | AD7: ★★★ | AE7: 内部管理 | AI7: 潘敏君 | AJ7: 潘敏君 | AK7: 陈亚婕 | AL7: =VLOOKUP(G7,'指标体系-教育'!G:G,1,0)=G7 -> #N/A | AM7: 否 | AN7: 营收保障 | AP7: 是 | AQ7: 一期
A8: 营销 | B8: 扩大营业收入 | D8: 收入分析 | E8: 营业收入分析 | F8: 核心指标 | G8: BOM毛利率预算偏差率 | H8: BOM毛利率与预算BOM毛利率之差 | I8: BOM毛利率 -预算毛利率 | J8: BOM毛利率预算偏差率=BOM毛利率 -预算BOM毛利率 1、BOM毛利率：取上述BOM毛利率 2、预算BOM毛利率：手工导入 维度： 1、期间：收入成本表【年份】【月份】按月/季/年 2、事业部：按收入成本表上的【产品所属事业部】 | K8: √ | L8: √ | Z8: % | AA8: 月/季/年 | AB8: 两位小数点 | AC8: PBCS | AD8: ★★★ | AE8: 内部管理 | AI8: 潘敏君 | AJ8: 潘敏君 | AK8: 陈亚婕 | AL8: =VLOOKUP(G8,'指标体系-教育'!G:G,1,0)=G8 -> #N/A | AM8: 否 | AN8: 营收保障 | AP8: 是 | AQ8: 一期
B9: 扩大营业收入 | D9: 收入分析 | E9: 营业收入分析 | G9: 剔除返利后毛利率 | H9: 剔除供应商返利后的毛利率 | I9: （综合毛利额-返利额）/综合营业收入 | J9: 剔除返利后毛利额=综合营业收入-综合营业成本-返利额 1、综合营业收入 EDS系统中收入明细成本表， 筛选【冲销标记】不为 'Y'，【交易类型】 包含 ('',‘跨BG内部交易’)的数据，按【业绩所属事业部】列中事业部对应所属BG统计,汇总【订单行折扣后不含税金额】列; 2、综合营业成本 EDS系统中收入明细成本表，筛选【冲销标记】不为 'Y'，【交易类型】 包含 ('',‘跨BG内部交易’)的数据的数据，按【业绩所属事业部】列中事业部对应所属BG统计,汇总【原始合计成本】列 3、返利额 EDS系统中收入明细成本表，筛选【冲销标记】不为 'Y'，【交易类型】 包含 ('',‘跨BG内部交易’)的数据，【调整数备注】包含“返利”的数据，按【业绩所属事业部】列中事业部对应所属BG统计,汇总【原始合计成本】列 | AQ9: 一期
A10: 营销 | B10: 扩大营业收入 | D10: 收入分析 | E10: 营业收入分析 | F10: 一级指标 | G10: 综合营业收入 | H10: 综合营业收入 | I10: 综合营业收入 | J10: 1、综合营业收入 EDS系统中收入明细成本表，筛选【冲销标记】不为 'Y'，【交易类型】 包含 ('',‘跨BG内部交易’)的数据的数据，按【业绩所属事业部】列中事业部对应所属BG统计,汇总【订单行折扣后不含税金额】列; | K10: √ | L10: √ | N10: √ | O10: √ | P10: √ | Q10: √ | R10: √ | S10: √ | T10: √ | U10: √ | V10: √ | Z10: 万元 | AA10: 日/周/月/季/年 | AB10: 无小数点 | AC10: EDS | AD10: ★★★ | AE10: 内部管理 | AI10: 陈亚婕 | AJ10: 潘敏君 | AK10: 陈亚婕 | AL10: =VLOOKUP(G10,'指标体系-教育'!G:G,1,0)=G10 -> #N/A | AM10: 否 | AN10: =AN5 -> 营收保障 | AO10: 是 | AP10: 是 | AQ10: 一期
A11: 营销 | B11: 扩大营业收入 | D11: 收入分析 | E11: 营业收入分析 | F11: 一级指标 | G11: 销售目标完成率及排名 | H11: 完成销售目标的比例 | I11: 综合营业收入/销售目标 | J11: 销售目标完成率=综合营业收入/销售目标 1、综合营业收入 EDS系统中收入明细成本表，筛选【冲销标记】不为 'Y'，【交易类型】 包含 ('',‘跨BG内部交易’)的数据的数据，按【业绩所属事业部】列中事业部对应所属BG统计,汇总【订单行折扣后不含税金额】列; 2、销售目标：手工导入。 | Z11: % | AA11: 日/周/月/季/年 | AB11: 两位小数点 | AC11: EDS/导入 | AD11: ★★★ | AE11: 内部管理 | AI11: 陈亚婕 | AJ11: 潘敏君 | AK11: 陈亚婕 | AL11: 否 | AM11: 否 | AN11: =AN10 -> 营收保障 | AO11: 是 | AP11: 是 | AQ11: 一期
A12: 营销 | B12: 扩大营业收入 | D12: 收入分析 | E12: 营业收入分析 | F12: 一级指标 | G12: 预算完成率 | H12: 完成预算的比例 | I12: 综合营业收入/预算目标 | J12: 预算完成率=综合营业收入/预算目标 1、综合营业收入 EDS系统中收入明细成本表，筛选【冲销标记】不为 'Y'，【交易类型】 包含 ('',‘跨BG内部交易’)的数据的数据，按【业绩所属事业部】列中事业部对应所属BG统计,汇总【订单行折扣后不含税金额】列; 2、预算目标：手工导入。 | K12: √ | L12: √ | O12: √ | P12: √ | Q12: √ | R12: √ | S12: √ | Z12: % | AA12: 日/周/月/季/年 | AB12: 两位小数点 | AC12: EDS/导入 | AD12: ★★★ | AE12: 内部管理 | AI12: 陈亚婕 | AJ12: 潘敏君 | AK12: 陈亚婕 | AL12: 否 | AM12: 否 | AN12: =AN11 -> 营收保障 | AO12: 是 | AP12: 是 | AQ12: 一期
A13: 营销 | B13: 扩大营业收入 | D13: 收入分析 | E13: 营业收入分析 | F13: 一级指标 | G13: 预测完成率 | H13: 完成预测的比例 | I13: 综合营业收入/预测目标 | J13: 预测完成率=综合营业收入/预测目标 1、综合营业收入 EDS系统中收入明细成本表，筛选【冲销标记】不为 'Y'，【交易类型】 包含 ('',‘跨BG内部交易’)的数据的数据，按【业绩所属事业部】列中事业部对应所属BG统计,汇总【订单行折扣后不含税金额】列; 2、预测目标：手工导入。 | K13: √ | L13: √ | N13: √ | O13: √ | P13: √ | Q13: √ | R13: √ | S13: √ | Z13: % | AA13: 日/周/月/季/年 | AB13: 两位小数点 | AC13: EDS/导入 | AD13: ★★★ | AE13: 内部管理 | AI13: 陈亚婕 | AJ13: 潘敏君 | AK13: 陈亚婕 | AL13: 否 | AM13: 否 | AN13: =AN12 -> 营收保障 | AO13: 是 | AP13: 是 | AQ13: 一期
A14: 营销 | B14: 扩大营业收入 | D14: 收入分析 | E14: 营业收入分析 | F14: 一级指标 | G14: 收入同比增长率 | H14: 收入同比增长比例 | I14: （本期营业收入-同期收入）/同期营业收入 | J14: 收入同比增长率=（本期营业收入-同期收入）/同期营业收入 1、综合营业收入 EDS系统中收入明细成本表，筛选【冲销标记】不为 'Y'，【交易类型】 包含 ('',‘跨BG内部交易’)的数据的数据，按【业绩所属事业部】列中事业部对应所属BG统计,汇总【订单行折扣后不含税金额】列; | K14: √ | L14: √ | N14: √ | O14: √ | P14: √ | Q14: √ | R14: √ | S14: √ | Z14: % | AA14: 月/季/年 | AB14: 两位小数点 | AC14: EDS | AD14: ★★★ | AE14: 内部管理 | AI14: 陈亚婕 | AJ14: 潘敏君 | AK14: 陈亚婕 | AL14: =VLOOKUP(G14,'指标体系-教育'!G:G,1,0)=G14 -> TRUE | AM14: 否 | AN14: =AN11 -> 营收保障 | AO14: 是 | AP14: 是 | AQ14: 一期
A15: 营销 | B15: 扩大营业收入 | D15: 收入分析 | E15: 营业收入分析 | F15: 一级指标 | G15: 本年累计收入同比增长率 | H15: 本年累计收入同比增长比例 | I15: （本年累计营业收入-上年同期累计营业收入）/上年同期累计营业收入 | J15: 本年累计收入同比增长率=（本年累计营业收入-上年同期累计营业收入）/上年同期累计营业收入 1、综合营业收入 EDS系统中收入明细成本表，筛选【冲销标记】不为 'Y'，【交易类型】 包含 ('',‘跨BG内部交易’)的数据的数据，按【业绩所属事业部】列中事业部对应所属BG统计,汇总【订单行折扣后不含税金额】列; | K15: √ | L15: √ | N15: √ | O15: √ | P15: √ | Q15: √ | R15: √ | S15: √ | Z15: % | AA15: 月/季/年 | AB15: 两位小数点 | AC15: EDS | AD15: ★★★ | AE15: 内部管理 | AI15: 陈亚婕 | AJ15: 潘敏君 | AK15: 陈亚婕 | AL15: =VLOOKUP(G15,'指标体系-教育'!G:G,1,0)=G15 -> #N/A | AM15: 否 | AN15: =AN12 -> 营收保障 | AO15: 是 | AP15: 是 | AQ15: 一期
B16: 扩大营业收入 | D16: 收入分析 | E16: 营业收入分析 | G16: 新业务占比 | H16: 新业务收入占比 | I16: 新业务收入/综合营业收入 | J16: 新业务占比=新业务收入/综合营业收入 1、新业务收入 EDS系统中收入明细成本表，筛选【冲销标记】不为 'Y'，【交易类型】 包含 ('',‘跨BG内部交易’)的数据，【业绩所属事业部】所属BG为‘未来教育BG’且【业绩所属事业部】不包含‘多媒体事业部’的数据，汇总【订单行折扣后不含税金额】列; 2、综合营业收入 EDS系统中收入明细成本表，筛选【冲销标记】不为 'Y'，【交易类型】 包含 ('',‘跨BG内部交易’)的数据的数据，【业绩所属事业部】所属BG为‘未来教育BG’,汇总【订单行折扣后不含税金额】列; | K16: √ | L16: √ | R16: √ | S16: √ | AI16: 陈亚婕 | AL16: 否 | AM16: 否 | AN16: =AN12 -> 营收保障 | AO16: 是 | AQ16: 一期
B17: 扩大营业收入 | D17: 收入分析 | E17: 销量分析 | F17: 一级指标 | G17: 配比率 | H17: 周边产品占整机产品比 | I17: 周边产品数量/整机数量 | J17: 配比率=周边产品数量/整机数量 1、周边产品数量： EDS系统中收入明细成本表，【冲销标记】不为 'Y'，【交易类型】不含“教育BG内部交易”，【业绩所属事业部】所属BG为‘未来教育BG’，【产品线分类】为“音视频产品线”的数据，汇总【数量】列 2、整机数量： EDS系统中收入明细成本表，【冲销标记】不为 'Y'，【交易类型】不含“教育BG内部交易”，【业绩所属事业部】所属BG为‘未来教育BG’，【产品线分类】为“交互智能平板产品线”的数据，【物料小分类】为“智慧黑板”、“交互智能平板”，汇总【数量】列 维度： 区域、办事处、销售、物料小分类 学段：CRM 内销发货通知视睿全数据中的【学段】字段，通过【发货通知单号】映射到EDS收入成本明细表 | AI17: 郭梓樱 | AO17: 是
B18: 扩大营业收入 | D18: 收入分析 | E18: 销量分析 | F18: 一级指标 | G18: 数量占比 | H18: 数量占总数量比 | I18: 数量/总数量 | J18: 数量： EDS系统中收入明细成本表，【冲销标记】不为 'Y'，【交易类型】不含“教育BG内部交易”，【业绩所属事业部】所属BG为‘未来教育BG’，【产品线分类】筛选为“音视频产品线”，【数量】汇总 维度： 产品线、物料小分类 销售型号：EDS收入成本明细表，【销售型号】 大屏尺寸：①按【销售型号】汇总【合同号】；②用【合同号】汇总【尺寸】（包含【产品线分类】为“交互智能平板产品线”且【物料小分类】为“智慧黑板”、“交互智能平板”的【尺寸】）；③通过【合同号】建立【销售型号】和【尺寸】的对应关系。④若一个【合同号】中存在2个或者以上的【尺寸】，分摊比例为【物料小分类】为“智慧黑板”、“交互智能平板”的【数量】） 学段：CRM 内销发货通知视睿全数据中的【学段】字段，通过【发货通知单号】映射到EDS收入成本明细表 | AI18: 郭梓樱 | AO18: 是
B19: 扩大营业收入 | D19: 收入分析 | E19: 销量分析 | F19: 一级指标 | G19: 当月/当年交易渠道 | H19: 有交易记录的下单客户 | J19: 当月/当年交易渠道： EDS系统中收入明细成本表，【冲销标记】不为 'Y'，【交易类型】不含“教育BG内部交易”，【业绩所属事业部】所属BG为‘未来教育BG’，【下单客户】去重后的计数。 维度： 区域、办事处 | AI19: 郭梓樱
B20: 扩大营业收入 | D20: 收入分析 | E20: 销量分析 | F20: 一级指标 | G20: 当月/当年新增渠道 | H20: 新增的下单客户 | J20: 当月/当年交易渠道： EDS系统中收入明细成本表，【冲销标记】不为 'Y'，【交易类型】不含“教育BG内部交易”，【业绩所属事业部】所属BG为‘未来教育BG’，历史首次出现交易的【下单客户】去重后的计数。（需要考虑不同维度，存在对于办事处A是历史已经交易过的客户，但是对办事处B为首次） 维度： 区域、办事处 | AI20: 郭梓樱
B21: 扩大营业收入 | D21: 收入分析 | E21: 销量分析 | F21: 一级指标 | G21: 当月/当年新增渠道占比 | H21: 新增渠道占交易渠道比重 | I21: 新增渠道/交易渠道 | J21: 取值同上 | AI21: 郭梓樱
B22: 扩大营业收入 | D22: 收入分析 | E22: 销量分析 | F22: 一级指标 | G22: 当月/当年静默渠道 | H22: 过去1年无交易记录的客户 | J22: 当月/当年交易渠道： EDS系统中收入明细成本表，【冲销标记】不为 'Y'，【交易类型】不含“教育BG内部交易”，【业绩所属事业部】所属BG为‘未来教育BG’，当前日期距离【出货日期】超过1年（含1年）不存在交易记录的【下单客户】去重后的计数。 维度： 区域、办事处 | AI22: 郭梓樱
A23: 营销 | B23: 扩大营业收入 | D23: 收入分析 | E23: 销量分析 | F23: 一级指标 | G23: 整机销量 | H23: 整机销量 | I23: 整机销量 | J23: 1、整机销量 EDS系统中收入明细成本表，筛选【冲销标记】不为 'Y'，【交易类型】 包含 ('',‘跨BG内部交易’)的数据，产品型号+产品维 对应的商务产品标签类为‘整机’的数据，按【业绩所属事业部】中事业部对应所属BG统计,汇总【成套成品数量】列。增加：2020年3月的数据，【调整备注】为“本期未签收本期调减收入”的【成品数量】列须由正数改为对应的负数。 企服 成套成品数量换算规则： I产品型号+产品维 对应的商务产品标签类为‘整机’ ,则成套成品数量=数量；产品的小分类=‘LED工程屏’需按合同换算【成套成品数量】为1，一个合同号1台；ELSE 成套成品数量=成品数量 | K23: √ | L23: √ | N23: √ | O23: √ | P23: √ | Q23: √ | R23: √ | S23: √ | T23: √ | V23: √ | Z23: 台 | AA23: 日/周/月/季/年 | AB23: 无小数点 | AC23: EDS | AD23: ★★★ | AE23: 内部管理 | AI23: 陈亚婕 | AJ23: 潘敏君 | AK23: 陈亚婕 | AL23: =VLOOKUP(G23,'指标体系-教育'!G:G,1,0)=G23 -> TRUE | AM23: 否 | AN23: =AN14 -> 营收保障 | AO23: 是 | AP23: 是 | AQ23: 一期
A24: 营销 | B24: 扩大营业收入 | D24: 收入分析 | E24: 销量分析 | F24: 一级指标 | G24: 整机销量同比增长率 | H24: 整机销量同比增长比例 | I24: （本期整机销量-同期整机销量）/同期整机销量 | J24: 整机销量同比增长率=（本期整机销量-同期整机销量）/同期整机销量 1、整机销量 EDS系统中收入明细成本表，筛选【冲销标记】不为 'Y'，【交易类型】 包含 ('',‘跨BG内部交易’)的数据，产品型号+产品维 对应的商务产品标签类为‘整机’的数据，按【业绩所属事业部】列中事业部对应所属BG统计,汇总【成套成品数量】列。增加：2020年3月的数据，【调整备注】为“本期未签收本期调减收入”的【成品数量】列须由正数改为对应的负数。 产品的小分类=‘LED工程屏’需按合同换算【成套成品数量】为1，一个合同号1台 | Z24: % | AA24: 月/季/年 | AB24: 两位小数点 | AC24: EDS | AD24: ★★★ | AE24: 内部管理 | AI24: 陈亚婕 | AJ24: 潘敏君 | AK24: 陈亚婕 | AL24: =VLOOKUP(G24,'指标体系-教育'!G:G,1,0)=G24 -> TRUE | AM24: 否 | AN24: =AN23 -> 营收保障 | AO24: 是 | AP24: 是 | AQ24: 一期
A25: 营销 | B25: 扩大营业收入 | D25: 收入分析 | E25: 配比分析 | F25: 一级指标 | G25: 周边配比 | H25: 周边产品收入占整体(整机-会议平板+周边产品)收入比例 | I25: 周边产品营业收入/(会议平板+周边产品营业收入) | J25: 周边配比=周边产品营业收入/(整体营业收入) 教育 1、周边产品营业收入 EDS系统中收入明细成本表，筛选【冲销标记】不为 'Y'，【交易类型】 包含 ('',‘跨BG内部交易’)的数据，【业绩所属事业部】=‘多媒体事业部’AND 产品型号对应的产品线分类=‘音视频周边产品线’，汇总【订单行折扣后不含税金额】列; 2、整体收入 EDS系统中收入明细成本表，筛选【冲销标记】不为 'Y'，【交易类型】 包含 ('',‘跨BG内部交易’)的数据，【业绩所属事业部】=‘多媒体事业部’AND 产品型号对应的产品线分类 in (‘音视频周边产品线’,'智能平板产品线'），汇总【订单行折扣后不含税金额】列; 企服 1、周边产品营业收入 EDS系统中收入明细成本表，筛选【冲销标记】不为 'Y'，【交易类型】 包含 ('',‘跨BG内部交易’)的数据，产品型号+产品维对应的商务产品标签类为‘周边’+‘PC’的数据，按【业绩所属事业部】列中事业部对应所属BG统计，汇总【订单行折扣后不含税金额】列; 2、整体收入 EDS系统中收入明细成本表，筛选【冲销标记】不为 'Y'，【交易类型】 包含 ('',‘跨BG内部交易’)的数据，按【业绩所属事业部】列中事业部对应所属BG统计，汇总【订单行折扣后不含税金额】列; | K25: √ | L25: √ | Z25: % | AA25: 月/季/年 | AB25: 两位小数点 | AC25: PBCS | AD25: ★★ | AE25: 内部管理 | AI25: 潘敏君 | AJ25: 龚芬芬 | AK25: 陈亚婕 | AL25: =VLOOKUP(G25,'指标体系-教育'!G:G,1,0)=G25 -> TRUE | AM25: 否 | AN25: =AN24 -> 营收保障 | AO25: 是 | AP25: 是 | AQ25: 一期
A26: 营销 | B26: 扩大营业收入 | D26: 收入分析 | E26: 配比分析 | F26: 一级指标 | G26: 主要周边销量配比 | H26: XX销量占对应整机销量比例 | I26: XX销量/对应整机销量 | J26: @龚芬芬 暂无此配置表，主数据2期项目会包含此内容，实现时间后调【回复】ok 企服： XX型号销量：PBCS系统中收入成本表，筛选【产品所属事业部】中属于企业服务BG的事业部，筛选【冲销标记】不为 'Y'，剔除【交易类型】列为”XXBG内部交易“，汇总对应XX型号【数量】列 对应整机销量： 1、先根据提供的配置表，确定主要周边对应的整机型号，如SA06对应三代STU系列。 2、PBCS系统中收入成本表，筛选【产品所属事业部】中属于企业服务BG的事业部，筛选【冲销标记】不为 'Y'，剔除【交易类型】列为“跨BG内部交易“及”XXBG内部交易“，汇总对应整机【数量】列。 维度： 1、期间：收入成本表【年份】【月份】按月/季/年 2、事业部：按收入成本表上的【产品所属事业部】 教育： 1、周边销量配比=**销售型号销量/对应整机销量 周边产品定义： 【业绩所属事业部】=‘多媒体事业部’AND 产品型号对应的产品线分类=‘音视频周边产品线’ **销售型号销量： EDS系统中收入明细成本表，筛选【冲销标记】不为 'Y'，【交易类型】 包含 ('',‘跨BG内部交易’)的数据，【业绩所属事业部】=‘多媒体事业部’AND 产品型号对应的产品线分类=‘音视频周边产品线’，按销售型号汇总【数量】列; 对应整机销量 EDS系统中收入明细成本表，筛选【冲销标记】不为 'Y'，【交易类型】 包含 ('',‘跨BG内部交易’)的数据，【业绩所属事业部】=‘多媒体事业部’AND 产品型号对应的产品线分类 in (‘音视频周边产品线’,'智能平板产品线'），汇总【成套成品数量】列; | K26: √ | L26: √ | Z26: % | AA26: 月/季/年 | AB26: 两位小数点 | AC26: PBCS | AD26: ★★ | AE26: 内部管理 | AI26: 潘敏君 | AJ26: 龚芬芬 | AK26: 陈亚婕 | AL26: =VLOOKUP(G26,'指标体系-教育'!G:G,1,0)=G26 -> TRUE | AM26: 否 | AN26: =AN25 -> 营收保障 | AO26: 是 | AP26: 是 | AQ26: 一期
A27: 营销 | B27: 扩大营业收入 | D27: 收入分析 | E27: 订单分析 | F27: 一级指标 | G27: 订单平均金额 | H27: 平均每个订单含税销售额 | I27: 含税销售额/订单个数 | J27: 订单平均金额=含税销售额/订单个数 企业服务： 1、含税销售额 EDS系统中收入明细成本表，筛选【冲销标记】不为 'Y'，【交易类型】 包含 ('',‘跨BG内部交易’)的数据，【收入分类】为“主营业务收入”，且【合同号】不为空或NULL 的数据，按【业绩所属事业部】列中事业部对应所属BG统计，汇总【订单行折扣后不含税金额】*（1+【当月税率】） 2、订单个数 EDS系统中收入明细成本表，筛选，【冲销标记】不为 'Y'，【交易类型】 包含 ('',‘跨BG内部交易’)的数据，【收入分类】为“主营业务收入”且【合同号】不为空的数据，按【业绩所属事业部】列中事业部对应所属BG统计，汇总【合同号】个数，同一个合同号多行记录去重取1； 未来教育 1、含税销售额 EDS系统中收入明细成本表，筛选【冲销标记】不为 'Y'，【交易类型】 包含 ('',‘跨BG内部交易’)的数据，【合同号】不为空或NULL的数据，按【业绩所属事业部】列中事业部对应所属BG统计，汇总【订单行折扣后不含税金额】*（1+【当月税率】）； 2、订单个数 EDS系统中收入明细成本表，筛选，【冲销标记】不为 'Y'，【交易类型】 包含 ('',‘跨BG内部交易’)的数据，【合同号】不为空的数据，按【业绩所属事业部】列中事业部对应所属BG统计，汇总【合同号】个数，同一个合同号多行记录去重取1； | K27: √ | L27: √ | R27: √ | S27: √ | T27: √ | V27: √ | Z27: 万元 | AA27: 日/周/月/季/年 | AB27: 无小数点 | AC27: PBCS | AD27: ★★ | AE27: 内部管理 | AI27: 潘敏君 | AJ27: 龚芬芬 | AK27: 陈亚婕 | AL27: =VLOOKUP(G27,'指标体系-教育'!G:G,1,0)=G27 -> TRUE | AM27: 否 | AN27: =AN28 -> 营收保障 | AO27: 是 | AP27: 是 | AQ27: 一期
A28: 营销 | B28: 扩大营业收入 | D28: 收入分析 | E28: 价格分析 | F28: 一级指标 | G28: 低价销量占比 | H28: 低价单销量占整机销量比例 | I28: 低价整机销量/整机销量 | J28: 低价量占比=低价整机销量/整机销量 1、低价整机销量： 1）低价单 CRM系统-销售订单，订单行的底价字段值<单价字段值，则此订单编号+产品型号的行为低价订单行 2）低价单整机销量： EDS系统中收入明细成本表，筛选【冲销标记】不为 'Y'，【交易类型】 包含 ('',‘跨BG内部交易’)的数据，合同号对应的订单编号+产品型号为低价订单行，产品型号+产品维 对应的商务产品标签类为‘整机’的数据，按【业绩所属事业部】列中事业部对应所属BG统计,汇总【成套成品数量】列； 2020年3月的数据修改同上。 2、整机销量： EDS系统中收入明细成本表，筛选【冲销标记】不为 'Y'，【交易类型】 包含 ('',‘跨BG内部交易’)的数据，产品型号+产品维 对应的商务产品标签类为‘整机’的数据，按【业绩所属事业部】列中事业部对应所属BG统计,汇总【数量】列; | K28: √ | L28: √ | N28: √ | O28: √ | P28: √ | Q28: √ | R28: √ | S28: √ | T28: √ | V28: √ | Z28: % | AA28: 月/季/年 | AB28: 两位小数点 | AC28: CRM | AD28: ★★ | AE28: 内部管理 | AI28: 潘敏君 | AJ28: 龚芬芬 | AK28: 陈亚婕 | AL28: =VLOOKUP(G28,'指标体系-教育'!G:G,1,0)=G28 -> #N/A | AM28: 否 | AN28: =AN26 -> 营收保障 | AO28: 是 | AP28: 是 | AQ28: 一期
A29: 营销 | B29: 扩大营业收入 | D29: 收入分析 | E29: 价格分析 | F29: 一级指标 | G29: 低价营收占比 | H29: 低价单金额占全部金额比例 | I29: 低价营收/综合营业收入 | J29: 低价金额占比=低价单金额/全部营收 1、低价营收 CRM系统-销售订单，订单行的底价字段值<单价字段值，则此订单编号+产品型号的行为低价订单行 EDS系统中收入明细成本表，筛选【冲销标记】不为 'Y'，【交易类型】 包含 ('',‘跨BG内部交易’)的数据，合同号对应的订单编号+产品型号为低价订单行，按【业绩所属事业部】列中事业部对应所属BG统计,汇总【订单行折扣后不含税金额】列; 2、综合营业收入 EDS系统中收入明细成本表，筛选【冲销标记】不为 'Y'，【交易类型】 包含 ('',‘跨BG内部交易’)的数据的数据，按【业绩所属事业部】列中事业部对应所属BG统计,汇总【订单行折扣后不含税金额】列; | K29: √ | L29: √ | N29: √ | O29: √ | R29: √ | S29: √ | T29: √ | V29: √ | Z29: % | AA29: 月/季/年 | AB29: 一位小数点 | AC29: CRM/EDS | AD29: ★★★ | AE29: 内部管理 | AI29: 陈亚婕 | AK29: 陈亚婕 | AL29: 否 | AM29: 否 | AN29: =AN27 -> 营收保障 | AO29: 是 | AP29: 是 | AQ29: 一期
A30: 营销 | B30: 扩大营业收入 | D30: 收入分析 | E30: 价格分析 | F30: 一级指标 | G30: 平均单价 | H30: 产品平均单价 | I30: 综合营业收入/整机数量 | J30: 平均单价=综合营业收入/数量 1、综合营业收入 EDS系统中收入明细成本表，筛选【冲销标记】不为 'Y'，【交易类型】 包含 ('',‘跨BG内部交易’)的数据的数据，按【业绩所属事业部】列中事业部对应所属BG统计,汇总【订单行折扣后不含税金额】列; 2、数量 EDS系统中收入明细成本表，筛选【冲销标记】不为 'Y'，【交易类型】 包含 ('',‘跨BG内部交易’)的数据的数据，按【业绩所属事业部】列中事业部对应所属BG统计，汇总【成套成品数量】列。2020年3月数据修改同上。 产品的小分类=‘LED工程屏’需按合同换算【成套成品数量】为1，一个合同号1台 | K30: √ | L30: √ | N30: √ | O30: √ | P30: √ | Q30: √ | R30: √ | S30: √ | T30: √ | Z30: % | AA30: 月/季/年 | AB30: 一位小数点 | AC30: CRM/EDS | AD30: ★★★ | AE30: 内部管理 | AI30: 陈亚婕 | AK30: 陈亚婕 | AL30: 否 | AM30: 否 | AN30: =AN29 -> 营收保障 | AO30: 是 | AP30: 是 | AQ30: 一期
B31: 扩大营业收入 | D31: 收入分析 | E31: 价格分析 | G31: 预测出货量 | H31: 可在当天早上更新出当天出货数量 | I31: 预计出货数量 | J31: 1、出货整机数量 取CRM-发货通知单+门户发货通知，单据状态不包含‘已作废’,‘制单中’【发货日期】=当天，产品型号的商务标签=‘整机’的发货产品行，汇总 【数量】字段值 | AH31: 陈亚婕 | AJ31: 陈亚婕 | AK31: 否 | AL31: 否 | AM31: =AM30 -> 否 | AN31: 是 | AO31: 是 | AQ31: 一期
B32: 扩大营业收入 | D32: 收入分析 | E32: 价格分析 | G32: 预测出货收入 | H32: 可在当天早上更新出当天出货收入 | I32: 预计出货收入 | J32: 1、出货收入=销售额/(1+销售订单税率） 2、销售额=发货金额-返利额 取CRM-发货通知单+门户发货通知，单据状态不包含‘已作废’,‘制单中’【发货日期】=当天，汇总 【销售额】字段值 | AH32: 陈亚婕 | AJ32: 陈亚婕 | AK32: 否 | AL32: 否 | AM32: =AM31 -> 否 | AN32: 是 | AO32: 是 | AQ32: 一期
B33: 扩大营业收入 | D33: 收入分析 | E33: 价格分析 | G33: 预测出货收入 | H33: 可在当天早上更新出当天出货收入 | I33: 预计出货收入(含税) | J33: 1、出货收入含税=发货金额-返利额 取CRM-发货通知单+门户发货通知，单据状态不包含‘已作废’,‘制单中’【发货日期】=当天，汇总 【销售额】字段值 | AH33: 陈亚婕 | AJ33: 陈亚婕 | AK33: 否 | AL33: 否 | AM33: =AM32 -> 否 | AN33: 是 | AO33: 是 | AQ33: 一期
B34: 扩大营业收入 | D34: 收入分析 | E34: 价格分析 | G34: 区域管理营业收入 | H34: 区域管理营业收入 | I34: 区域管理营业收入=综合营业收入+门户发货通知已过账收入 | J34: BI另一套业务数据 只单独做区域-办事处营业收入 区域管理营业收入=综合营业收入+门户发货通知已过账收入 综合营业收入： EDS系统中收入明细成本表，筛选【冲销标记】不为 'Y'，【交易类型】 包含 ('',‘跨BG内部交易’)的数据的数据，按【业绩所属事业部】列中事业部对应所属BG统计,汇总【订单行折扣后不含税金额】列; 门户收入：经销商发货表，单据状态=‘已完成’，汇总【销售额】/(1+税率)字段值，日期：过帐时间，数量：地址数量，收入=(单价*数量）/(1+当月税率） EDS按照区域-办事处维度，区域取自字段【区域】，办事处取自字段【办事处】 维度： 1、期间：收入成本表【年份】【月份】按月/季/年 2、事业部：EDS部分按收入成本表上的【产品所属事业部】，门户取值【业绩归属事业部】 3、产品线：取收入成本表【销售型号】列，根据【销售型号】对应产品线匹配（详见产品目录） 4、按收入成本表中【销售型号】列，门户【销售型号】列 5、系列：取收入成本表【销售型号】列，根据【销售型号】对应系列匹配（详见产品目录） 6、尺寸：取收入成本表【销售型号】列，根据【销售型号】对应尺寸匹配（详见产品目录） 7、区域：按【销售人员】组织架构所在的区域，门户OUT销售所在部门 8、办事处：按【销售人员】组织架构所在的办事处，门户OUT销售所在部门 9、销售：eds取值【销售人员】+门户【 out销售】 （含事业部专岗销售，系统需要双重身份） | K34: √ | L34: √ | N34: √ | O34: √ | P34: √ | Q34: √ | R34: √ | S34: √ | T34: √ | U34: √ | V34: √ | Z34: % | AA34: 月/季/年 | AB34: 两位小数点 | AC34: PBCS | AD34: ★★★ | AE34: 内部管理 | AI34: 陈亚婕 | AQ34: 一期
B35: 扩大营业收入 | D35: 收入分析 | E35: 价格分析 | G35: 区域管理营业成本 | H35: 区域管理营业成本 | I35: 区域管理营业成本=综合营业成本+门户发货成本 | J35: BI另一套业务数据 只单独做区域-办事处营业收入 营业成本=综合营业成本+门户发货通知已过账收入对应追溯至EDS成本 综合营业成本： EDS系统中收入明细成本表，筛选【冲销标记】不为 'Y'，【交易类型】 包含 ('',‘跨BG内部交易’)的数据的数据，按【业绩所属事业部】列中事业部对应所属BG统计,汇总【原始合计成本】列 门户发货成本：经销商发货表中单据状态=‘已完成’，过帐时间不为空，发货成本=地址数量*原始单位成本 原始单位成本：收入成本明细表中下单客户=佳电（上海）管理有限公司，对应产品型号+生产批次+产品编码的【原始单位成本】 维度： 1、期间：收入成本表【年份】【月份】按月/季/年+经销商发货列表 过账时间 2、事业部：EDS部分按收入成本表上的【产品所属事业部】，门户取值【业绩归属事业部】 3、产品线：取收入成本表【销售型号】列，根据【销售型号】对应产品线匹配（详见产品目录） 4、按收入成本表中【销售型号】列，门户【销售型号】列 5、系列：取收入成本表【销售型号】列，根据【销售型号】对应系列匹配（详见产品目录） 6、尺寸：取收入成本表【销售型号】列，根据【销售型号】对应尺寸匹配（详见产品目录） 7、区域：按【销售人员】组织架构所在的区域，门户OUT销售所在部门 8、办事处：按【销售人员】组织架构所在的办事处，门户OUT销售所在部门 9、销售：eds取值【销售人员】+门户【 out销售】 （含事业部专岗销售，系统需要双重身份） | AQ35: 一期
B36: 扩大营业收入 | D36: 收入分析 | E36: 价格分析 | G36: 区域管理毛利率 | H36: 区域管理毛利率 | I36: 区域管理毛利率 | J36: (区域管理营业收入-区域管理营业成本)/区域管理营业成本 | AQ36: 一期
B37: 扩大营业收入 | D37: 收入分析 | E37: 低价分析 | G37: 低价幅度 | H37: 低价营收的低价幅度 | I37: 低价幅度=（底价销售收入-低价销售收入）/底价销售收入 | J37: 低价幅度=（底价销售收入-低价销售收入）/底价销售收入 1、底价销售收入 EDS系统中收入明细成本表，筛选【冲销标记】不为 'Y'，【交易类型】 包含 ('',‘跨BG内部交易’)的数据，合同号对应的订单编号+产品型号为低价订单行，汇总对应低价订单行的【底价】*【数量】/(1+当月税率) 2、低价销售收入 CRM系统-销售订单，订单行的底价字段值<单价字段值，则此订单编号+产品型号的行为低价订单行 EDS系统中收入明细成本表，筛选【冲销标记】不为 'Y'，【交易类型】 包含 ('',‘跨BG内部交易’)的数据，合同号对应的订单编号+产品型号为低价订单行，按【业绩所属事业部】列中事业部对应所属BG统计,汇总【订单行折扣后不含税金额】列; | K37: √ | L37: √ | N37: √ | O37: √ | P37: √ | Q37: √ | R37: √ | S37: √ | AJ37: 潘敏君 | AQ37: 一期
B38: 扩大营业收入 | D38: 收入分析 | E38: 销售个人业绩（本报表数据均取含税） | G38: 销售个人业绩（渠道、金融） | J38: 【需手工导入】 1、同期业绩（去年同期按月业绩）：需手工导入2019年1月-2020年8月的销售个人业绩数据 2、每月销售个人目标：从2020年Q4开始导入，预计9月底业务可提供数据导入。 销售个人业绩仅含SO业绩（本报表数据均取含税） SO业绩：CRM-销售管理-PSI报表管理-SZ PSI报表-销售OUT数据查询，期间按照【过账时间】，按照【OUT销售】字段统计【销售总金额】字段。 | AJ38: 车颖慧 | AQ38: 三期
B39: 扩大营业收入 | D39: 收入分析 | E39: 销售个人业绩（本报表数据均取含税） | G39: 销售个人业绩（除渠道、金融之外） | I39: =SI业绩+SO业绩 | J39: 【需手工导入】 1、同期业绩（去年同期按月业绩）：需手工导入2019年1月-2020年8月的销售个人业绩数据 2、每月销售个人目标：从2020年Q4开始导入，预计9月底业务可提供数据导入。 销售个人业绩=1、SI业绩+2、SO业绩（本报表数据均取含税） 1、SI业绩：CRM-内销发货通知查询，【业绩归属事业部】为视臻，选取【是否过账】为已过账，期间按照【过账日期】，按照【销售】字段统计【销售额】字段； 2、SO业绩：CRM-销售管理-PSI报表管理-SZ PSI报表-销售OUT数据查询，期间按照【过账时间】，按照【OUT销售】字段统计【销售总金额】字段。 | AJ39: 车颖慧 | AQ39: 三期
B40: 2.业务拓展
A41: 营销 | B41: 强化业务拓展跟进 | D41: 业务拓展分析 | E41: 签约分析 | F41: 一级指标 | G41: 签约达成率 | H41: 完成签约数量目标的比例 | I41: 累计达成/目标 | J41: 需导入数据：签约数量目标 1.累计达成 SCRM中客户管理-经销商管理-经销商申请 【目标年份】为当年、【审核通过时间】开始时间为本年年初，截止时间为选择的截止日期、【当前状态】为“审核通过”的单据数量。 2.签约数量目标手工导入（在二期导入文件夹，已提供） 维度： 1.单据状态：【当前状态】 2.事业部/区域/办事处：根据【开拓销售】录入数据时组织架构所在事业部/区域/办事处 3.期间：【审核通过时间】 4.客户分类：【经销商类型】 | K41: √ | L41: √ | R41: √ | S41: √ | T41: √ | U41: √ | V41: √ | Z41: % | AA41: 日/周/月/季/年 | AB41: 两位小数点 | AC41: SCRM/导入 | AD41: ★★★ | AE41: 内部管理 | AI41: 龚芬芬 | AJ41: 龚芬芬 | AK41: 陈亚婕 | AL41: =VLOOKUP(G41,'[1]指标体系-教育'!G:G,1,0)=G41 -> TRUE | AM41: 否 | AN41: 业务拓展 | AP41: 是 | AQ41: 二期
B42: 强化业务拓展跟进 | D42: 业务拓展分析 | E42: 签约分析 | F42: 一级指标 | G42: 本期签约数量 | H42: 可根据选择期间统计的签约数量 | J42: SCRM中客户管理-经销商管理-经销商申请 【目标年份】为当年、【审核通过时间】起始时间均为上方选择的起始日期、【当前状态】为“审核通过”的单据数量。 维度： 1.单据状态：【当前状态】 2.事业部/区域/办事处：根据【开拓销售】录入数据时组织架构所在事业部/区域/办事处 3.期间：【审核通过时间】 4.客户分类：【经销商类型】 | AI42: 车颖慧 | AP42: 是 | AQ42: 二期
A43: 营销 | B43: 强化业务拓展跟进 | D43: 业务拓展分析 | E43: 签约分析 | F43: 一级指标 | G43: 二级数量 | H43: 每个区域/办事处/核心下属的签约和非签约二级数量 | I43: 签约数量+非签约数量 | J43: 1、签约数量： SCRM-客户管理-经销商管理-经销商申请 筛选【起始时间】为当期、【当前状态】为“审核通过”、【经销商类型】为“授权经销商”/“授权行业经销商”的【经销商名称】个数。 2、非签约数量 CRM-销售管理-PSI报表管理-经销商出货明细 筛选【单据状态】为“已审核”、【填报时间】为当期，【授权经销商】名称不在“SCRM-客户管理-经销商管理-经销商申请”中的不重复数量。 维度增加：核心经销商，可以按核心经销商（关联核代）统计其下属的二级经销商 二级经销商：经销商类型 IN ‘授权经销商’、‘授权行业经销商’ 二级经销商的定义？ 【回复】OUT出货包含核心直销和核心对应的二级分销，授权%即为二级经销商，【核心经销商】和【授权经销商】相同则为核心直销，直接卖给终端，不同则为二级分销，二级卖给终端。 授权经销商字段填写不规范，有些是1 0 这些数据需数据清理【回复】2020年起已与企查查联动，填写为全称，历史无法还原，从2020年开始取数即可。 维度： 1.期间：SCRM【起始时间】，CRM【填报时间】 2.区域/办事处：SCRM【开拓销售】，CRM【OUT销售】组织架构所在区域/办事处 3.客户：SCRM【经销商类型】为“核心经销商”的【经销商名称】 4.是否签约：如上，来源SCRM-签约，其他-非签约 | K43: √ | R43: √ | S43: √ | T43: √ | Z43: % | AA43: 日/周/月/季/年 | AB43: 两位小数点 | AC43: SCRM/CRM | AD43: ★★★ | AE43: 内部管理 | AI43: 龚芬芬 | AJ43: 龚芬芬 | AK43: 陈亚婕 | AL43: 否 | AM43: 否 | AN43: 业务拓展 | AP43: 是 | AQ43: 二期
A44: 营销 | B44: 强化业务拓展跟进 | D44: 业务拓展分析 | E44: 样机分析 | F44: 一级指标 | G44: 样机申请率 | H44: 样机申请量占额度比例 | I44: 样机申请量/样机额度 | J44: 需导入数据：样机额度 样机申请率=样机申请量/样机额度 1.样机申请量 CRM-样机管理-借用单 【单据状态】为“已完成”,'审核中'，【样机来源】不包含“转借样机”，【实发型号】+产品维 对应的商务产品标签类为‘整机’的数据，汇总【实发数量】 2.样机额度手工导入 维度： 1.期间：【申请日期】 2.事业部/区域/办事处：【保管人】组织架构的【事业部】【区域】【省份】 3.人员：【保管人】 4.客户：【借用方】 5.产品线/系列/尺寸/产品型号：根据【实发销售型号】与产品目录判断 6.用途：【借机用途】 | K44: √ | L44: √ | N44: √ | O44: √ | P44: √ | Q44: √ | R44: √ | S44: √ | T44: √ | V44: √ | Y44: √ | Z44: % | AA44: 日/周/月/季/年 | AB44: 两位小数点 | AC44: CRM/导入 | AD44: ★★★ | AE44: 内部管理 | AI44: 龚芬芬 | AJ44: 龚芬芬 | AL44: 否 | AM44: 否 | AN44: =#REF! -> #REF! | AP44: 是 | AQ44: 二期
A45: 营销 | B45: 强化业务拓展跟进 | D45: 业务拓展分析 | E45: 样机分析 | F45: 一级指标 | G45: 样机转销率 | H45: 样机转销量占申请比例 | I45: 样机转销量/样机申请量 | J45: 1.样机转销量 CRM-样机管理-归还单 【单据状态】为““已完成”,'审核中'，【归还类型】为“转销”，【产品型号】+产品维 对应的商务产品标签类为‘整机’的数据，汇总【实际归还数量】 2.样机申请量 CRM-样机管理-借用单 【单据状态】为““已完成”,'审核中'，【样机来源】不包含“转借样机”，【实发型号】+产品维 对应的商务产品标签类为‘整机’的数据，汇总【实发数量】 维度： 1.期间：【审核完成时间】 2.事业部/区域/办事处：【保管人】组织架构的【事业部】【区域】【省份】 3.人员：【保管人】 4.客户借机：客户【借用方】 5.系列/产品型号：【产品系列】【销售型号】 6.用途：样机归还报表的【借用单号】匹配【样机借用报表】的借机用途 | K45: √ | L45: √ | N45: √ | O45: √ | P45: √ | Q45: √ | R45: √ | S45: √ | T45: √ | V45: √ | Y45: √ | Z45: % | AA45: 日/周/月/季/年 | AB45: 两位小数点 | AC45: CRM | AD45: ★★★ | AE45: 内部管理 | AI45: 龚芬芬 | AJ45: 龚芬芬 | AK45: 郭梓樱 | AL45: =VLOOKUP(G45,'[1]指标体系-教育'!G:G,1,0)=G45 -> TRUE | AM45: 否 | AN45: =AN44 -> #REF! | AO45: 是 | AP45: 是 | AQ45: 二期
A46: 营销 | B46: 强化业务拓展跟进 | D46: 业务拓展分析 | E46: 样机分析 | F46: 一级指标 | G46: 样机在外率 | H46: 样机在外量占申请比例 | I46: 样机在外量/样机申请量 | J46: 样机在外率=样机在外量/样机申请量 1.样机在外量 CRM-样机管理-借用单： 筛选【单据状态】为““已完成”,'审核中'，【实发型号】+产品维 对应的商务产品标签类为‘整机’的数据，汇总【实发数量】-【实际归还数量】 2.样机申请量 CRM-样机管理-借用单 【单据状态】为“已完成”,'审核中'，【样机来源】不包含“转借样机”，【实发型号】+产品维 对应的商务产品标签类为‘整机’的数据，汇总【实发数量】 维度： 1.期间：【申请日期】 2.事业部/区域/办事处：【保管人】组织架构的【事业部】【区域】【省份】 3.人员：【保管人】 4.客户借机：客户【借用方】 5.系列/产品型号：【产品系列】【销售型号】 6.用途：【借机用途】 | K46: √ | L46: √ | N46: √ | O46: √ | P46: √ | Q46: √ | R46: √ | S46: √ | T46: √ | V46: √ | Y46: √ | Z46: % | AA46: 日/周/月/季/年 | AB46: 无小数点 | AC46: CRM | AD46: ★★★ | AE46: 内部管理 | AI46: 龚芬芬 | AJ46: 龚芬芬 | AK46: 郭梓樱 | AL46: =VLOOKUP(G46,'[1]指标体系-教育'!G:G,1,0)=G46 -> #N/A | AM46: 否 | AN46: =AN45 -> #REF! | AO46: 是 | AP46: 是 | AQ46: 二期
A47: 营销 | B47: 强化业务拓展跟进 | D47: 业务拓展分析 | E47: 样机分析 | F47: 一级指标 | G47: 样机逾期率 | H47: 样机逾期量占在外量比例 | I47: 样机逾期量/样机在外量 | J47: 1.样机在外量 CRM-样机管理-借用单 筛选【单据状态】为“已完成”,'审核中'，，【实发型号】+产品维 对应的商务产品标签类为‘整机’的数据，汇总【实发数量】-【实际归还数量】 2.样机逾期量 CRM-样机管理-借用单 【单据状态】为“已完成”,'审核中'，【实发型号】+产品维 对应的商务产品标签类为‘整机’的数据，【预计归还日期】<当天，汇总【实发数量】-【实际归还数量】 如下逾期规则销管已提需求在CRM实现 1）逾期规则：大客6个月，其他3个月，不含渠道样机、天使用户试用、及XX部门-展厅样机。 大客-【事业部】为“大客户平台”，其他-【事业部】为“大客户平台”之外的； 放样周期-【申请日期】为基准，到当前时间，是否超过3/6个月 渠道样机、天使用户试用-【借用用途】为渠道样机与天使用户试用 XX部门-展厅样机- 【保管人】对应组织架构为渠道平台/售前支持部/品牌市场中心，【借用用途】为展厅样机 ------------------------------------教育原始需求 在外样机数量 样机借用报表： 1.筛选教育的公司（北京视源、苏州视源、视睿）——筛选【是否整机】是 ——【是否归还选择】否——查询——导出 2.导出数据后：筛选归属教育的【事业部】——筛选归属教育的【管辖部门】——筛选【单据状态】（制单中都删除，审核中的，如果来源是样机转借，保留；如果是正常借机，已发货的产品行保留，其他删除）——汇总【未归还数量】 根据表格中字段【是否超期】判断，是，就是超期，否就是未超期 判断规则：当前日期超过预计归还日期，超期；当前日期小于预计归还日期，未超期 汇总【未归还数量】 | K47: √ | L47: √ | N47: √ | O47: √ | P47: √ | Q47: √ | R47: √ | S47: √ | T47: √ | V47: √ | Z47: % | AA47: 日/周/月/季/年 | AB47: 两位小数点 | AC47: CRM | AD47: ★★★ | AE47: 内部管理 | AI47: 龚芬芬 | AJ47: 龚芬芬 | AK47: 郭梓樱 | AL47: =VLOOKUP(G47,'[1]指标体系-教育'!G:G,1,0)=G47 -> TRUE | AM47: 否 | AN47: =AN46 -> #REF! | AO47: 是 | AP47: 是 | AQ47: 二期
B48: 强化业务拓展跟进 | D48: 业务拓展分析 | E48: 样机分析 | F48: 一级指标 | G48: 样机处理率 | H48: 样机处理量占样机申请量 | I48: 样机处理量/样机申请量 | J48: 样机处理率=样机处理量/样机申请量 1.样机处理量 CRM-样机管理-归还单 筛选【单据状态】为“已完成”,'审核中'，【产品型号】+产品维 对应的商务产品标签类为‘整机’的数据，汇总【实际归还数量】 2.样机申请量 CRM-样机管理-借用单： 筛选【单据状态】为“已完成”,'审核中'，【样机来源】不包含“转借样机”，【实发型号】+产品维 对应的商务产品标签类为‘整机’的数据，汇总【实发数量】 维度： 1.期间：【审核完成时间】 2.事业部/区域/办事处：【保管人】组织架构的【事业部】【区域】【省份】 3.人员：【保管人】 4.客户借机：客户【借用方】 5.系列/产品型号：【产品系列】【销售型号】 6.用途：【归还类型】 | K48: √ | L48: √ | N48: √ | O48: √ | P48: √ | Q48: √ | R48: √ | S48: √ | T48: √ | V48: √ | Y48: √ | Z48: % | AA48: 日/周/月/季/年 | AB48: 两位小数点 | AC48: CRM | AD48: ★★★ | AJ48: 潘敏君 | AP48: 是 | AQ48: 二期
B49: 强化业务拓展跟进 | D49: 业务拓展分析 | E49: 样机分析 | F49: 一级指标 | G49: 样机剩余率 | H49: 剩余额度占总额度 | I49: 样机剩余额度/样机总额度 | J49: 样机剩余率=样机剩余额度/样机额度 1.样机剩余额度=样机额度-样机申请量 2、样机额度：手工导入 3、样机申请量 CRM-样机管理-借用单： 筛选【单据状态】为“已完成”,'审核中'，【样机来源】不包含“转借样机”，【实发型号】+产品维 对应的商务产品标签类为‘整机’的数据，汇总【实发数量】 维度： 1.期间：【发货日期】 2.事业部/区域/办事处：【经销商名称】对应的【区域】、【省份】 4.客户：【经销商名称】 5.产品型号：【销售型号】 | K49: √ | L49: √ | N49: √ | O49: √ | P49: √ | Q49: √ | R49: √ | S49: √ | T49: √ | V49: √ | Y49: √ | Z49: % | AA49: 日/周/月/季/年 | AB49: 两位小数点 | AC49: CRM | AD49: ★★★ | AJ49: 潘敏君 | AP49: 是 | AQ49: 二期
B50: 强化业务拓展跟进 | D50: 业务拓展分析 | E50: 样机分析 | F50: 一级指标 | G50: 样机申请量（针对渠道样机表单） | H50: 渠道样机申请量 | J50: 1.渠道样机申请量 CRM-样机管理-样机借用-门户样机激活信息：筛选【已发货】为“是”的数据，汇总【实发数量】 维度： 1.期间：【发货日期】 2.事业部/区域/办事处：根据【经销商名称】匹配”经销商申请"表中【开拓销售】，根据【开拓销售】录入数据时组织架构对应的事业部、区域、办事处 4.客户：【经销商名称】 5.产品型号：【销售型号】 | K50: √ | L50: √ | N50: √ | R50: √ | S50: √ | T50: √ | Z50: 台 | AA50: 日/周/月/季/年 | AB50: 两位小数点 | AC50: CRM | AD50: ★★★ | AJ50: 潘敏君 | AP50: 是 | AQ50: 二期
B51: 强化业务拓展跟进 | D51: 业务拓展分析 | E51: 样机分析 | F51: 一级指标 | G51: 样机激活量（针对渠道样机表单） | H51: 渠道样机激活量 | J51: 1、渠道样机激活量 CRM-样机管理-样机借用-门户样机激活信息：筛选【已激活】为“是”的数据，汇总【实发数量】 维度： 1.期间：【发货日期】 2.事业部/区域/办事处：根据【经销商名称】匹配”经销商申请"表中【开拓销售】，根据【开拓销售】录入数据时组织架构对应的事业部、区域、办事处 4.客户：【经销商名称】 5.产品型号：【销售型号】 | K51: √ | L51: √ | N51: √ | R51: √ | S51: √ | T51: √ | Z51: 台 | AA51: 日/周/月/季/年 | AB51: 两位小数点 | AC51: CRM | AD51: ★★★ | AJ51: 潘敏君 | AP51: 是 | AQ51: 二期
B52: 强化业务拓展跟进 | D52: 业务拓展分析 | E52: 样机分析 | F52: 一级指标 | G52: 样机转销量（针对渠道样机表单） | H52: 渠道样机转销量 | J52: 1渠道.样机转销量 CRM-样机管理-样机借用-门户样机激活信息：筛选【已转销】为“是”的数据，汇总【实发数量】 维度： 1.期间：【发货日期】 2.事业部/区域/办事处：根据【经销商名称】匹配”经销商申请"表中【开拓销售】，根据【开拓销售】录入数据时组织架构对应的事业部、区域、办事处 4.客户：【经销商名称】 5.产品型号：【销售型号】 | K52: √ | L52: √ | N52: √ | R52: √ | S52: √ | T52: √ | Z52: 台 | AA52: 日/周/月/季/年 | AB52: 两位小数点 | AC52: CRM | AD52: ★★★ | AJ52: 潘敏君 | AP52: 是 | AQ52: 二期
B53: 强化业务拓展跟进 | D53: 业务拓展分析 | E53: 样机分析 | F53: 一级指标 | G53: 样机申请率（针对渠道样机表单） | H53: 渠道样机申请金额占渠道样机总额度 | I53: 渠道样机申请金额/渠道样机总额度 | J53: 需导入数据：渠道样机押金、渠道样机额度 渠道样机申请率=渠道样机申请金额/渠道样机总额度 1.渠道样机申请金额=申请量*样机押金 CRM-样机管理-样机借用-门户样机激活信息：筛选【已发货】为“是”，汇总【实发数量】*样机押金 根据销售型号获取对应的样机押金 2.渠道样机额度手工导入 维度： 1.期间：【发货日期】 2.事业部/区域/办事处：根据【经销商名称】匹配”经销商申请"表中【开拓销售】，根据【开拓销售】录入数据时组织架构对应的事业部、区域、办事处 4.客户：【经销商名称】 5.产品型号：【销售型号】 | K53: √ | L53: √ | N53: √ | R53: √ | S53: √ | T53: √ | Z53: % | AA53: 日/周/月/季/年 | AB53: 两位小数点 | AC53: CRM | AD53: ★★★ | AJ53: 潘敏君 | AP53: 是 | AQ53: 二期
B54: 强化业务拓展跟进 | D54: 业务拓展分析 | E54: 样机分析 | F54: 一级指标 | G54: 样机激活率（针对渠道样机表单） | H54: 渠道样机激活量占渠道样机申请量 | I54: 渠道样机激活率=渠道样机激活量/渠道样机申请量 | J54: 渠道样机激活率=渠道样机激活量/渠道样机申请量 1.渠道样机激活量 CRM-样机管理-样机借用-门户样机激活信息：筛选【已激活】为“是”，汇总【实发数量】 2.渠道样机申请量 CRM-样机管理-样机借用-门户样机激活信息：筛选【已发货】为“是”的数据，汇总【实发数量】 维度： 1.期间：【发货日期】 2.事业部/区域/办事处：根据【经销商名称】匹配”经销商申请"表中【开拓销售】，根据【开拓销售】录入数据时组织架构对应的事业部、区域、办事处 4.客户：【经销商名称】 5.产品型号：【销售型号】 | K54: √ | L54: √ | N54: √ | R54: √ | S54: √ | T54: √ | Z54: % | AA54: 日/周/月/季/年 | AB54: 两位小数点 | AC54: CRM | AD54: ★★★ | AJ54: 潘敏君 | AP54: 是 | AQ54: 二期
B55: 强化业务拓展跟进 | D55: 业务拓展分析 | E55: 样机分析 | F55: 一级指标 | G55: 样机转销率（针对渠道样机表单） | H55: 渠道样机转销金额占发货金额比例 | I55: 渠道样机转销金额/渠道样机申请金额 | J55: 渠道样机转销率=渠道样机转销金额/渠道样机申请金额 1.渠道样机转销金额 CRM-样机管理-样机借用-门户样机激活信息：筛选【已转销】为“是”，根据【销售型号】及对应的押金金额汇总总金额（押金金额手工导入） 2.渠道样机申请金额 CRM-样机管理-样机借用-门户样机激活信息：筛选【已发货】为“是”，根据【销售型号】及对应的押金金额汇总总金额（押金金额手工导入） 维度： 1.期间：【发货日期】 2.事业部/区域/办事处：根据【经销商名称】匹配”经销商申请"表中【开拓销售】，根据【开拓销售】录入数据时组织架构对应的事业部、区域、办事处 4.客户：【经销商名称】 5.产品型号：【销售型号】 | K55: √ | L55: √ | N55: √ | R55: √ | S55: √ | T55: √ | Z55: % | AA55: 日/周/月/季/年 | AB55: 两位小数点 | AC55: CRM | AD55: ★★★ | AJ55: 潘敏君 | AP55: 是 | AQ55: 二期
B56: 强化业务拓展跟进 | D56: 业务拓展分析 | E56: 样机分析 | F56: 一级指标 | G56: 样机剩余率（针对渠道样机表单） | H56: 渠道样机剩余额度占发货量比例 | I56: 渠道样机剩余额度/渠道样机总额度 | J56: 渠道样机剩余率=渠道样机剩余额度/渠道样机额度 1、渠道样机剩余额度=渠道样机额度-渠道样机申请金额 2、渠道样机额度：手工导入 3、渠道样机申请金额 CRM-样机管理-样机借用-门户样机激活信息：筛选【已发货】为“是”，根据【销售型号】及对应的押金金额汇总总金额（押金金额手工导入） 维度： 1.期间：【发货日期】 2.事业部/区域/办事处：根据【经销商名称】匹配”经销商申请"表中【开拓销售】，根据【开拓销售】录入数据时组织架构对应的事业部、区域、办事处 4.客户：【经销商名称】 5.产品型号：【销售型号】 | K56: √ | L56: √ | N56: √ | R56: √ | S56: √ | T56: √ | Z56: % | AA56: 日/周/月/季/年 | AB56: 两位小数点 | AC56: CRM | AD56: ★★★ | AJ56: 潘敏君 | AP56: 是 | AQ56: 二期
A57: 营销 | B57: 强化业务拓展跟进 | D57: 业务拓展分析 | E57: 线索分析 | F57: 一级指标 | G57: 有效线索率 | H57: 有效线索数量占总线索数量比例 | I57: 有效线索量/总线索量 | J57: 线索有效率=有效线索量/总线索量 1.总线索量 SCRM-线索管理：【线索编号】计数 2.有效线索量 SCRM-线索管理：【线索状态】为“有效线索” 维度： 1.期间：【产生时间】 2.事业部/区域/办事处：【渠道经理】或【销售名称】为“张娉娉”则为电商事业部，剩余根据【大区】、【办事处】判断 3.人员：【销售名称】 4.来源：先按【信息来源】，若【信息来源】为空，取【线索来源】 | K57: √ | L57: √ | R57: √ | S57: √ | V57: √ | Z57: % | AA57: 日/周/月/季/年 | AB57: 两位小数点 | AC57: SCRM | AD57: ★★★ | AE57: 内部管理 | AI57: 龚芬芬 | AJ57: 龚芬芬 | AK57: 陈亚婕 | AL57: =VLOOKUP(G57,'[1]指标体系-教育'!G:G,1,0)=G57 -> #N/A | AM57: 否 | AN57: =AN47 -> #REF! | AP57: 是 | AQ57: 二期
A58: 营销 | B58: 强化业务拓展跟进 | D58: 业务拓展分析 | E58: 线索分析 | F58: 一级指标 | G58: 及时线索率 | H58: 及时处理线索数量占总线索数量比例 | I58: 及时线索量/总线索量 | J58: 线索及时率=及时线索量/总线索量 1.总线索量 SCRM-线索管理：【线索编号】计数 2.及时线索量 【单据状态】为“已关闭”“已完成”,【最后修改时间】-【产生时间】<=2的数据，将【线索编号】计数 维度： 1.期间：【产生时间】 2.事业部/区域/办事处：【渠道经理】或【销售名称】为“张娉娉”则为电商事业部，剩余根据【大区】、【办事处】判断 3.人员：【销售名称】 4.来源：先按【信息来源】，若【信息来源】为空，取【线索来源】 | K58: √ | L58: √ | R58: √ | S58: √ | V58: √ | Z58: % | AA58: 日/周/月/季/年 | AB58: 两位小数点 | AC58: SCRM | AD58: ★★★ | AE58: 内部管理 | AI58: 龚芬芬 | AJ58: 龚芬芬 | AK58: 陈亚婕 | AL58: =VLOOKUP(G58,'[1]指标体系-教育'!G:G,1,0)=G58 -> #N/A | AM58: 否 | AN58: =AN57 -> #REF! | AP58: 是 | AQ58: 二期
B59: 强化业务拓展跟进 | D59: 业务拓展分析 | E59: 线索分析 | F59: 一级指标 | G59: 重复线索条量 | H59: 重复线索量 | J59: 1.重复线索量 SCRM-线索管理：【无效原因】中包含“重复”关键字，按【线索编号】计数 维度： 1.期间：【产生时间】 2.事业部/区域/办事处：【渠道经理】或【销售名称】为“张娉娉”则为电商事业部，剩余根据【大区】、【办事处】判断 3.人员：【销售名称】 4.来源：先按【信息来源】，若【信息来源】为空，取【线索来源】 | K59: √ | L59: √ | R59: √ | S59: √ | Z59: 条 | AA59: 日/周/月/季/年 | AB59: 整数 | AC59: SCRM | AI59: 潘敏君 | AP59: 是 | AQ59: 二期
B60: 强化业务拓展跟进 | D60: 业务拓展分析 | E60: 线索分析 | F60: 一级指标 | G60: 已处理线索量 | H60: 已处理线索量 | J60: 1.已处理线索量 SCRM-线索管理：【单据状态】为“跟进中”“已关闭”“已完成”，按【线索编号】计数 维度： 1.期间：【产生时间】 2.事业部/区域/办事处：【渠道经理】或【销售名称】为“张娉娉”则为电商事业部，剩余根据【大区】、【办事处】判断 3.人员：【销售名称】 4.来源：先按【信息来源】，若【信息来源】为空，取【线索来源】 | K60: √ | L60: √ | R60: √ | S60: √ | Z60: 条 | AA60: 日/周/月/季/年 | AB60: 整数 | AC60: SCRM | AI60: 潘敏君 | AP60: 是 | AQ60: 二期
B61: 强化业务拓展跟进 | D61: 业务拓展分析 | E61: 线索分析 | F61: 一级指标 | G61: 已结束线索量 | H61: 已结束线索量 | J61: 1.已结束线索量 SCRM-线索管理：【单据状态】为“已关闭”“已完成”，按【线索编号】计数 维度： 1.期间：【产生时间】 2.事业部/区域/办事处：【渠道经理】或【销售名称】为“张娉娉”则为电商事业部，剩余根据【大区】、【办事处】判断 3.人员：【销售名称】 4.来源：先按【信息来源】，若【信息来源】为空，取【线索来源】 | K61: √ | L61: √ | R61: √ | S61: √ | Z61: 条 | AA61: 日/周/月/季/年 | AB61: 整数 | AC61: SCRM | AI61: 潘敏君 | AP61: 是 | AQ61: 二期
B62: 强化业务拓展跟进 | D62: 业务拓展分析 | E62: 线索分析 | F62: 一级指标 | G62: 有效线索量 | H62: 有效线索量 | J62: 1.有效线索量 SCRM-线索管理：【线索状态】为“有效线索”，按【线索编号】计数 维度： 1.期间：【产生时间】 2.事业部/区域/办事处：【渠道经理】或【销售名称】为“张娉娉”则为电商事业部，剩余根据【大区】、【办事处】判断 3.人员：【销售名称】 4.来源：先按【信息来源】，若【信息来源】为空，取【线索来源】 | K62: √ | L62: √ | R62: √ | S62: √ | Z62: 条 | AA62: 日/周/月/季/年 | AB62: 整数 | AC62: SCRM | AI62: 潘敏君 | AP62: 是 | AQ62: 二期
B63: 强化业务拓展跟进 | D63: 业务拓展分析 | E63: 线索分析 | F63: 一级指标 | G63: 待确认线索量 | H63: 待确认线索量 | J63: 1.待确认线索量 SCRM-线索管理：【线索状态】为“待确认”，按【线索编号】计数 维度： 1.期间：【产生时间】 2.事业部/区域/办事处：【渠道经理】或【销售名称】为“张娉娉”则为电商事业部，剩余根据【大区】、【办事处】判断 3.人员：【销售名称】 4.来源：先按【信息来源】，若【信息来源】为空，取【线索来源】 | K63: √ | L63: √ | R63: √ | S63: √ | Z63: 条 | AA63: 日/周/月/季/年 | AB63: 整数 | AC63: SCRM | AI63: 车颖慧 | AP63: 是 | AQ63: 二期
A64: 营销 | B64: 强化业务拓展跟进 | D64: 业务拓展分析 | E64: 线索分析 | F64: 一级指标 | G64: 已联系有效线索率 | H64: 有效线索数量占已联系线索比例 | I64: 有效线索量/已联系线索比例 | J64: 已联系有效线索率=有效线索量/（总线索量-待确认线索量） | K64: √ | L64: √ | R64: √ | S64: √ | V64: √ | Z64: % | AA64: 日/周/月/季/年 | AB64: 两位小数点 | AC64: SCRM | AD64: ★★★ | AE64: 内部管理 | AI64: 车颖慧 | AL64: =VLOOKUP(G64,'[1]指标体系-教育'!G:G,1,0)=G64 -> #N/A | AM64: 否 | AN64: =AN54 -> 0 | AP64: 是 | AQ64: 二期
B65: 强化业务拓展跟进 | D65: 业务拓展分析 | E65: 线索分析 | F65: 一级指标 | G65: 平均时效 | H65: 线索平时处理时效 | I65: 线索处理天数汇总/已结束线索量 | J65: 平均时效=线索处理天数汇总/已结束线索量 1、线索处理天数 SCRM-线索管理：【最后修改时间】-【产生时间】 2、已结束线索量 SCRM-线索管理：【单据状态】为“已关闭”“已完成”，按【线索编号】计数 维度： 1.期间：【产生时间】 2.事业部/区域/办事处：【渠道经理】或【销售名称】为“张娉娉”则为电商事业部，剩余根据【大区】、【办事处】判断 3.人员：【销售名称】 4.来源：先按【信息来源】，若【信息来源】为空，取【线索来源】 | K65: √ | L65: √ | R65: √ | S65: √ | Z65: 天 | AA65: 日/周/月/季/年 | AB65: 整数 | AC65: SCRM | AI65: 潘敏君 | AP65: 是 | AQ65: 二期
B66: 强化业务拓展跟进 | D66: 业务拓展分析 | E66: 线索分析 | F66: 一级指标 | G66: 未处理线索量 | H66: 未处理线索量 | J66: 1.未处理线索量 SCRM-线索管理：【单据状态】为“新建”和“跟进中”，按【线索编号】计数 维度： 1.期间：【产生时间】 2.事业部/区域/办事处：【渠道经理】或【销售名称】为“张娉娉”则为电商事业部，剩余根据【大区】、【办事处】判断 3.人员：【销售名称】 4.来源：先按【信息来源】，若【信息来源】为空，取【线索来源】 | K66: √ | L66: √ | R66: √ | S66: √ | Z66: 条 | AA66: 日/周/月/季/年 | AB66: 整数 | AC66: SCRM | AI66: 潘敏君 | AP66: 是 | AQ66: 二期
B67: 强化业务拓展跟进 | D67: 业务拓展分析 | E67: 线索分析 | F67: 一级指标 | G67: 逾期线索量 | H67: 未处理线索量中，产生时间截止至今大于1天的线索量 | J67: 未处理线索量中，产生时间截止至今大于1天的线索量 1.逾期线索量 SCRM-线索管理：【单据状态】为“新建”，当前时间-【产生时间】>1D，按【线索编号】计数 维度： 1.期间：【产生时间】 2.事业部/区域/办事处：【渠道经理】或【销售名称】为“张娉娉”则为电商事业部，剩余根据【大区】、【办事处】判断 3.人员：【销售名称】 4.来源：先按【信息来源】，若【信息来源】为空，取【线索来源】 | K67: √ | L67: √ | R67: √ | S67: √ | Z67: 条 | AA67: 日/周/月/季/年 | AB67: 整数 | AC67: SCRM | AI67: 潘敏君 | AP67: 是 | AQ67: 二期
B68: 强化业务拓展跟进 | D68: 业务拓展分析 | E68: 线索分析 | F68: 一级指标 | G68: 线索处理率 | H68: 已处理线索量/总线索量 | J68: 线索处理率=已处理线索量/总线索量 1.已处理线索量 SCRM-线索管理：【单据状态】为“跟进中”“已关闭”“已完成”，按【线索编号】计数 2、.总线索量 SCRM-线索管理：【线索编号】计数 维度： 1.期间：【产生时间】 2.事业部/区域/办事处：【渠道经理】或【销售名称】为“张娉娉”则为电商事业部，剩余根据【大区】、【办事处】判断 3.人员：【销售名称】 4.来源：先按【信息来源】，若【信息来源】为空，取【线索来源】 | K68: √ | L68: √ | R68: √ | S68: √ | Z68: 条 | AA68: 日/周/月/季/年 | AB68: 整数 | AC68: SCRM | AI68: 潘敏君 | AP68: 是 | AQ68: 二期
B69: 强化业务拓展跟进 | D69: 业务拓展分析 | E69: 线索分析 | F69: 一级指标 | G69: 线索逾期率 | H69: 逾期线索量/未处理线索量 | J69: 线索逾期率=逾期线索量/未处理线索量 1、逾期线索量 SCRM-线索管理：【单据状态】为“新建”，当前时间-【产生时间】>1D，按【线索编号】计数 2、未处理线索量 SCRM-线索管理：【单据状态】为“新建”，按【线索编号】计数 维度： 1.期间：【产生时间】 2.事业部/区域/办事处：【渠道经理】或【销售名称】为“张娉娉”则为电商事业部，剩余根据【大区】、【办事处】判断 3.人员：【销售名称】 4.来源：先按【信息来源】，若【信息来源】为空，取【线索来源】 | K69: √ | L69: √ | R69: √ | S69: √ | Z69: 条 | AA69: 日/周/月/季/年 | AB69: 整数 | AC69: SCRM | AI69: 潘敏君 | AP69: 是 | AQ69: 二期
A70: 营销 | B70: 强化业务拓展跟进 | D70: 业务拓展分析 | E70: 商机分析 | F70: 一级指标 | G70: 商机完成率 | H70: 完成商机目标的比例 | I70: 商机额/商机目标 | J70: 需导入数据：商机目标 1.商机额 SCRM-渠道商机-【出货金额】/(1+当月税率) + SCRM-销售商机-【出货金额】/(1+当月税率) 【商机状态】不包含【已作废】、【已丢单】 SCRM-销售商机-【是否来自渠道】选择【否】（即和渠道商机表单数据去重） 2.商机目标手工导入 维度： 1.期间：【创建日期】 2.事业部、区域、办事处：渠道商机【渠道经理IN】+销售商机【销售】，获取对应组织架构的事业部 3.人员：销售商机【销售】 6.客户：渠道商机【核心经销商】+销售商机【经销商】 7.产品线/系列/尺寸/产品型号：根据【产品型号】+产品维获取 | K70: √ | L70: √ | N70: √ | O70: √ | P70: √ | Q70: √ | R70: √ | S70: √ | T70: √ | V70: √ | Z70: % | AA70: 日/周/月/季/年 | AB70: 两位小数点 | AC70: SCRM/导入 | AD70: ★★★ | AE70: 内部管理 | AI70: 龚芬芬 | AJ70: 龚芬芬 | AL70: 否 | AM70: 否 | AN70: =AN41 -> 业务拓展 | AP70: 是 | AQ70: 二期
A71: 营销 | B71: 强化业务拓展跟进 | D71: 业务拓展分析 | E71: 商机分析 | F71: 一级指标 | G71: 商机转化率 | H71: 商机转化为销售收入的比例 | I71: 教育：已出货金额/总金额 企服：销售额/商机额 | J71: 教育： 商机转化率=已出货金额/总金额 SCRM-教育商机管理-商机详细列表 【开标结果】不包含【丢标】【流标】【废标】 【商机状态】不包含【已作废】、【已丢单】 1、已出货金额 商机对应订单的已出货金额/(1+当月税率) 2、总金额 商机【总金额】 维度： 期间：预计出货日期 事业部-【产品线事业部】，区域-【销售所属大区】，办事处-【部门名称】，销售-【负责销售】型号-【销售型号】 注意区域只取东北、华北、华东、华南、西北、西南、华中） 企服：商机转化率=销售额/商机金额 1、销售额 EDS系统中收入明细成本表，筛选【冲销标记】不为 'Y'，【交易类型】 包含 ('',‘跨BG内部交易’)的数据的数据，按【业绩所属事业部】列中事业部对应所属BG统计,汇总【订单行折扣后不含税金额】 2、商机额 SCRM-渠道商机-【出货金额】/(1+当月税率) + SCRM-销售商机-【出货金额】/(1+当月税率) 【商机状态】不包含【已作废】、【已丢单】 SCRM-销售商机-【是否来自渠道】选择【否】（即和渠道商机表单数据去重） 维度： 期间：【创建日期】 | K71: √ | L71: √ | N71: √ | O71: √ | P71: √ | Q71: √ | R71: √ | S71: √ | T71: √ | V71: √ | Z71: % | AA71: 日/周/月/季/年 | AB71: 两位小数点 | AC71: SCRM/CRM | AD71: ★★★ | AE71: 内部管理 | AI71: 陈亚婕 | AJ71: 龚芬芬 | AK71: 陈亚婕 | AL71: =VLOOKUP(G71,'[1]指标体系-教育'!G:G,1,0)=G71 -> TRUE | AM71: 否 | AN71: =AN58 -> #REF! | AO71: 是 | AP71: 是 | AQ71: 二期
B72: 强化业务拓展跟进 | D72: 业务拓展分析 | E72: 商机分析 | F72: 一级指标 | G72: 商机条数 | H72: 商机条数 | J72: 1.商机条数 SCRM-渠道商机-统计商机条数 加上 SCRM-销售商机-统计商机条数 【商机状态】不包含【已作废】、【已丢单】 SCRM-销售商机-【是否来自渠道】选择【否】（即和渠道商机表单数据去重） 维度： 1.期间：【创建日期】 2.事业部、区域、办事处：渠道商机【渠道经理IN】+销售商机【销售】，获取对应组织架构的事业部 3.人员：销售商机【销售】 6.客户：渠道商机【核心经销商】+销售商机【经销商】 7.产品线/系列/尺寸/产品型号：根据【产品型号】+产品维获取 | K72: √ | L72: √ | N72: √ | O72: √ | P72: √ | Q72: √ | R72: √ | S72: √ | T72: √ | V72: √ | Z72: 条 | AA72: 日/周/月/季/年 | AB72: 整数 | AC72: SCRM/CRM | AD72: ★★★ | AI72: 潘敏君 | AP72: 是 | AQ72: 二期
B73: 强化业务拓展跟进 | D73: 业务拓展分析 | E73: 商机分析 | F73: 一级指标 | G73: 商机量 | H73: 商机量 | J73: 1.商机量 SCRM-渠道商机-【数量】 + SCRM-销售商机-【数量】 产品的小分类=‘LED工程屏’需按商机换算【数量】为1，一个商机1台； 【商机状态】不包含【已作废】、【已丢单】 SCRM-销售商机-【是否来自渠道】选择【否】（即和渠道商机表单数据去重） 维度： 1.期间：【创建日期】 2.事业部、区域、办事处：渠道商机【渠道经理IN】+销售商机【销售】，获取对应组织架构的事业部 3.人员：销售商机【销售】 6.客户：渠道商机【核心经销商】+销售商机【经销商】 7.产品线/系列/尺寸/产品型号：根据【产品型号】+产品维获取 | K73: √ | L73: √ | N73: √ | O73: √ | P73: √ | Q73: √ | R73: √ | S73: √ | T73: √ | V73: √ | Z73: 台 | AA73: 日/周/月/季/年 | AB73: 整数 | AC73: SCRM/CRM | AD73: ★★★ | AI73: 潘敏君 | AP73: 是 | AQ73: 二期
B74: 强化业务拓展跟进 | D74: 业务拓展分析 | E74: 商机分析 | F74: 一级指标 | G74: 商机额来源占比 | H74: 各客户类型商机来源占比 | I74: 核心商机额来源占比=核心商机额/商机总额=（渠道商机核心商机额 + 销售商机核心商机额）/商机总额 行商商机额来源占比=行商商机额/商机总额=（渠道商机行商商机额 + 销售商机行商商机额）/商机总额 二级商机额来源占比=二级商机额/商机总额=（渠道商机二级商机额 + 销售商机二级商机额）/商机总额 | J74: 商机额 商机总额：SCRM-渠道商机-【出货金额】/(1+当月税率) + SCRM-销售商机-【出货金额】/(1+当月税率) 【商机状态】不包含【已作废】、【已丢单】 SCRM-销售商机-【是否来自渠道】选择【否】（即和渠道商机表单数据去重） 核心商机额来源占比=（渠道商机核心经销商商机额 /(1+当月税率)+ 销售商机核心经销商商机额/(1+当月税率)）/商机总额 行商商机额来源占比=（渠道商机行业经销商商机额 /(1+当月税率)+ 销售商机行业经销商商机额/(1+当月税率) ）/商机总额 二级商机额来源占比=（渠道商机授权行业经销商商机额/(1+当月税率) + 渠道商机授权经销商商机额/(1+当月税率)+销售商机授权行业经销商商机额/(1+当月税率) + 销售商机授权经销商商机额/(1+当月税率)）/商机总额 1、判断“渠道商机”商机金额来源为核心/二级/行商： 优先根据【授权经销商】字段值匹配 经销商申请中的【经销商类型】，若【授权经销商】为空，根据【核心经销商】字段值匹配 经销商申请中的【经销商类型】，如经销商类型为空则归类为“授权经销商” 2、判断“销售商机”商机金额来源为核心/二级/行商： 优先根据【二级经销商】字段值匹配 经销商申请中的【经销商类型】，若【二级经销商】字段为空，根据【经销商】字段匹配 经销商申请中的【经销商类型】，如经销商类型为空且【经销商】名称不包含“视臻”并且不为空，归类为“授权经销商” | K74: √ | L74: √ | N74: √ | O74: √ | P74: √ | Q74: √ | R74: √ | S74: √ | T74: √ | V74: √ | Z74: % | AA74: 日/周/月/季/年 | AB74: 整数 | AC74: SCRM/CRM | AD74: ★★★ | AI74: 潘敏君 | AP74: 是 | AQ74: 二期
B75: 强化业务拓展跟进 | D75: 业务拓展分析 | E75: 商机分析 | F75: 一级指标 | G75: 整机数量订单转化率 | H75: 商机数量转化为订单数量的比例 | I75: 已转订单数量/商机数量 | J75: 订单数量转化率=已转订单数量/商机数量 教育：SCRM-教育商机管理-商机详细列表 【商机状态】不包含【已作废】、【已丢单】 1、已转订单数量 【开标结果】不包含【丢标】【流标】【废标】 【产品型号】+产品维 对应的商务产品标签类为‘整机’的数据，汇总商机的【已转订单数量】 2、商机数量 【产品型号】+产品维 对应的商务产品标签类为‘整机’的数据，商机【数量】 期间：【创建日期】 维度： 事业部-【产品线事业部】，区域-【销售所属大区】，办事处-【部门名称】，销售-【负责销售】型号-【销售型号】 注意区域只取东北、华北、华东、华南、西北、西南、华中） 企服： SCRM-企业商机管理-销售商机 商机状态不包含【已作废】、【已丢单】 订单数量转化率=【已转订单数量】/【商机数量】 期间：【创建日期】 | AI75: 陈亚婕 | AO75: 是 | AP75: 是 | AQ75: 二期
B76: 强化业务拓展跟进 | D76: 业务拓展分析 | E76: 商机分析 | F76: 一级指标 | G76: 主产品订单数量转化率 | H76: 商机主产品数量转化为订单数量的比例 | I76: 已转订单数量/商机数量 | J76: 订单数量转化率=已转订单数量/商机数量 教育：SCRM-教育商机管理-商机详细列表 【商机状态】不包含【已作废】、【已丢单】 1、已转订单数量 【开标结果】不包含【丢标】【流标】【废标】 【产品型号】+产品维 对应的主产品为'是'的数据，汇总商机的【已转订单数量】 2、商机数量 【产品型号】+产品维 对应的主产品为'是'的数据，商机【数量】 期间：【创建日期】 维度： 事业部-【产品线事业部】，区域-【销售所属大区】，办事处-【部门名称】，销售-【负责销售】型号-【销售型号】 注意区域只取东北、华北、华东、华南、西北、西南、华中） 企服： SCRM-企业商机管理-销售商机 商机状态不包含【已作废】、【已丢单】 订单数量转化率=【已转订单数量】/【商机数量】 期间：【创建日期】 | AI76: 陈亚婕 | AO76: 是 | AP76: 是 | AQ76: 二期
B77: 强化业务拓展跟进 | D77: 业务拓展分析 | E77: 商机分析 | F77: 一级指标 | G77: 订单金额转化率 | H77: 商机金额转化为订单金额的比例 | I77: 教育：已转订单金额/商机总额 企服：已转订单金额/出货金额 | J77: 订单金额转化率=已转订单金额/总金额 教育：SCRM-教育商机管理-商机详细列表 【商机状态】不包含【已作废】、【已丢单】 【开标结果】不包含【丢标】【流标】【废标】 1、已转订单金额 汇总商机的【已转订单数量】*单价/(1+当月税率) 2、总金额 商机【总金额】 维度： 期间：【创建日期】 事业部-【产品线事业部】，区域-【销售所属大区】，办事处-【部门名称】，销售-【负责销售】型号-【销售型号】 注意区域只取东北、华北、华东、华南、西北、西南、华中） 企业服务： 企服：SCRM-企业商机管理-销售商机 商机状态不包含【已作废】、【已丢单】 订单金额转化率=（【已转订单数】*【出货单价】/(1+当月税率)）/（【出货金额】/(1+当月税率)） 维度： 期间：【创建日期】 | AI77: 陈亚婕 | AO77: 是 | AP77: 是 | AQ77: 二期
A78: 营销 | B78: 强化业务拓展跟进 | D78: 业务拓展分析 | E78: 商机分析 | F78: 核心指标 | G78: 商机储备整机数量 | H78: 商机项目整机数量（分阶段） | I78: 商机项目数量（分阶段） | J78: SCRM-教育商机管理-商机详细列表， 【商机状态】不包含【已作废】、【已丢单】 【是否转订单】：否， 【开标结果】不包含【丢标】【流标】【废标】 【商机阶段】不包含【已出货】 【产品型号】+产品维 对应的商务产品标签类为‘整机’的数据 按商机阶段汇总【数量】值 维度： 期间：【创建日期】 事业部-【产品线事业部】，区域-【销售所属大区】，办事处-【部门名称】，销售-【负责销售】型号-【销售型号】 注意区域只取东北、华北、华东、华南、西北、西南、华中） | K78: √ | L78: √ | N78: √ | O78: √ | P78: √ | Q78: √ | R78: √ | S78: √ | T78: √ | V78: √ | Z78: 万元 | AA78: 日/周/月/季/年 | AB78: 无小数点 | AC78: SCRM | AD78: ★★★ | AE78: 内部管理 | AI78: 陈亚婕 | AK78: 陈亚婕 | AL78: 否 | AM78: 否 | AN78: 业务拓展 | AO78: 是 | AQ78: 二期
A79: 营销 | B79: 强化业务拓展跟进 | D79: 业务拓展分析 | E79: 商机分析 | F79: 核心指标 | G79: 商机储备主产品数量（分阶段） | H79: 商机项目主产品数量（分阶段） | I79: 商机项目数量（分阶段） | J79: SCRM-教育商机管理-商机详细列表， 【商机状态】不包含【已作废】、【已丢单】 【是否转订单】：否， 【开标结果】不包含【丢标】【流标】【废标】 【商机阶段】不包含【已出货】 【产品型号】+产品维 对应的主产品为‘是’的数据 按商机阶段汇总【数量】值 维度： 期间：【创建日期】 事业部-【产品线事业部】，区域-【销售所属大区】，办事处-【部门名称】，销售-【负责销售】型号-【销售型号】 注意区域只取东北、华北、华东、华南、西北、西南、华中） | K79: √ | L79: √ | N79: √ | O79: √ | P79: √ | Q79: √ | R79: √ | S79: √ | T79: √ | V79: √ | Z79: 万元 | AA79: 日/周/月/季/年 | AB79: 无小数点 | AC79: SCRM | AD79: ★★★ | AE79: 内部管理 | AI79: 陈亚婕 | AK79: 陈亚婕 | AL79: 否 | AM79: 否 | AN79: 业务拓展 | AO79: 是 | AQ79: 二期
B80: 强化业务拓展跟进 | D80: 业务拓展分析 | E80: 商机分析 | F80: 核心指标 | G80: 商机储备金额（分阶段） | H80: 商机项目金额（分阶段） | I80: 商机项目金额（分阶段） | J80: SCRM-教育商机管理-商机详细列表， 【商机状态】不包含【已作废】、【已丢单】 【是否转订单】：否， 【开标结果】不包含【丢标】【流标】【废标】 【商机阶段】不包含【已出货】 【产品型号】+产品维 按商机阶段汇总【总金额】/(1+当月税率)值 见分析表单 维度： 期间：【创建日期】 事业部-【产品线事业部】，区域-【销售所属大区】，办事处-【部门名称】，销售-【负责销售】型号-【销售型号】 注意区域只取东北、华北、华东、华南、西北、西南、华中） | Z80: 万元 | AI80: 陈亚婕 | AK80: 陈亚婕 | AL80: 否 | AM80: 否 | AN80: 业务拓展 | AO80: 是 | AQ80: 二期
B81: 强化业务拓展跟进 | D81: 业务拓展分析 | E81: 商机分析 | F81: 核心指标 | G81: 过期商机 | H81: 过期商机 | I81: 过期商机 | J81: 报表来源：SCRM-教育商机管理-商机详细列表； 筛选：①【开标结果】不包含【丢标】【流标】【废标】；②【商机状态】不包含【已作废】、【已丢单】 ；③【是否转订单】：否；④【商机阶段】不包含【已出货】； 过期商机：【预计出货时间】<所选年份月份；汇总金额
B82: 强化业务拓展跟进 | D82: 业务拓展分析 | E82: 商机分析 | F82: 核心指标 | G82: 已中标预计出货量（分预计出货期间） | H82: 已中标商机预计出货整机数量（分预计出货期间） | I82: 商机项目数量（分预计出货期间） | J82: SCRM-教育商机管理-商机详细列表， 【商机状态】不包含【已作废】、【已丢单】 【是否转订单】：否， 【开标结果】不包含【丢标】【流标】【废标】 【商机阶段】：【已开标】 【产品型号】+产品维 对应的商务产品标签类为‘整机’的数据 按【预计出货时间】汇总【数量】值 当月：【预计出货时间】=所选年份月份 N+1：【预计出货时间】=（所选年份月份+所选年份月份后1月） 维度： 期间：预计出货时间 事业部-【产品线事业部】，区域-【销售所属大区】，办事处-【部门名称】，销售-【负责销售】型号-【销售型号】 注意区域只取东北、华北、华东、华南、西北、西南、华中） | K82: √ | L82: √ | N82: √ | O82: √ | P82: √ | Q82: √ | R82: √ | S82: √ | T82: √ | V82: √ | Z82: 万元 | AA82: 日/周/月/季/年 | AB82: 无小数点 | AC82: SCRM | AI82: 陈亚婕 | AL82: 否 | AM82: 否 | AN82: 业务拓展 | AO82: 是 | AQ82: 二期
B83: 强化业务拓展跟进 | D83: 业务拓展分析 | E83: 商机分析 | F83: 核心指标 | G83: 已中标预计出货量（分预计出货期间） | H83: 已中标商机预计出货主产品数量（分预计出货期间） | I83: 商机项目主产品数量（分预计出货期间） | J83: SCRM-教育商机管理-商机详细列表， 【商机状态】不包含【已作废】、【已丢单】 【是否转订单】：否， 【开标结果】不包含【丢标】【流标】【废标】 【商机阶段】：【已开标】 【产品型号】+产品维 对应的主产品为‘是’的数据 按【预计出货时间】汇总【数量】值 预计出货时间处理为月度和季度：Q1/Q2/Q3/Q4 维度： 期间：预计出货时间 事业部-【产品线事业部】，区域-【销售所属大区】，办事处-【部门名称】，销售-【负责销售】型号-【销售型号】 注意区域只取东北、华北、华东、华南、西北、西南、华中） | K83: √ | L83: √ | N83: √ | O83: √ | P83: √ | Q83: √ | R83: √ | S83: √ | T83: √ | V83: √ | Z83: 万元 | AA83: 日/周/月/季/年 | AB83: 无小数点 | AC83: SCRM | AI83: 陈亚婕 | AL83: 否 | AM83: 否 | AN83: 业务拓展 | AO83: 是 | AQ83: 二期
B84: 强化业务拓展跟进 | D84: 业务拓展分析 | E84: 商机分析 | G84: 已中标预计出货收入（分预计出货期间） | H84: 商机项目金额（分预计出货期间） | I84: 商机项目金额（分预计出货期间） | J84: SCRM-教育商机管理-商机详细列表， 【商机状态】不包含【已作废】、【已丢单】 【是否转订单】：否， 【开标结果】不包含【丢标】【流标】【废标】 【商机阶段】：【已开标】 【产品型号】+产品维 按【预计出货时间】汇总【总金额】/(1+当月税率)值 预计出货时间处理为月度和季度：Q1/Q2/Q3/Q4 维度： 期间：预计出货时间 事业部-【产品线事业部】，区域-【销售所属大区】，办事处-【部门名称】，销售-【负责销售】型号-【销售型号】 注意区域只取东北、华北、华东、华南、西北、西南、华中） | AI84: 陈亚婕 | AK84: 陈亚婕 | AL84: 否 | AM84: 否 | AN84: 业务拓展 | AO84: 是 | AQ84: 二期
B85: 强化业务拓展跟进 | D85: 业务拓展分析 | E85: 商机分析 | G85: 已中标预计本月出货收入 | J85: SCRM-教育商机管理-商机详细列表， 【商机状态】不包含【已作废】、【已丢单】 【是否转订单】：否， 【开标结果】不包含【丢标】【流标】【废标】 【商机阶段】：【已开标】 【产品型号】+产品维 按【预计出货时间】汇总【总金额】/(1+当月税率)值 预计出货时间处理为月度 维度： 期间：预计出货时间 事业部-【产品线事业部】，区域-【销售所属大区】，办事处-【部门名称】，销售-【负责销售】型号-【销售型号】 注意区域只取东北、华北、华东、华南、西北、西南、华中） | AI85: 陈亚婕 | AK85: 陈亚婕 | AL85: 否 | AM85: 否 | AN85: 业务拓展 | AO85: 是 | AQ85: 二期
A86: 营销 | B86: 强化业务拓展跟进 | D86: 业务拓展分析 | E86: 接单分析 | F86: 核心指标 | G86: 接单量 | H86: 接单整机数量 | I86: 接单整机数量 | J86: 取值来自于CRM-销售管理-内销订单管理-销售订单-客户订单 订单状态：筛选 审核通过 日期：审核通过的取合同【审批通过日期】 接单整机数量取值：【产品型号】+产品维 对应的商务产品标签类为‘整机’的数据，汇总【数量】 维度： 事业部-【产品出货所属事业部】，大区-【大区】，办事处-【部门】，销售-【销售】 型号- 【产品型号】前五位--主销售型号 企服：现有BI已配置【月接单量】 | K86: √ | L86: √ | N86: √ | O86: √ | P86: √ | Q86: √ | R86: √ | S86: √ | T86: √ | V86: √ | Z86: % | AA86: 日/周/月/季/年 | AB86: 一位小数点 | AC86: SCRM/CRM | AD86: ★★★ | AE86: 内部管理 | AI86: 陈亚婕 | AK86: 陈亚婕 | AL86: 否 | AM86: 否 | AN86: 业务拓展 | AO86: 是 | AP86: 是 | AQ86: 二期
B87: 强化业务拓展跟进 | D87: 业务拓展分析 | E87: 接单分析 | F87: 核心指标 | G87: 接单收入 | H87: 接单金额 | I87: 接单金额 | J87: 取值来自于CRM-销售管理-内销订单管理-销售订单-客户订单 订单状态：筛选 审核通过 日期：审核通过的取合同【审批通过日期】 接单金额=【折让后总金额】/（1+订单税率） 维度： 事业部-【产品出货所属事业部】，大区-【大区】，办事处-【部门】，销售-【销售】 主销售型号 | AI87: 陈亚婕 | AK87: 陈亚婕 | AL87: 否 | AM87: 否 | AN87: 业务拓展 | AO87: 是 | AP87: 是 | AQ87: 二期
B88: 强化业务拓展跟进 | D88: 业务拓展分析 | E88: 接单分析 | F88: 核心指标 | I88: 接单金额（含税） | J88: 取值来自于CRM-销售管理-内销订单管理-销售订单-客户订单 订单状态：筛选 审核通过 日期：审核通过的取合同【审批通过日期】 接单金额=【折让后总金额】 维度： 事业部-【产品出货所属事业部】，大区-【大区】，办事处-【部门】，销售-【销售】 主销售型号 | AQ88: 二期
A89: 营销 | B89: 强化业务拓展跟进 | D89: 业务拓展分析 | E89: 接单分析 | F89: 核心指标 | G89: 订单未出货数量 | H89: 订单未出货数量 | I89: 已接单未出货数量分时段 | J89: 接单未出货数量=接单整机数量-过账整机数量 取值来自于CRM-销售管理-内销发货通知管理-内销待发货查询和等待审核待发货查询 订单状态：筛选 审核通过 日期：审核通过的取合同【审批通过日期】 过账整机数量：根据合同订单行对应的【内销发货通知查询】 中筛选产品型号+产品型号维的商务标签=‘整机’的已过账数量 原有的以上数据来源是直接从BI4.0中导出【接单明细表】 计算：筛选【未出货额】，日期合同【审批通过日期】与当日日期计算出未出货天数，分出时段【30天内】【30-60天】【60-90天】【90-180天】【180天-360天】【360天以上】 维度： 事业部-【产品出货所属事业部】，大区-【大区】，办事处-【部门】，销售-【销售】 型号- 【产品型号】前五位--主销售型号 企服：现有BI已配置【未出货量】，分为本月未出货与累计未出货 | K89: √ | L89: √ | N89: √ | O89: √ | P89: √ | Q89: √ | R89: √ | S89: √ | T89: √ | V89: √ | Z89: % | AA89: 日/周/月/季/年 | AB89: 一位小数点 | AC89: SCRM/CRM | AD89: ★★★ | AE89: 内部管理 | AI89: 陈亚婕 | AK89: 陈亚婕 | AL89: 否 | AM89: 否 | AN89: 业务拓展 | AO89: 是 | AP89: 是 | AQ89: 二期
B90: 强化业务拓展跟进 | D90: 业务拓展分析 | E90: 接单分析 | F90: 核心指标 | G90: 订单未出货金额 | H90: 订单未出货金额 | I90: 已接单未出货金额 | J90: 接单未出货金额=接单金额-已发货金额 取值来自于CRM-销售管理-内销发货通知管理-内销待发货查询和等待 订单状态：筛选 审核通过 日期：审核通过的取合同【审批通过日期】 接单金额=【折让后总金额】/（1+订单税率） 已发货额：【内销发货通知查询】对应已过账数量的【销售额】/（1+订单税率） 原有的以上数据来源是直接从BI4.0中导出【接单明细表】 计算：筛选【未出货额】，日期合同【审批通过日期】与当日日期计算出未出货天数，分出时段【30天内】【30-60天】【60-90天】【90-180天】【180天-360天】【360天以上】 维度： 事业部-【产品出货所属事业部】，大区-【大区】，办事处-【部门】，销售-【销售】 型号- 【产品型号】前五位--主销售型号 企服：现有BI已配置【未出货额】，分为本月未出货与累计未出货 | K90: √ | L90: √ | M90: √ | N90: √ | P90: √ | Q90: √ | R90: √ | S90: √ | T90: √ | AI90: 陈亚婕 | AK90: 陈亚婕 | AL90: 否 | AM90: 否 | AN90: 业务拓展 | AO90: 是 | AP90: 是 | AQ90: 二期
B91: 强化业务拓展跟进 | D91: 业务拓展分析 | E91: 接单分析 | F91: 核心指标 | I91: 已接单未出货金额(含税) | J91: 接单未出货金额=接单金额-已发货金额 取值来自于CRM-销售管理-内销发货通知管理-内销待发货查询和等待 订单状态：筛选 审核通过 日期：审核通过的取合同【审批通过日期】 接单金额=【折让后总金额】 已发货额：【内销发货通知查询】对应已过账数量的【销售额】 原有的以上数据来源是直接从BI4.0中导出【接单明细表】 计算：筛选【未出货额】，日期合同【审批通过日期】与当日日期计算出未出货天数，分出时段【30天内】【30-60天】【60-90天】【90-180天】【180天-360天】【360天以上】 维度： 事业部-【产品出货所属事业部】，大区-【大区】，办事处-【部门】，销售-【销售】 型号- 【产品型号】前五位--主销售型号 企服：现有BI已配置【未出货额】，分为本月未出货与累计未出货 | AQ91: 二期
B92: 强化业务拓展跟进 | D92: 业务拓展分析 | E92: 接单分析 | F92: 核心指标 | G92: 全款未出货额 | H92: 已打款未出货金额（全款） | J92: 取值来源：CRM-财务管理-资金管理-已建单未发货报表，【资金状态】为“分配完成”,‘超额分配’，计算【已分款未发货金额】/（1+订单税率） 维度：根据销售订单的【业绩归属事业部】及【区域】判断归属
B93: 强化业务拓展跟进 | D93: 业务拓展分析 | E93: 接单分析 | F93: 核心指标 | G93: 全款未出货量 | H93: 已打款未出货数量（全款） | J93: 取值来源：CRM-财务管理-资金管理-已建单未发货报表，【资金状态】为“分配完成”,‘超额分配’，根据物料编码判断是否整机，按照“已分款未发货金额”/（订单单价-返利单价）换算整机数量，如有小数位向下取整数位 维度：根据销售订单的【业绩归属事业部】及【区域】判断归属
B94: 强化业务拓展跟进 | D94: 业务拓展分析 | E94: 接单分析 | F94: 核心指标 | G94: 定金未出货额 | H94: 已打款未出货金额（定金） | J94: 取值来源：CRM-财务管理-资金管理-已建单未发货报表，【资金状态】为“部分分配”，计算【已分款未发货金额】/（1+订单税率） 维度：根据销售订单的【业绩归属事业部】及【区域】判断归属
B95: 强化业务拓展跟进 | D95: 业务拓展分析 | E95: 接单分析 | F95: 核心指标 | G95: 90天内订单储备 | J95: 同上，未出货天数分出时段后=30天内+30-60天+90天 的已接单未出货金额 | AQ95: 二期
B96: 强化业务拓展跟进 | D96: 业务拓展分析 | E96: 商机分析 | F96: 一级指标 | G96: 商机预测达成率 | H96: 商机预计本期出货实际在当月出货的比率 | I96: 已出货金额/预计出货商机金额 | J96: SCRM-教育商机管理-商机详细列表， 【商机状态】不包含【已作废】、【已丢单】 【开标结果】不包含【丢标】【流标】【废标】 按【预计出货时间】汇总【总金额】/(1+当月税率)值 预计出货时间处理为月度和季度：Q1/Q2/Q3/Q4 计算逻辑：按照商机行，已出货金额/预计当期出货商机 维度： 期间：预计出货时间 事业部-【产品线事业部】，区域-【销售所属大区】，办事处-【部门名称】，销售-【负责销售】型号-【销售型号】 注意区域只取东北、华北、华东、华南、西北、西南、华中） | K96: √ | L96: √ | M96: √ | N96: √ | P96: √ | Q96: √ | R96: √ | S96: √ | T96: √ | AI96: 陈亚婕 | AK96: 陈亚婕 | AO96: 是 | AQ96: 二期
B97: 强化业务拓展跟进 | D97: 业务拓展分析 | E97: 商机分析 | F97: 一级指标 | G97: 订单转出货率 | H97: 订单转化为出货收入 | I97: 已出货金额/已转订单金额 | J97: 订单转出货率=已出货金额/商机已转订单金额 教育：SCRM-教育商机管理-商机详细列表 1、已出货金额 汇总商机的【已出货金额】/(1+当月税率) 已转订单金额 汇总商机的【已转订单数量】*单价/(1+当月税率) 维度： 期间：【创建日期】 事业部-【产品线事业部】，区域-【销售所属大区】，办事处-【部门名称】，销售-【负责销售】型号-【销售型号】 注意区域只取东北、华北、华东、华南、西北、西南、华中） | K97: √ | L97: √ | M97: √ | N97: √ | P97: √ | Q97: √ | R97: √ | S97: √ | T97: √ | AI97: 陈亚婕 | AK97: 陈亚婕 | AO97: 是 | AQ97: 二期
B98: 强化业务拓展跟进 | D98: 业务拓展分析 | E98: 商机分析 | F98: 一级指标 | G98: 最小商机转化率 | H98: 现有的商机和订单支撑预测达成，最小的商机转化率需多少 | I98: 最小商机转化率=（本期预测-90天内订单储备）/已中标预计本月出货商机收入 | J98: 最小商机转化率=（本期销售预测-90天内订单储备）/已中标预计本月出货商机收入 | K98: √ | L98: √ | R98: √ | S98: √ | AQ98: 二期
B99: 强化业务拓展跟进 | D99: 业务拓展分析 | E99: 商机分析 | F99: 一级指标 | G99: 预计本月落单数量 | H99: 预计本月落单数量 | J99: 数量只统计整机数量：【产品型号】+产品维 对应的商务产品标签类为‘整机’ SCRM-渠道商机-【预签日期】为本月的-统计 ‘整机’的【数量】 加上 SCRM-销售商机-【预签日期】为本月的-统计 ‘整机’【数量】 排除商机状态为【已作废】、【已丢单】 SCRM-销售商机-【是否来自渠道】选择【否】（即和渠道商机表单数据去重） 维度： 1.期间：【创建日期】 2.事业部、区域、办事处：渠道商机【渠道经理IN】+销售商机【销售】，获取对应组织架构的事业部 3.人员：销售商机【销售】 6.客户：渠道商机【核心经销商】+销售商机【经销商】 7.产品线/系列/尺寸/产品型号：根据【产品型号】+产品维获取 | K99: √ | L99: √ | R99: √ | S99: √ | AJ99: 车颖慧 | AP99: 是 | AQ99: 二期
B100: 强化业务拓展跟进 | D100: 业务拓展分析 | E100: 商机分析 | F100: 一级指标 | G100: 预计本月落单金额 | H100: 预计本月落单金额 | J100: SCRM-渠道商机-【预签日期】为本月的-统计【出货金额】 加上 SCRM-销售商机-【预签日期】为本月的-统计【出货金额】 排除商机状态为【已作废】、【已丢单】 SCRM-销售商机-【是否来自渠道】选择【否】（即和渠道商机表单数据去重） 维度： 1.期间：【创建日期】 2.事业部、区域、办事处：渠道商机【渠道经理IN】+销售商机【销售】，获取对应组织架构的事业部 3.人员：销售商机【销售】 6.客户：渠道商机【核心经销商】+销售商机【经销商】 7.产品线/系列/尺寸/产品型号：根据【产品型号】+产品维获取 | K100: √ | L100: √ | R100: √ | S100: √ | AJ100: 车颖慧 | AP100: 是 | AQ100: 二期
...

Sheet 事业部映射表（企服）
A1: 事业部 | B1: 核算事业部 | C1: 线上/线下
A2: 大客户平台 | B2: 大客户平台 | C2: 线下 | D2: 事业部映射关系关系为空，则默认为：线下
A3: CVTOUCH事业部 | B3: 电商事业部 | C3: 线上
A4: 电商部 | B4: 电商事业部 | C4: 线上
A5: 电商事业部 | B5: 电商事业部 | C5: 线上
A6: 会议ODM事业部 | B6: 渠道平台 | C6: 线下
A7: 会议事业部 | B7: 渠道平台 | C7: 线下
A8: 渠道平台 | B8: 渠道平台 | C8: 线下
A9: 金融事业部 | B9: 金融事业部 | C9: 线下
A10: 酒店地产事业部 | B10: 酒店地产事业部 | C10: 线下
A11: 军工事业部 | B11: 军工事业部 | C11: 线下
A12: 餐饮事业部 | B12: 新零售事业部 | C12: 线下
A13: 服装饰品事业部 | B13: 新零售事业部 | C13: 线下
A14: 家居建材事业部 | B14: 新零售事业部 | C14: 线下
... A25: 美业事业部 | B25: 新零售事业部 | C25: 线下

Sheet BI原型
A1: 目录页
C2: 营销
A3: 核心价值 | C3: 营收保障 | D3: 业务拓展 | E3: 运营效率提升 | I3: 客户提升 | K3: 组织能力提升
C4: 扩大营业收入 | D4: 强化业务拓展跟进 | E4: 扩大品牌认知 | F4: 提升市场运作效率 | G4: 严控费用 | H4: 提升运营效率 | I4: 提升经销商能力及效率 | J4: 优化客户结构 | K4: 提升营销人效 | L4: 增强团队能力建设
A7: 分析主题域 | C7: 收入分析 | D7: 业务拓展分析 | E7: 品牌分析 | F7: 市场分析 | G7: 费用分析 | H7: 运营效率分析 | I7: 经销商分析 | J7: 客户分析 | K7: 人效分析 | L7: 团队能力分析
A10: 分析主题 | C10: 营业收入分析 | D10: 签约分析 | E10: 品牌指数分析 | F10: 二级覆盖度 | G10: 招待费分析 | H10: 销售预测准确率分析 | I10: 渠道结构分析 | J10: 客户结构分析 | K10: 人员效率分析 | L10: 职级分析
C11: 销量分析 | D11: 商机分析 | E11: 专项曝光分析 | F11: 活动成效分析 | G11: 差旅费分析 | H11: 物流效率分析 | I11: 二级分析 | J11: 客户复购率分析
C12: 配比分析 | D12: 样机分析 | E12: 用户案例分析 | G12: 广宣费分析 | H12: 分仓效率分析 | I12: 返利分析 | J12: 客户流失分析(FML）
C13: 价格分析 | D13: 接单分析 | G13: 运输费分析 | H13: 库存周转分析 | I13: 库存分析 | J13: 定制项目投入产出分析
C14: 订单分析 | D14: 线索分析 | G14: 服务费分析 | I14: 赋能分析 | J14: 客户成单周期分析
J15: 订单分析价格
C16: 可点击跳转
A20: 分析页 | C20: 举例：营业收入分析
D21: 营业收入 | F21: 营业收入达成率 | G21: 排名 | I21: 营业收入同比
A22: 指标区
A24: 图表区
A26: （营业收入） | D26: 分BU | E26: 分办事处 | F26: 分人员 | G26: 分客户 | H26: 分产品

Sheet 日程安排
F1: 43891 | G1: 43892 | H1: 43893 | I1: 43894 | J1: 43895 | K1: 43896 | L1: 43897 | M1: 43898 | N1: 43899 | O1: 43900 | P1: 43901 | Q1: 43902 | R1: 43903 | S1: 43904 | T1: 43905 | U1: 43906 | V1: 43907 | W1: 43908 | X1: 43909 | Y1: 43910 | Z1: 43911 | AA1: 43912 | AB1: 43913 | AC1: 43914 | AD1: 43915 | AE1: 43916 | AF1: 43917 | AG1: 43918 | AH1: 43919 | AI1: 43920 | AJ1: 43921 | AK1: 43922 | AL1: 43923 | AM1: 43924 | AN1: 43925 | AO1: 43926 | AP1: 43927 | AQ1: 43928 | AR1: 43929 | AS1: 43930 | AT1: 43931 | AU1: 43932 | AV1: 43933 | AW1: 43934 | AX1: 43935 | AY1: 43936 | AZ1: 43937 | BA1: 43938 | BB1: 43939 | BC1: 43940 | BD1: 43941 | BE1: 43942 | BF1: 43943 | BG1: 43944 | BH1: 43945 | BI1: 43946 | BJ1: 43947 | BK1: 43948 | BL1: 43949 | BM1: 43950 | BN1: 43951
E2: 星期 | F2: 日 | G2: 一 | H2: 二 | I2: 三 | J2: 四 | K2: 五 | L2: 六 | M2: 日 | N2: 一 | O2: 二 | P2: 三 | Q2: 四 | R2: 五 | S2: 六 | T2: 日 | U2: 一 | V2: 二 | W2: 三 | X2: 四 | Y2: 五 | Z2: 六 | AA2: 日 | AB2: 一 | AC2: 二 | AD2: 三 | AE2: 四 | AF2: 五 | AG2: 六 | AH2: 日 | AI2: 一 | AJ2: 二 | AK2: 三 | AL2: 四 | AM2: 五 | AN2: 六 | AO2: 日 | AP2: 一 | AQ2: 二 | AR2: 三 | AS2: 四 | AT2: 五 | AU2: 六 | AV2: 日 | AW2: 一 | AX2: 二 | AY2: 三 | AZ2: 四 | BA2: 五 | BB2: 六 | BC2: 日 | BD2: 一 | BE2: 二 | BF2: 三 | BG2: 四 | BH2: 五 | BI2: 六 | BJ2: 日 | BK2: 一 | BL2: 二 | BM2: 三 | BN2: 四
A3: 序号 | B3: 项目 | C3: 责任部门 | D3: 跟进人 | E3: 进度 | F3: 3月 | AK3: 4月
F4: 1 | G4: 2 | H4: 3 | I4: 4 | J4: 5 | K4: 6 | L4: 7 | M4: 8 | N4: 9 | O4: 10 | P4: 11 | Q4: 12 | R4: 13 | S4: 14 | T4: 15 | U4: 16 | V4: 17 | W4: 18 | X4: 19 | Y4: 20 | Z4: 21 | AA4: 22 | AB4: 23 | AC4: 24 | AD4: 25 | AE4: 26 | AF4: 27 | AG4: 28 | AH4: 29 | AI4: 30 | AJ4: 31 | AK4: 1 | AL4: 2 | AM4: 3 | AN4: 4 | AO4: 5 | AP4: 6 | AQ4: 7 | AR4: 8 | AS4: 9 | AT4: 10 | AU4: 11 | AV4: 12 | AW4: 13 | AX4: 14 | AY4: 15 | AZ4: 16 | BA4: 17 | BB4: 18 | BC4: 19 | BD4: 20 | BE4: 21 | BF4: 22 | BG4: 23 | BH4: 24 | BI4: 25 | BJ4: 26 | BK4: 27 | BL4: 28 | BM4: 29 | BN4: 30
A5: 1 | B5: 梳理营销BI框架 | C5: 财务 | D5: 龚芬芬 | E5: 已完成
A6: =1+A5 -> 2 | B6: 会议：营销BI框架及指标沟通 | C6: =OFFSET($G$1,0,MATCH("★",$G6:$BO6,0)-1) -> 43893 | H6: ★
A7: =1+A6 -> 3 | B7: 梳理营销BI指标体系及优先级 | C7: 财务 | D7: 龚芬芬 | E7: 已完成
A8: =1+A7 -> 4 | B8: 整合企服教育指标，确定资源分配 | C8: IT | D8: 朱林生 | E8: 进行中
A9: =1+A8 -> 5 | B9: 会议：营销BI一期上线计划沟通 | C9: =OFFSET($G$1,0,MATCH("★",$G9:$BO9,0)-1) -> 43896 | K9: ★
A10: =1+A9 -> 6 | B10: 一期(★★★)上线准备 | C10: IT/财务 | D10: 袁红云 | E10: 未开始
A11: =1+A10 -> 7 | B11: 一期(★★)上线准备 | C11: IT/财务 | D11: 袁红云 | E11: 未开始
A12: =1+A11 -> 8 | B12: 一期(★)上线准备 | C12: IT/财务 | D12: 袁红云 | E12: 未开始
A13: =1+A12 -> 9 | B13: 营销BI一期上线及检验 | C13: IT/财务 | D13: 袁红云 | E13: 未开始
A14: =1+A13 -> 10 | B14: 会议：营销BI一期总结及二期上线沟通 | C14: =OFFSET($G$1,0,MATCH("★",$G14:$BO14,0)-1) -> 43927 | AP14: ★
A15: =1+A14 -> 11 | B15: 二期(★★★)上线准备 | C15: IT/财务 | D15: 袁红云 | E15: 未开始
A16: =1+A15 -> 12 | B16: 二期(★★)上线准备 | C16: IT/财务 | D16: 袁红云 | E16: 未开始
A17: =1+A16 -> 13 | B17: 二期(★)上线准备 | C17: IT/财务 | D17: 袁红云 | E17: 未开始
A18: =1+A17 -> 14 | B18: 营销BI二期上线及检验 | C18: IT/财务 | D18: 袁红云 | E18: 未开始
A19: =1+A18 -> 15 | B19: 会议：营销BI总结 | C19: =OFFSET($G$1,0,MATCH("★",$G19:$BO19,0)-1) -> 43951 | BN19: ★
K22: 节假日 | N22: 工作开展日 | R22: 阶段工作结束日 | V22: ★ | W22: 会议

Sheet 会议
A1: 会议时间 | B1: 会议主题 | C1: 与会人 | D1: 会议纪要 | E1: 附表 | F1: 负责人 | G1: 完成时间
A2: 2020/3/3 16:00-17:00 | B2: 营销BI框架及指标沟通 | C2: 朱林生、马兰军、梅娟娟、邓凤娟、 陈亚婕、郭梓樱、潘敏君、龚芬芬 | D2: 1.梳理一期具体指标逻辑 (模板见《指标体系》) | E2: 指标体系 | F2: 龚芬芬/潘敏君/陈亚婕 | G2: 43894
D3: 2.确定一期指标内部优先级 | E3: 指标体系 | F3: 邓凤娟/梅娟娟 | G3: 43894
A4: 2020/3/6 9:00-10:00 | B4: 营销BI一期上线计划沟通 | C4: 朱林生、马兰军、梅娟娟、邓凤娟、袁红云、陈亚婕、郭梓樱、潘敏君、龚芬芬 | D4: 1.整理不重复指标(见《指标体系》)，补充计算口径 | E4: 指标体系 | F4: 龚芬芬/潘敏君/曾丽/陈亚婕/郭梓樱 | G4: 43897
D5: 2.重新梳理优化商务价值链 | E5: 营销BI分析体系 | F5: 邓凤娟/梅娟娟/马兰军/朱林生 | G5: 43897
D6: 3.确定调研计划 | F6: 马兰军/朱林生 | G6: 43898
A7: 2020/3/10 4:00-5:00 | B7: 营销BI一期调研-营收保障 | C7: 朱林生、马兰军、梅娟娟、邓凤娟、袁红云、陈亚婕、郭梓樱、潘敏君、龚芬芬、曾丽 | D7: 【毛利率】产品线、产品型号、系列、尺寸：现不是直接获取PCBS的收入成本表，业务会手工匹配，需提供线下匹配规则； | E7: 产品目录 | F7: 潘敏君/陈亚婕 | G7: 43902
D8: 【收入达成率及排名】需根据销售目标、预算和预测分解成3个指标，销售目标、预算、预测 提供一份数据供IT参考 | E8: 3种目标 | F8: 陈亚婕 | G8: 43902
D9: 【周边配比】整机、周边、整体营业收入的定义及计算规则需补充确认 | F9: 整体=整机(仅会议平板)+周边
D10: 【低价量占比】从CRM系统“价格清单”获取核心提货价，补充完整取值表单及字段 | E10: 指标体系 | F10: 龚芬芬 | G10: 43902
D11: 【订单平均金额】确认含税销售额取值逻辑，不含税+税额还是引入税率 ——收入成本表中“税额”字段很多空值，而且显示的是内部交易的税额，并不能使用，需要引入当月税率 | E11: 指标体系 | F11: 潘敏君 | G11: 43902
D12: 整机及成品的定义，整机及周边的成品数量的计算规则，现会议有线下的对应规则，需提供线下的匹配及计算规则 | E12: 产品目录 | F12: 整机规则与产品目录一同提供
D13: 确认所有指标的计算维度是否完整，补充各计算维度的取值来源及规则，例如：期间、项目、期间、各区域、客户、办事处、人员等的字段取值来源及规则 | E13: 指标体系 | F13: 潘敏君/陈亚婕/龚芬芬 | G13: 43902
D14: 所有指标的计算口径的字段取值及逻辑补充完整；例如：剔除内部交易的逻辑规则；营业收入的取值来源需修正，保持统一； | E14: 指标体系 | F14: 潘敏君 | G14: 43902
D15: 提供PBCS的收入成本表的原表数据，数据留少量即可以便IT核对取值字段； | E15: 收入成本表 | F15: 陈亚婕 | G15: 43902
D16: 软件收入、CKD业务是否纳入考虑，计算的规则 | F16: 软件规则与产品目录一同提供
D17: 【组织架构】PBCS中事业部对应的BG现在是IT手工在BI建立映射关系，IT提供组织架构的建议解决方案 | F17: 马兰军
D18: 【低价金额占比】CRM单据记录单据对应的底价，底价现只存了含税价需如何计算不含税价（考虑税改 税率会有变化） | F18: 袁红云
A19: 2020/3/24 11:00-12:00 | B19: 教育&企服营销数字化运营项目立项会议 | C19: 马兰军 邓凤娟 袁慧君 袁红云 王子赫 曾戈 苏骏强 廖明楷 李梓铭 杨铁铮 梅娟娟 朱林生 胡明 黄逸涛 陆艳玲 范元冬 曾诚 邓毅刚 刘洋 | D19: 1. 项目经理&项目总监在项目管理上的投入人天需要增加；
D20: 2. 项目范围指标需要再沟通，财务和商务达成一致；
D21: 3. 需要关注基础数据的质量：
D22: a. 业务部分需要保证录入数据的质量；
D23: b. IT部分需要再梳理和确保系统数据逻辑和质量；
A24: 2020/3/30 11:00-12:00 | B24: 教育&企服业绩归属口径讨论 | C24: 胡明、龚芬芬、孔秀芳、朱林生、向文华、陈亚婕、梅娟娟、李荣荣、马兰军、邓凤娟、陆艳玲、杨林 | D24: 1、提供业绩归属的业务场景及具体案例，业绩计算规则 | F24: 杨林/胡明 | G24: 43921
D25: 2、补充坚果云指标框架文件中的营销业绩指标及计算口径 | E25: 指标体系 | F25: 龚芬芬 | G25: 43921
D26: 3、提供线下走JD自营业绩计算的案例及期望管控方式 | E26: 指标体系 | F26: 龚芬芬 | G26: 43921
D27: 4、确认未来教育的业绩划分规则 | F27: 陈亚婕 | G27: 43921
D28: 5、确认并提供教育返利等特殊业务场景的业绩计算规则 | F28: 陈亚婕 | G28: 43921
A29: 2020/4/11 17:30-18:30 | B29: 营销BI调研-驾驶舱 | C29: 袁红云、胡明、龚芬芬、朱林生、陈亚婕、马兰军、邓凤娟、杨林、黄逸涛 | D29: 1、提供近三年的目标，预测，预算的数据，做同期和趋势分析的时候需要用 | F29: 龚芬芬/曾丽/陈亚婕 | G29: 43934
D30: 2、和财务对接主数据项目的人沟通产品主数据的财务和商务归类规则 | F30: 龚芬芬/潘敏君/陈亚婕 | G30: 43934
D31: 3、按岗位梳理核心指标及驾驶舱的展示形式 | F31: 龚芬芬/陈亚婕 | G31: 43936
D32: 4、确认教育的佳电备货业务模式启动后 营收等指标的计算口径 | F32: 陈亚婕 | G32: 43936
A38: 3.13问题 | G38: 回复
A39: 1、销售目标的表格请帮忙提供一份，现只收到预测，预算的表，谢谢。 @陈亚婕 | F39: 陈亚婕 | G39: 请见sheet 预算预测（教育）
A40: 2、【交易类型】字段剔除“内部交易”后，【跨BG内部交易】【未来教育BG内部交易】这句话是什么意思？是指剔除【交易类型】列为“跨BG内部交易“及”未来教育BG内部交易“？ @陈亚婕 | F40: 陈亚婕 | G40: 是的
A41: 3、LED对应尺寸为工程机的数量换算为1，这个换算的维度是什么？按合同换算还是按AR事务处理换算？ @陈亚婕 | F41: 龚芬芬 | G41: 按合同，已补充
A42: 4、教育的产品映射表没有整机和周边的映射，根据什么规则判断是教育的整机、周边？ @陈亚婕 | F42: 陈亚婕 | G42: 教育整机用产品线=智能平板产品线_交互智能平板，智能平板产品线_智慧黑板，幼教产品线_幼教机,小间距LED产品线，是用产品线、系列、品类等分类，不单独分整机/周边
A43: 5、主要周边销量配比：根据周边对应的【整机型号】是指收入成本明细表的【配套整机型号】字段？ @潘敏君 | F43: 潘敏君 | G43: 按配置表确定对应整机型号，已补充
A44: 6、订单平均金额：汇总的【订单行折扣后不含税金额】列，再乘以当月税率； 当月税率系统在哪里获取？ @潘敏君 | F44: 潘敏君 | G44: EBS的AR模块中，对于每个事务处理，有对应的税率，可以根据收入成本表【事物处理编号】先抓取该订单对应的税率，然后乘以该订单【订单行折扣后不含税金额】
A45: 7、物料订单，散料CKD是否纳入计算，计算的规则，数量是否折算？ @潘敏君 @陈亚婕 | F45: 潘敏君/陈亚婕 | G45: 按照收入成本表映射，无特殊规则
A46: 8、平均单价维度有项目，项目的取值来源是什么？ @陈亚婕 | F46: 陈亚婕 | G46: 项目维度暂时取消。
A47: 9、维度有按客户、人员、区域、办事处统计，但提供的收入明细表中下单客户、销售人员、区域、办事处有为空情况，此种情况如何处理?@陈亚婕 @潘敏君 | F47: 潘敏君/陈亚婕 | G47: 企业服务按销售人员架构匹配区域，若人员/下单客户为空的统一计入渠道平台-华南-广东，已补充
A48: 10、营业收入：企业服务特例：客户分类为核心经销商、行业经销商及其他 ，是指分析维度需要增加 客户分类？ @陈亚婕 | F48: 陈亚婕 | G48: 是的，营业收入按区域、产品、客户三个主要维度展开，客户分为核心经销商、行业经销商、其他(企业服务特有)
A49: 11、2019年数据需要还原。是指按什么还原？ @陈亚婕 | F49: 陈亚婕 | G49: 2020年教育BG架构变化，需将2019年收入成本数据还原成7BU,CRM和PBCS都未还原，我们是手工还原的底稿，如果可以导入更好。
A50: 12、低价量占比：核心价从哪里取值？是指核心经销商的裸机价（核心价也区分线上、线下）？特定经销商的计算规则呢，例如京东？ @潘敏君 | F50: 龚芬芬 | G50: 统一从CRM价格清单【裸机价】取销售型号对应价格(含税)，不分线上线下和经销商类型，已补充
A51: 13、毛利率：汇总”原始不含税成本“列 提供的收入成本表无此字段，如下字段是指哪一个@潘敏君 | F51: 潘敏君 | G51: 原始合计成本，已修改

Sheet 净利润(会议)
A1: 净利润 | O1: 不含税
A2: 事业部 | B2: 区域 | C2: 2019年
C3: 1月 | D3: 2月 | E3: 3月 | F3: 4月 | G3: 5月 | H3: 6月 | I3: 7月 | J3: 8月 | K3: 9月 | L3: 10月 | M3: 11月 | N3: 12月 | O3: 合计
A4: 渠道平台 | B4: 东北区域 | O4: =SUM(C4:N4) -> 0
A5: 渠道平台 | B5: 华北区域 | O5: =SUM(C5:N5) -> 0
A6: 渠道平台 | B6: 华东区域 | O6: =SUM(C6:N6) -> 0
A7: 渠道平台 | B7: 华南区域 | O7: =SUM(C7:N7) -> 0
A8: 渠道平台 | B8: 华中区域 | O8: =SUM(C8:N8) -> 0
A9: 渠道平台 | B9: 西北区域 | O9: =SUM(C9:N9) -> 0
A10: 渠道平台 | B10: 西南区域 | O10: =SUM(C10:N10) -> 0
A11: 大客户平台 | B11: 南部区域 | O11: =SUM(C11:N11) -> 0
A12: 大客户平台 | B12: 北部区域 | O12: =SUM(C12:N12) -> 0
A13: 金融事业部 | B13: 金融事业部 | O13: =SUM(C13:N13) -> 0
A14: 军工事业部 | B14: 军工事业部 | O14: =SUM(C14:N14) -> 0
A15: 政府事业部 | B15: 政府事业部 | O15: =SUM(C15:N15) -> 0
... A22: 泛零售事业部 | B22: 泛零售事业部 | O22: =SUM(C22:N22) -> 0
B23: 合计 | C23: =SUM(C4:C22) -> 0 | D23: =SUM(D4:D22) -> 0 | E23: =SUM(E4:E22) -> 0 | F23: =SUM(F4:F22) -> 0 | G23: =SUM(G4:G22) -> 0 | H23: =SUM(H4:H22) -> 0 | I23: =SUM(I4:I22) -> 0 | J23: =SUM(J4:J22) -> 0 | ... O23: =SUM(O4:O22) -> 0

Sheet 产品目录(企服)
A1: 销售型号 | B1: 是否整机 | C1: 产品线 | D1: 产品系列大类 | E1: 产品系列 | F1: 尺寸 | G1: 备注
A2: MT08 | B2: 非整机 | C2: 周边产品 | D2: 周边产品 | E2: PC模块 | F2: 其他
A3: MT11 | B3: 非整机 | C3: 周边产品 | D3: 周边产品 | E3: PC模块 | F3: 其他
A4: MT15 | B4: 非整机 | C4: 周边产品 | D4: 周边产品 | E4: PC模块 | F4: 其他
A5: MT21 | B5: 非整机 | C5: 周边产品 | D5: 周边产品 | E5: PC模块 | F5: 其他
A6: MT21/I3 | B6: 非整机 | C6: 周边产品 | D6: 周边产品 | E6: PC模块 | F6: 其他
A7: MT21/I5 | B7: 非整机 | C7: 周边产品 | D7: 周边产品 | E7: PC模块 | F7: 其他
A8: MT21/I5 | B8: 非整机 | C8: 周边产品 | D8: 周边产品 | E8: PC模块 | F8: 其他
A9: MT21/I7 | B9: 非整机 | C9: 周边产品 | D9: 周边产品 | E9: PC模块 | F9: 其他
A10: MT21F | B10: 非整机 | C10: 周边产品 | D10: 周边产品 | E10: PC模块 | F10: 其他
A11: MT21T | B11: 非整机 | C11: 周边产品 | D11: 周边产品 | E11: PC模块 | F11: 其他
A12: MT23 | B12: 非整机 | C12: 周边产品 | D12: 周边产品 | E12: PC模块 | F12: 其他
A13: MT24 | B13: 非整机 | C13: 周边产品 | D13: 周边产品 | E13: PC模块 | F13: 其他
... A416: SC86CD | B416: 整机 | C416: 会议平板 | D416: 电商款 | E416: 三代电商S款 | F416: 86寸
A417: 14781 | B417: 整机 | C417: 会议平板 | D417: 定制 | E417: 定制 | F417: 65寸
A418: C65CA | B418: 整机 | C418: 会议平板 | D418: 定制 | E418: 定制 | F418: 65寸
A419: C65UA | B419: 整机 | C419: 会议平板 | D419: 定制 | E419: 定制 | F419: 65寸
A420: S65FD | B420: 整机 | C420: 会议平板 | D420: 定制 | E420: 定制 | F420: 65寸
A421: C75UA | B421: 整机 | C421: 会议平板 | D421: 定制 | E421: 定制 | F421: 75寸
A422: C86CA | B422: 整机 | C422: 会议平板 | D422: 定制 | E422: 定制 | F422: 86寸
A423: C86UA | B423: 整机 | C423: 会议平板 | D423: 定制 | E423: 定制 | F423: 86寸
A424: S86FD | B424: 整机 | C424: 会议平板 | D424: 定制 | E424: 定制 | F424: 86寸
A425: C65CD | B425: 整机 | C425: 会议平板 | D425: 定制 | E425: 定制 | F425: 65寸
A426: C75CA | B426: 整机 | C426: 会议平板 | D426: 定制 | E426: 定制 | F426: 75寸
A427: H84ED | B427: 整机 | C427: 其他整机 | D427: 其他整机 | E427: 海外机 | F427: 其他
A428: I65EA | B428: 整机 | C428: 其他整机 | D428: 其他整机 | E428: 海外机 | F428: 其他
A429: I65EB | B429: 整机 | C429: 其他整机 | D429: 其他整机 | E429: 海外机 | F429: 其他
... A707: U3020506 | B707: 整机 | C707: 智能镜 | D707: 智能镜 | E707: 智能镜 | F707: 其他
B708: 非整机 | C708: 周边产品 | D708: 周边产品 | E708: 软件 | F708: 其他 | G708: 物料编码006开头

Sheet 净利润（教育）
C2: 2019年
A3: 事业部 | B3: 区域 | C3: 1月 | D3: 2月 | E3: 3月 | F3: 4月 | G3: 5月 | H3: 6月 | I3: 7月 | J3: 8月 | K3: 9月 | L3: 10月 | M3: 11月 | N3: 12月 | O3: 合计
A4: 多媒体事业部 | O4: =SUM(C4:N4) -> 0
A5: 学务事业部 | O5: =SUM(C5:N5) -> 0
A6: 屏显事业部 | O6: =SUM(C6:N6) -> 0
A7: 教务事业部 | O7: =SUM(C7:N7) -> 0
A8: 录播事业部 | O8: =SUM(C8:N8) -> 0
A9: 教培事业部 | O9: =SUM(C9:N9) -> 0
A10: 幼教事业部 | O10: =SUM(C10:N10) -> 0
A11: 东北区域 | O11: =SUM(C11:N11) -> 0
A12: 华北区域 | O12: =SUM(C12:N12) -> 0
A13: 华东区域 | O13: =SUM(C13:N13) -> 0
A14: 华南区域 | O14: =SUM(C14:N14) -> 0
A15: 华中区域 | O15: =SUM(C15:N15) -> 0
... A17: 西南区域 | O17: =SUM(C17:N17) -> 0
A18: 长春办事处
A19: 哈尔滨办事处
A20: 沈阳办事处
A21: 北京办事处
A22: 石家庄办事处
A23: 太原办事处
A24: 呼和浩特办事处
A25: 西安办事处
A26: 银川办事处
A27: 兰州办事处
A28: 乌市办事处
A29: 成都办事处
... A46: 广州办事处

Sheet 产品映射表(教育)
A1: 物料编码 | B1: 产品型号 | C1: 产品线 | D1: 系列 | E1: 尺寸
A2: 001.301.0000657 | B2: X75SC-GLA210A-G | C2: 智能平板产品线_交互智能平板 | D2: X | E2: 75
A3: 001.301.0001276 | B3: L70EB-CP7S10A-G | C3: 智能平板产品线_交互智能平板 | D3: L2 | E3: 70
A4: 001.301.0001307 | B4: L55EB-CLM310A-G | C4: 智能平板产品线_交互智能平板 | D4: L2 | E4: 55
A5: 001.301.0001691 | B5: K75IB-CLA251A-G | C5: 智能平板产品线_交互智能平板 | D5: K | E5: 75
A6: 001.301.0001710 | B6: X86SD-GLA451A-G | C6: 智能平板产品线_交互智能平板 | D6: X | E6: 86
A7: 001.301.0001976 | B7: L65EC-CLM351A-G | C7: 智能平板产品线_交互智能平板 | D7: L3 | E7: 65
A8: 001.301.0002202 | B8: L75EB-CLA210A-G | C8: 智能平板产品线_交互智能平板 | D8: L2 | E8: 75
A9: 001.301.0002203 | B9: K75VC-CLA251A-G | C9: 智能平板产品线_交互智能平板 | D9: K | E9: 75
A10: 001.301.0002217 | B10: L75EC-CLA251B-G | C10: 智能平板产品线_交互智能平板 | D10: L3 | E10: 75
A11: 001.301.0002422 | B11: R86EA-CLA451A-G | C11: 智能平板产品线_交互智能平板 | D11: K | E11: 86
A12: 001.301.0002435 | B12: L55CB-CB1151A-G | C12: 智能平板产品线_交互智能平板 | D12: LC | E12: 55
A13: 001.301.0002547 | B13: L75CB-GLM151A-G | C13: 智能平板产品线_交互智能平板 | D13: LC | E13: 75
... A17: 001.301.0003168 | B17: K65CA-BO9011A-G | C17: 智能平板产品线_交互智能平板 | D17: K | E17: 65
A18: 001.315.0000001 | B18: WIB9060A-G | C18: 智能平板产品线_周边产品 | D18: (空白) | E18: (空白)
A19: 001.315.0000008 | B19: WIB9060A-G | C19: 智能平板产品线_周边产品 | D19: (空白) | E19: (空白)
A20: 001.501.0000018 | B20: S55EA-LGE108B-E | C20: 智能平板产品线_交互智能平板 | D20: S1 | E20: 55
A21: 001.501.0000101 | B21: S55EB-CLA238A-E | C21: 智能平板产品线_交互智能平板 | D21: S2 | E21: 55
A22: 001.501.0000105 | B22: S55EB-CLE138A-E | C22: 智能平板产品线_交互智能平板 | D22: S2 | E22: 55
A23: 001.501.0000106 | B23: S55EB-CLE138A-E | C23: 智能平板产品线_交互智能平板 | D23: S2 | E23: 55
A24: 001.501.0000125 | B24: S55EB-CLA238H-E | C24: 智能平板产品线_交互智能平板 | D24: S2 | E24: 55
A25: 001.501.0000177 | B25: S65EA-AU2208B-E | C25: 智能平板产品线_交互智能平板 | D25: S1 | E25: 65
A26: 001.501.0000267 | B26: S65EA-LGM208B-E | C26: 智能平板产品线_交互智能平板 | D26: S1 | E26: 65
A27: 001.501.0000307 | B27: S65EA-SA0108B-E | C27: 智能平板产品线_交互智能平板 | D27: S1 | E27: 65
A28: 001.501.0000315 | B28: S65EB-AU2208A-E | C28: 智能平板产品线_交互智能平板 | D28: S2 | E28: 65
A29: 001.501.0000334 | B29: S65EB-CLM138A-E | C29: 智能平板产品线_交互智能平板 | D29: S2 | E29: 65
A30: 001.501.0000349 | B30: S65EB-CS0138B-E | C30: 智能平板产品线_交互智能平板 | D30: S2 | E30: 65
A31: 001.501.0000353 | B31: S65EB-CS0138B-E | C31: 智能平板产品线_交互智能平板 | D31: S2 | E31: 65
... A601: 001.501.0003279 | B601: F86EB-GLA538D-E | C601: 智能平板产品线_交互智能平板 | D601: F2 | E601: 86
B602: MT23DS-E | C602: 智能平板产品线_周边产品 | D602: (空白) | E602: (空白)
A603: 001.501.0003280 | B603: F86EB-CLA538D-E | C603: 智能平板产品线_交互智能平板 | D603: F2 | E603: 86
A604: 001.501.0003281 | B604: F86EB-CLA538D-E | C604: 智能平板产品线_交互智能平板 | D604: F2 | E604: 86
A605: 001.501.0003286 | B605: F65EB-CA4038G-E | C605: 智能平板产品线_交互智能平板 | D605: F2 | E605: 65
A606: 001.501.0003287 | B606: F65EB-GA4038A-E | C606: 智能平板产品线_交互智能平板 | D606: F2 | E606: 65
A607: 001.501.0003288 | B607: F65EB-GA4038G-E | C607: 智能平板产品线_交互智能平板 | D607: F2 | E607: 65
A608: 001.501.0003290 | B608: F70EB-GF9Z38A-E | C608: 智能平板产品线_交互智能平板 | D608: F2 | E608: 70
A609: 001.501.0003291 | B609: F70EB-GF9Z38G-E | C609: 智能平板产品线_交互智能平板 | D609: F2 | E609: 70
A610: 001.501.0003293 | B610: F65EB-GB9038A-E | C610: 智能平板产品线_交互智能平板 | D610: F2 | E610: 65
A611: 001.501.0003294 | B611: F65EB-TA4038G-E | C611: 智能平板产品线_交互智能平板 | D611: F2 | E611: 65
A612: 001.501.0003295 | B612: S55EB-TC3538H-E | C612: 智能平板产品线_交互智能平板 | D612: S2 | E612: 55
A613: 001.501.0003296 | B613: F65EB-TA4038G-E | C613: 智能平板产品线_交互智能平板 | D613: F2 | E613: 65
A614: 001.501.0003297 | B614: F86EB-GLA338D-E | C614: 智能平板产品线_交互智能平板 | D614: F2 | E614: 86
... A1244: 001.501.0004766 | B1244: F75EC-CS2251D-E | C1244: 智能平板产品线_交互智能平板 | D1244: F3 | E1244: 75
A1245: 001.502.0000043 | B1245: MT08-E | C1245: 智能平板产品线_周边产品 | D1245: (空白) | E1245: (空白)
A1246: 001.502.0000051 | B1246: MT08-E | C1246: 智能平板产品线_周边产品 | D1246: (空白) | E1246: (空白)
A1247: 001.502.0000122 | B1247: MT11-E | C1247: 智能平板产品线_周边产品 | D1247: (空白) | E1247: (空白)
A1248: 001.502.0000135 | B1248: MT11-E | C1248: 智能平板产品线_周边产品 | D1248: (空白) | E1248: (空白)
A1249: 001.502.0000159 | B1249: MT11-E | C1249: 智能平板产品线_周边产品 | D1249: (空白) | E1249: (空白)
A1250: 001.502.0000196 | B1250: MT11-E | C1250: 智能平板产品线_周边产品 | D1250: (空白) | E1250: (空白)
A1251: 001.502.0000216 | B1251: MT11-E | C1251: 智能平板产品线_周边产品 | D1251: (空白) | E1251: (空白)
A1252: 001.502.0000233 | B1252: MT11-E | C1252: 智能平板产品线_周边产品 | D1252: (空白) | E1252: (空白)
A1253: 001.502.0000237 | B1253: MT11-E | C1253: 智能平板产品线_周边产品 | D1253: (空白) | E1253: (空白)
A1254: 001.502.0000239 | B1254: MT11-E | C1254: 智能平板产品线_周边产品 | D1254: (空白) | E1254: (空白)
A1255: 001.502.0000252 | B1255: MT11-E | C1255: 智能平板产品线_周边产品 | D1255: (空白) | E1255: (空白)
A1256: 001.502.0000257 | B1256: MT11-E | C1256: 智能平板产品线_周边产品 | D1256: (空白) | E1256: (空白)
... A1565: 001.502.0002218 | B1565: MT23JW-E | C1565: 智能平板产品线_周边产品 | D1565: (空白) | E1565: (空白)
A1566: 001.502.0002219 | B1566: F86EB-GLA538D-E | C1566: 智能平板产品线_交互智能平板 | D1566: F2 | E1566: 86
B1567: MT23DS-E | C1567: 智能平板产品线_周边产品 | D1567: (空白) | E1567: (空白)
A1568: 001.502.0002220 | B1568: MT23DS-E | C1568: 智能平板产品线_周边产品 | D1568: (空白) | E1568: (空白)
A1569: 001.502.0002236 | B1569: MT21DS-E | C1569: 智能平板产品线_周边产品 | D1569: (空白) | E1569: (空白)
A1570: 001.502.0002239 | B1570: MT21DS-E | C1570: 智能平板产品线_周边产品 | D1570: (空白) | E1570: (空白)
A1571: 001.502.0002240 | B1571: MT23DS-E | C1571: 智能平板产品线_周边产品 | D1571: (空白) | E1571: (空白)
A1572: 001.502.0002242 | B1572: MT23JW-E | C1572: 智能平板产品线_周边产品 | D1572: (空白) | E1572: (空白)
A1573: 001.502.0002243 | B1573: MT23JW-E | C1573: 智能平板产品线_周边产品 | D1573: (空白) | E1573: (空白)
A1574: 001.502.0002245 | B1574: MT21DS-E | C1574: 智能平板产品线_周边产品 | D1574: (空白) | E1574: (空白)
A1575: 001.502.0002247 | B1575: MT23DS-E | C1575: 智能平板产品线_周边产品 | D1575: (空白) | E1575: (空白)
A1576: 001.502.0002248 | B1576: MT24JW-E | C1576: 幼教产品线_周边产品 | D1576: (空白) | E1576: (空白)
A1577: 001.502.0002249 | B1577: MT41B-DHA-E | C1577: 智能平板产品线_周边产品 | D1577: (空白) | E1577: (空白)
A1578: 001.502.0002250 | B1578: MT23DS-E | C1578: 智能平板产品线_周边产品 | D1578: (空白) | E1578: (空白)
A1579: 001.502.0002252 | B1579: MT23DS-E | C1579: 智能平板产品线_周边产品 | D1579: (空白) | E1579: (空白)
... A2307: 001.511.0000019 | B2307: SV09-E | C2307: 录播产品线 | D2307: (空白) | E2307: (空白)
A2308: 001.511.0000025 | B2308: SV10-E | C2308: 录播产品线 | D2308: (空白) | E2308: 15.6
A2309: 001.511.0000026 | B2309: SV10-E | C2309: 录播产品线 | D2309: (空白) | E2309: 15.6
A2310: 001.511.0000027 | B2310: SV10-E | C2310: 录播产品线 | D2310: (空白) | E2310: 15.6
A2311: 001.511.0000028 | B2311: SV10-E | C2311: 录播产品线 | D2311: (空白) | E2311: 15.6
A2312: 001.511.0000029 | B2312: SV10-E | C2312: 录播产品线 | D2312: (空白) | E2312: 15.6
A2313: 001.511.0000030 | B2313: SV10-E | C2313: 录播产品线 | D2313: (空白) | E2313: 15.6
A2314: 001.511.0000031 | B2314: SV10-E | C2314: 录播产品线 | D2314: (空白) | E2314: 15.6
A2315: 001.511.0000039 | B2315: SV10A-E | C2315: 录播产品线 | D2315: (空白) | E2315: (空白)
A2316: 001.511.0000040 | B2316: SV10A-E | C2316: 录播产品线 | D2316: (空白) | E2316: (空白)
A2317: 001.511.0000043 | B2317: SV10-E | C2317: 录播产品线 | D2317: (空白) | E2317: 15.6
A2318: 001.511.0000046 | B2318: SV10-E | C2318: 录播产品线 | D2318: (空白) | E2318: (空白)
A2319: 001.511.0000047 | B2319: SV10A-E | C2319: 录播产品线 | D2319: (空白) | E2319: (空白)
A2320: 001.511.0000048 | B2320: SV10A-E | C2320: 录播产品线 | D2320: (空白) | E2320: (空白)
A2321: 001.511.0000049 | B2321: SV10D-E | C2321: 录播产品线 | D2321: (空白) | E2321: (空白)
A2322: 001.511.0000052 | B2322: SV10A-E | C2322: 录播产品线 | D2322: (空白) | E2322: (空白)
A2323: 001.511.0000054 | B2323: SV10A-E | C2323: 录播产品线 | D2323: (空白) | E2323: (空白)
A2324: 001.511.0000055 | B2324: SV10D-E | C2324: 录播产品线 | D2324: (空白) | E2324: (空白)
A2325: 001.511.0000057 | B2325: SV10A-E | C2325: 录播产品线 | D2325: (空白) | E2325: (空白)
A2326: 001.512.0000002 | B2326: SW20-E | C2326: 音视频周边产品线 | D2326: (空白) | E2326: (空白)
A2327: 001.512.0000015 | B2327: SW21-E | C2327: 音视频周边产品线 | D2327: (空白) | E2327: (空白)
A2328: 001.512.0000023 | B2328: SW20-E | C2328: 音视频周边产品线 | D2328: (空白) | E2328: (空白)
A2329: 001.512.0000024 | B2329: SW21-E | C2329: 音视频周边产品线 | D2329: (空白) | E2329: (空白)
... A2343: 001.513.0000026 | B2343: SP09-E | C2343: 音视频周边产品线 | D2343: (空白) | E2343: (空白)
B2344: (空白) | C2344: 音视频周边产品线 | D2344: (空白) | E2344: (空白)
A2345: 001.513.0000029 | B2345: SP09-E | C2345: 音视频周边产品线 | D2345: (空白) | E2345: (空白)
A2346: 001.513.0000030 | B2346: SP05-E | C2346: 音视频周边产品线 | D2346: (空白) | E2346: (空白)
A2347: 001.513.0000036 | B2347: SP50-E | C2347: 音视频周边产品线 | D2347: (空白) | E2347: (空白)
A2348: 001.513.0000038 | B2348: SP20B-E | C2348: 音视频周边产品线 | D2348: (空白) | E2348: (空白)
A2349: 001.515.0000002 | B2349: SD11-E | C2349: 学生终端产品线 | D2349: (空白) | E2349: (空白)
...

Sheet 可发货子库（教育）
A1: 子库编码 | B1: 是否发货仓 | C1: 子库描述
A2: GZWL-247 | B2: Y | C2: 日日顺西北仓（广州物流）
A3: GZWL-245 | B3: Y | C3: 日日顺华北仓（广州物流）
A4: CY-248 | B4: Y | C4: 研发待发货成品仓保税（璨宇）
A5: HEG-31 | B5: Y | C5: 特殊物料管控仓(HEG海格)
A6: HEG-28 | B6: Y | C6: 客户借料仓(HEG海格)
A7: HEG-33 | B7: N | C7: 待报废仓（HEG海格）
A8: HEG-24 | B8: N | C8: 发出商品仓（HEG海格）
A9: HEG-23 | B9: N | C9: 待报废仓(HEG海格)
A10: HEG-22 | B10: N | C10: 返修机待修仓（HEG海格）
A11: HEG-16 | B11: N | C11: 拆机件仓(HEG海格)
A12: HEG-15 | B12: N | C12: 自制不良物料仓（HEG海格）
... A666: GZYJ-03 | B666: Y | C666: 样机部成品仓（广州总部）

Sheet 库存表（教育）
A1: 事业部 | B1: 库存合计金额（万元） | C1: 成品 | M1: 近3月使用事业部 | N1: 系列 | O1: 结存数量 | P1: 结存金额（万元） | Q1: 2个月以内（数量） | R1: 2-6个月（数量） | S1: 6-12月（数量） | T1: 1年以上（数量） | W1: CVTE产品型号 | X1: 产品系列
C2: 可发货仓 | G2: 不良仓 | H2: 样机仓 | I2: 软件 | J2: 客服仓 | M2: 多媒体事业部 | N2: B1 | O2: 1 | P2: 1.1473154 | Q2: 0 | R2: 1 | S2: 0 | T2: 0 | W2: B70EA-GPHC38A-E | X2: B1
C3: 2个月以内（万元） | D3: 2-6个月（万元） | E3: 6-12个月（万元） | F3: 1年以上（万元） | N3: B1.5 | O3: 87 | P3: 100.2874 | Q3: 0 | R3: 73 | S3: 14 | T3: 0 | W3: B70EA-GPHC38B-E | X3: B1.5
A4: 多媒体事业部 | B4: =C4+D4+E4+F4+I4+G4+H4+J4 -> 13459.928 | C4: 6420.03 | D4: 1361.0517 | E4: 640.0975 | F4: 23.273357 | G4: 1445.3612 | H4: 2629.7395 | I4: 744.81389 | J4: 195.56126 | N4: B2 | O4: 647 | P4: 721.10488 | Q4: 501 | R4: 68 | S4: 78 | T4: 0 | W4: B75EA-GLA238A-E | X4: B1
A5: 工控PC事业部 | B5: =C5+D5+E5+F5+I5+G5+H5+J5 -> 1712.2927 | C5: 1244.2535 | D5: 220.13292 | E5: 0.38433379 | F5: 0 | G5: 117.70983 | H5: 89.826395 | I5: 32.071418 | J5: 7.9143241 | N5: B3 | O5: 13 | P5: 18.246591 | Q5: 0 | R5: 13 | S5: 0 | T5: 0 | W5: B75EA-GLA238B-E | X5: B1.5
A6: 教培事业部 | B6: =C6+D6+E6+F6+I6+G6+H6+J6 -> 448.27462 | C6: 213.31217 | D6: 149.77895 | E6: 32.091685 | F6: 0 | G6: 26.923866 | H6: 25.305383 | J6: 0.86256796 | N6: B5 | O6: 18 | P6: 20.092833 | Q6: 18 | R6: 0 | S6: 0 | T6: 0 | W6: B75EB-CS2251B-E | X6: B2
A7: 录播事业部 | B7: =C7+D7+E7+F7+I7+G7+H7+J7 -> 657.00436 | C7: 57.700213 | D7: 80.285075 | E7: 29.906243 | F7: 0 | G7: 30.659998 | H7: 451.59391 | I7: 0 | J7: 6.8589168 | N7: F2 | O7: 1294 | P7: 511.01675 | Q7: 1176 | R7: 51 | S7: 47 | T7: 20 | W7: B75EB-LGM351A-E | X7: B2
A8: 屏显事业部 | B8: =C8+D8+E8+F8+I8+G8+H8+J8 -> 1196.4929 | C8: 133.60486 | D8: 351.05092 | E8: 23.718813 | F8: 0 | G8: 179.75004 | H8: 502.55307 | J8: 5.815238 | N8: F3 | O8: 5690 | P8: 2890.3632 | Q8: 5075 | R8: 412 | S8: 203 | T8: 0 | W8: B75EB-LGM351B-E | X8: B2
A9: 学务事业部 | B9: =C9+D9+E9+F9+I9+G9+H9+J9 -> 2225.782 | C9: 395.57115 | D9: 220.88921 | E9: 16.438764 | F9: 56.557678 | G9: 0.50061194 | H9: 1349.2904 | I9: 161.52461 | J9: 25.00958 | N9: F5 | O9: 109 | P9: 63.536133 | Q9: 30 | R9: 79 | S9: 0 | T9: 0 | W9: B75EB-LGM351H-E | X9: B2
A10: 幼教事业部 | B10: =C10+D10+E10+F10+I10+G10+H10+J10 -> 646.74842 | C10: 279.28945 | D10: 26.822766 | E10: 96.004251 | F10: 19.95598 | G10: 44.486613 | H10: 87.994706 | I10: 84.849054 | J10: 7.3455942 | N10: H+ | O10: 6 | P10: 7.7142911 | Q10: 0 | R10: 0 | S10: 6 | T10: 0 | W10: B80EA-GPA038A-E | X10: B1
A11: 教务事业部 | B11: =C11+D11+E11+F11+I11+G11+H11+J11 -> 124.5283 | I11: 124.5283 | N11: MT21 | O11: 356 | P11: 80.269841 | Q11: 82 | R11: 235 | S11: 12 | T11: 27 | W11: B80EA-GPA038C-E | X11: B1
A12: 总计 | B12: =C12+D12+E12+F12+I12+G12+H12+J12 -> 20471.052 | C12: =SUM(C4:C10) -> 8743.7613 | D12: =SUM(D4:D10) -> 2410.0116 | E12: =SUM(E4:E10) -> 838.64159 | F12: =SUM(F4:F10) -> 99.787014 | G12: =SUM(G4:G10) -> 1845.3922 | H12: =SUM(H4:H10) -> 5136.3033 | I12: =SUM(I4:I11) -> 1147.7873 | J12: =SUM(J4:J10) -> 249.36748 | N12: MT23 | O12: 3664 | P12: 622.04439 | Q12: 3164 | R12: 440 | S12: 60 | T12: 0 | W12: B80EA-GPA038D-E | X12: B1.5
N13: MT41 | O13: 10145 | P13: 2045.7288 | Q13: 8968 | R13: 920 | S13: 255 | T13: 2 | W13: B86EA-GLA338A-E | X13: B1
N14: S2 | O14: 56 | P14: 17.54712 | Q14: 6 | R14: 49 | S14: 1 | T14: 0 | W14: B86EA-GLA338B-E | X14: B1.5
N15: U1 | O15: 24 | P15: 6.8520267 | Q15: 24 | R15: 0 | S15: 0 | T15: 0 | W15: B86EB-CS1251B-E | X15: B2
N16: X | O16: 1 | P16: 1.0507467 | Q16: 0 | R16: 1 | S16: 0 | T16: 0 | W16: B86EB-LGA351A-E | X16: B2
N17: 电子白板 | O17: 721 | P17: 104.77078 | Q17: 721 | R17: 0 | S17: 0 | T17: 0 | W17: B86EB-LGA351B-E | X17: B2
N18: 记忆黑板 | O18: 255 | P18: 24.332697 | Q18: 96 | R18: 75 | S18: 84 | T18: 0 | W18: B86EB-LGA551A-E | X18: B2
N19: 其他 | O19: 17 | P19: 1.0697327 | Q19: 0 | R19: 16 | S19: 0 | T19: 1 | W19: B86EB-LGA551B-E | X19: B2
N20: 视频展台 | O20: 7624 | P20: 180.51515 | Q20: 7129 | R20: 495 | S20: 0 | T20: 0 | W20: B86EB-LGA551G-E | X20: B2
N21: 投影机 | O21: 1485 | P21: 811.49523 | Q21: 101 | R21: 820 | S21: 564 | T21: 0 | W21: B86EB-LGA551H-E | X21: B2
N22: 音视频周边 | O22: 13712 | P22: 171.85377 | Q22: 7187 | R22: 5755 | S22: 770 | T22: 0 | W22: B86EB-LGA551S-E | X22: B2
N23: 智能平板产品线周边 | O23: 955 | P23: 43.412802 | Q23: 578 | R23: 320 | S23: 57 | T23: 0 | W23: B86EC-LGA551B-E | X23: B3
M24: 多媒体事业部 汇总 | O24: 46880 | P24: 8444.4525 | Q24: 34856 | R24: 9823 | S24: 2151 | T24: 50 | W24: B86ED-LGA551A-E | X24: B3.5
M25: 工控PC事业部 | N25: MT23 | O25: 191 | P25: 29.732639 | Q25: 73 | R25: 118 | S25: 0 | T25: 0 | W25: B86ED-LGA551B-E | X25: B3.5
N26: MT41 | O26: 4946 | P26: 950.84328 | Q26: 3866 | R26: 1078 | S26: 2 | T26: 0 | W26: B86EV-LGN172A-E | X26: B5
N27: MT51 | O27: 2098 | P27: 479.85727 | Q27: 2094 | R27: 4 | S27: 0 | T27: 0 | W27: C55EF-CS8358A-E | X27: C1
N28: OPS42A | O28: 21 | P28: 4.3375594 | Q28: 21 | R28: 0 | S28: 0 | T28: 0 | W28: C65EF-AU7058A-E | X28: C1
M29: 工控PC事业部 汇总 | O29: 7256 | P29: 1464.7707 | Q29: 6054 | R29: 1200 | S29: 2 | T29: 0 | W29: C65EF-AU7558A-E | X29: C1
M30: 教培事业部 | N30: C1 | O30: 1142 | P30: 395.1828 | Q30: 783 | R30: 305 | S30: 54 | T30: 0 | W30: C75EF-AU3158A-E | X30: C1
M31: 教培事业部 汇总 | O31: 1142 | P31: 395.1828 | Q31: 783 | R31: 305 | S31: 54 | T31: 0 | W31: C75EF-BO9D58A-E | X31: C1
M32: 录播事业部 | N32: SV | O32: 1583 | P32: 160.45128 | Q32: 541 | R32: 688 | S32: 354 | T32: 0 | W32: C85EF-AU2358A-E | X32: C1
N33: 拾音套件 | O33: 175 | P33: 7.4402549 | Q33: 0 | R33: 63 | S33: 112 | T33: 0 | W33: C865A-GA6310A-E | X33: X
M34: 录播事业部 汇总 | O34: 1758 | P34: 167.89153 | Q34: 541 | R34: 751 | S34: 466 | T34: 0 | W34: C86EF-CS1158A-E | X34: C1
M35: 屏显事业部 | N35: LED | O35: 6 | P35: 95.875783 | Q35: 1 | R35: 4 | S35: 1 | T35: 0 | W35: C86EF-LGA558A-E | X35: C1
N36: 班牌 | O36: 1310 | P36: 166.65579 | Q36: 878 | R36: 303 | S36: 129 | T36: 0 | W36: D43EA-CLM120A-E | X36: D
N37: 物联 | O37: 117 | P37: 4.8335363 | Q37: 0 | R37: 100 | S37: 17 | T37: 0 | W37: D43EA-LGM120B-E | X37: D
N38: 信发 | O38: 1429 | P38: 241.00949 | Q38: 26 | R38: 1403 | S38: 0 | T38: 0 | W38: D43EA-LGM320A-E | X38: D
M39: 屏显事业部 汇总 | O39: 2862 | P39: 508.3746 | Q39: 905 | R39: 1810 | S39: 147 | T39: 0 | W39: D43EA-LGM320B-E | X39: D
M40: 学务事业部 | N40: 反馈器 | O40: 20121 | P40: 79.682506 | Q40: 18 | R40: 35 | S40: 102 | T40: 19966 | W40: E86EV-LGA572A-E | X40: F5
N41: 服务器 | O41: 121 | P41: 42.710136 | Q41: 121 | R41: 0 | S41: 0 | T41: 0 | W41: F55EC-CS8351B-E | X41: F3
N42: 网络设备 | O42: 44 | P42: 9.862069 | Q42: 44 | R42: 0 | S42: 0 | T42: 0 | W42: F65EA-GLM138A-E | X42: F1
N43: 学生终端 | O43: 5316 | P43: 543.68886 | Q43: 3324 | R43: 1963 | S43: 29 | T43: 0 | W43: F65EB-CA4038A-E | X43: F2
N44: 学生终端周边 | O44: 984 | P44: 13.513226 | Q44: 0 | R44: 984 | S44: 0 | T44: 0 | W44: F65EB-CA4038G-E | X44: F2
M45: 学务事业部 汇总 | O45: 26586 | P45: 689.4568 | Q45: 3507 | R45: 2982 | S45: 131 | T45: 19966 | W45: F65EB-GA4038A-E | X45: F2
M46: 幼教事业部 | N46: MT24 | O46: 46 | P46: 8.2115398 | Q46: 6 | R46: 6 | S46: 34 | T46: 0 | W46: F65EB-GA4038G-E | X46: F2
N47: MTA2A | O47: 398 | P47: 25.488765 | Q47: 383 | R47: 15 | S47: 0 | T47: 0 | W47: F65EB-GB9038A-E | X47: F2
N48: Y | O48: 4 | P48: 1.408481 | Q48: 0 | R48: 4 | S48: 0 | T48: 0 | W48: F65EB-GLM138A-E | X48: F2
N49: Y1 | O49: 389 | P49: 113.16675 | Q49: 19 | R49: 5 | S49: 298 | T49: 67 | W49: F65EB-TA4038A-E | X49: F2
N50: Y1+ | O50: 1080 | P50: 270.10837 | Q50: 968 | R50: 96 | S50: 16 | T50: 0 | W50: F65EB-TA4038G-E | X50: F2
N51: 智能平板产品线周边 | O51: 157 | P51: 3.6885468 | Q51: 145 | R51: 11 | S51: 1 | T51: 0 | W51: F65EC-AU6351B-E | X51: F3
M52: 幼教事业部 汇总 | O52: 2074 | P52: 422.07245 | Q52: 1521 | R52: 137 | S52: 349 | T52: 67 | W52: F65EC-BO9051B-E | X52: F3
M53: 总计 | O53: 88558 | P53: 12092.201 | Q53: 48167 | R53: 17008 | S53: 3300 | T53: 20083 | W53: F65EC-BO9A51A-E | X53: F3
W54: F65EC-BO9A51B-E | X54: F3
W55: F65EC-BO9A51H-E | X55: F3
W56: F65EC-CS2151B-E | X56: F3
W57: F65EV-BO9072A-E | X57: F5
W58: F70EA-GPHC38A-E | X58: F1
W59: F70EB-CF9Z38A-E | X59: F2
W60: F70EB-CF9Z38G-E | X60: F2
W61: F70EB-CPHC38A-E | X61: F2
W62: F70EB-CPHC38G-E | X62: F2
W63: F70EB-GF9Z38A-E | X63: F2
W64: F70EB-GF9Z38G-E | X64: F2
W65: F70EB-GPHC38A-E | X65: F2
... W368: Y65EB-BO9A58A-E | X368: Y1+

Sheet 仓库分类表（会议）-旧，最新见二期业务数据文件夹
A1: 仓库名称 | B1: 仓库分类—会议 | C1: 工厂/物流仓分类
A2: 视臻样机仓（广州样机） | B2: 样机仓
A3: 退机仓（广州总部） | B3: 样机仓
A4: 济南办事处（广州样机） | B4: 样机仓
A5: 展会投标机成品仓（广州总部） | B5: 样机仓
A6: 西安办事处（广州样机） | B6: 样机仓
A7: 客服国内仓库（广州客服） | B7: 客服仓
A8: 呼和浩特办事处（广州样机） | B8: 样机仓
A9: 客服在途仓（广州客服） | B9: 客服仓
A10: 待报废仓（广州总部） | B10: 不良仓
A11: 内销机仓（高创） | B11: 不良仓
A12: 待报废仓（高创） | B12: 不良仓
A13: 返修机待修仓（高创） | B13: 不良仓
... A27: 上海办事处（广州样机） | B27: 样机仓
A28: 成品仓（高创） | B28: 良品仓 | C28: 工厂
A29: 成品仓（璨宇） | B29: 良品仓 | C29: 工厂
A30: 贵阳办事处（广州样机） | B30: 样机仓
A31: 发出商品仓（广州样机） | B31: 样机仓
A32: 沈阳办事处（广州样机） | B32: 样机仓
A33: 在途仓（嘉里仓） | B33: 良品仓
A34: 华南仓（嘉里仓） | B34: 良品仓 | C34: 物流仓
A35: 西南仓（新亦源） | B35: 良品仓 | C35: 物流仓
A36: 成都办事处（广州样机） | B36: 样机仓
A37: 超期成品仓（璨宇） | B37: 不良仓
A38: 华中仓（嘉里仓） | B38: 良品仓 | C38: 物流仓
A39: 华东仓(良程仓) | B39: 良品仓 | C39: 物流仓
A40: 华北仓（嘉里仓） | B40: 良品仓 | C40: 物流仓
A41: 海外销售借机仓（广州样机） | B41: 样机仓
A42: 研发成品仓（广州） | B42: 研发仓
A43: 返修机待修仓（璨宇） | B43: 不良仓
A44: 西南仓（嘉里仓） | B44: 良品仓 | C44: 物流仓
A45: 北京办事处（广州样机） | B45: 样机仓
A46: 成品仓（苏州璨宇） | B46: 良品仓 | C46: 工厂
A47: 来料不良物料仓（苏州璨宇） | B47: 不良仓
A48: 成品仓2（高创） | B48: 良品仓 | C48: 工厂
A49: CQS返修成品仓（高创） | B49: 不良仓
A50: 超期成品仓（高创） | B50: 不良仓
A51: 在途仓（璨宇） | B51: 不良仓
A52: 武汉办事处（广州样机） | B52: 样机仓
A53: 在途仓（广州） | B53: 不良仓
A54: 返修机待修仓（视隆） | B54: 不良仓
A55: 在途仓（视隆） | B55: 不良仓
A56: 成品测试仓（苏州璨宇） | B56: 研发仓
A57: 来料不良物料仓（德晟达） | B57: 不良仓
A58: 待整改仓(广州总部) | B58: 样机仓
A59: 成品仓（TCL海外） | B59: 良品仓 | C59: 工厂
A60: 研发成品仓（高创） | B60: 研发仓
A61: 返修机待修仓（苏州璨宇） | B61: 不良仓
A62: 成品仓（视隆） | B62: 良品仓 | C62: 工厂
A63: 品质隔离成品仓（高创） | B63: 不良仓
A64: 研发待发货成品仓（高创） | B64: 研发仓
A65: 成品仓（德晟达） | B65: 良品仓 | C65: 工厂
A66: 成品仓（智微智能） | B66: 良品仓 | C66: 工厂
A67: 在途仓（德晟达） | B67: 不良仓
A68: 成品仓（芯电威） | B68: 良品仓 | C68: 工厂
A69: 研发待发货成品仓（苏州璨宇） | B69: 研发仓
A70: 在途仓（良程仓） | B70: 良品仓
A71: 待发货仓（广州总部） | B71: 良品仓
A72: 样机在途仓（广州样机） | B72: 样机仓
A73: 品质隔离成品仓（TCL海外） | B73: 不良仓
A74: 成品仓(XS-仙视) | B74: 良品仓
A75: 成品仓(QS-青松) | B75: 非会议仓
A76: 样机成品仓(QS-青松) | B76: 样机仓
A77: 在途仓（新亦源） | B77: 良品仓
A78: 在途仓（苏州璨宇） | B78: 不良仓
A79: 视臻在外样机仓（青松/仙视） | B79: 样机仓
A80: 监管仓（商显海外） | B80: 非会议仓
... A83: 发出商品仓(CY-璨宇) | B83: 良品仓
A84: 成品仓(顺达) | B84: 良品仓 | C84: 工厂
A85: 返修机待修仓（TCL海外） | B85: 不良仓
A86: 在途仓（高创） | B86: 不良仓
A87: 在途仓（TCL海外） | B87: 不良仓
A88: 在途仓（青松） | B88: 不良仓
A89: 样机部不良品退机仓（广州总部） | B89: 样机仓
A90: 品质隔离成品仓（芯电威） | B90: 不良仓
A91: 其它事业部（广州样机） | B91: 样机仓
A92: 嘉里仓华北仓（广州物流） | B92: 良品仓 | C92: 物流仓
A93: 良程仓华东仓（广州物流） | B93: 良品仓 | C93: 物流仓
A94: 嘉里仓华中仓（广州物流） | B94: 良品仓 | C94: 物流仓
A95: 嘉里仓华南仓（广州物流） | B95: 良品仓 | C95: 物流仓
A96: 嘉里仓西南仓（广州物流） | B96: 良品仓 | C96: 物流仓
A97: 物料仓（芯电威） | B97: 不良仓
A98: 在途仓(QS-青松) | B98: 不良仓
A99: 广州研发样机仓(广州) | B99: 样机仓
A100: 物料仓（苏州璨宇） | B100: 不良仓
A101: 成品仓4（高创） | B101: 良品仓 | C101: 工厂
A102: 新亦源仓西南仓（广州物流） | B102: 良品仓 | C102: 物流仓
A103: 成品仓（高创新厂） | B103: 良品仓 | C103: 工厂
A104: 返修机待修仓（青松） | B104: 不良仓
A105: 成品仓（青松） | B105: 非会议仓
A106: 来料不良物料仓（TCL海外） | B106: 不良仓
A107: 来料不良物料仓（璨宇） | B107: 不良仓
A108: 样机部物料仓（广州样机） | B108: 样机仓
A109: 待报废仓（广州客服） | B109: 客服仓
A110: MI仓（璨宇） | B110: 不良仓
A111: 成品测试仓（高创新厂） | B111: 研发仓
A112: 研发待发货成品仓（高创新厂） | B112: 研发仓
A113: 新亦源广州物流仓库(广州物流) | B113: 良品仓 | C113: 物流仓
A114: 在途仓（高创新厂） | B114: 不良仓
A115: 成品测试仓（璨宇） | B115: 研发仓
...

Sheet 预算预测(教育)
B1: 日/周/月 | C1: 月 | D1: 月
A2: BU | B2: 实际出货 | C2: 预测 | D2: 预算 | E2: 预测缺口 | F2: 预测完成率 | G2: 预算完成率
A3: 多媒体事业部 | B3: 200 | C3: 300 | D3: 500 | E3: =C3-B3 -> 100 | F3: =B3/C3 -> 0.66666667 | G3: =B3/D3 -> 0.4
A4: 学务事业部 | B4: 10 | C4: 20 | D4: 40 | E4: =C4-B4 -> 10 | F4: =B4/C4 -> 0.5 | G4: =B4/D4 -> 0.25
A5: 屏显事业部 | B5: 10 | C5: 20 | D5: 40 | E5: =C5-B5 -> 10 | F5: =B5/C5 -> 0.5 | G5: =B5/D5 -> 0.25
A6: 教务事业部 | B6: 10 | C6: 20 | D6: 40 | E6: =C6-B6 -> 10 | F6: =B6/C6 -> 0.5 | G6: =B6/D6 -> 0.25
A7: 录播事业部 | B7: 10 | C7: 20 | D7: 40 | E7: =C7-B7 -> 10 | F7: =B7/C7 -> 0.5 | G7: =B7/D7 -> 0.25
A8: 教培事业部 | B8: 10 | C8: 20 | D8: 40 | E8: =C8-B8 -> 10 | F8: =B8/C8 -> 0.5 | G8: =B8/D8 -> 0.25
A9: 幼教事业部 | B9: 10 | C9: 20 | D9: 40 | E9: =C9-B9 -> 10 | F9: =B9/C9 -> 0.5 | G9: =B9/D9 -> 0.25
A10: 合计 | B10: =SUM(B3:B9) -> 260 | C10: =SUM(C3:C9) -> 420 | D10: =SUM(D3:D9) -> 740 | E10: =C10-B10 -> 160 | F10: =B10/C10 -> 0.61904762 | G10: =B10/D10 -> 0.35135135
B12: 日/周/月 | C12: 月 | D12: 月
A13: 区域维度 | B13: 实际出货 | C13: 预算 | D13: 预算 | E13: 预测缺口 | F13: 预测完成率 | G13: 预算完成率
A14: 东北区域 | B14: 200 | C14: 500 | D14: 500 | E14: =C14-B14 -> 300 | F14: =B14/C14 -> 0.4 | G14: =B14/D14 -> 0.4
A15: 华北区域 | B15: 10 | C15: 40 | D15: 40 | E15: =C15-B15 -> 30 | F15: =B15/C15 -> 0.25 | G15: =B15/D15 -> 0.25
A16: 华东区域 | B16: 10 | C16: 40 | D16: 40 | E16: =C16-B16 -> 30 | F16: =B16/C16 -> 0.25 | G16: =B16/D16 -> 0.25
A17: 华南区域 | B17: 10 | C17: 40 | D17: 40 | E17: =C17-B17 -> 30 | F17: =B17/C17 -> 0.25 | G17: =B17/D17 -> 0.25
A18: 华中区域 | B18: 10 | C18: 40 | D18: 40 | E18: =C18-B18 -> 30 | F18: =B18/C18 -> 0.25 | G18: =B18/D18 -> 0.25
A19: 西北区域 | B19: 10 | C19: 40 | D19: 40 | E19: =C19-B19 -> 30 | F19: =B19/C19 -> 0.25 | G19: =B19/D19 -> 0.25
A20: 西南区域 | B20: 10 | C20: 40 | D20: 40 | E20: =C20-B20 -> 30 | F20: =B20/C20 -> 0.25 | G20: =B20/D20 -> 0.25
A21: 合计 | B21: =SUM(B14:B20) -> 260 | C21: =SUM(C14:C20) -> 740 | D21: =SUM(D14:D20) -> 740 | E21: =C21-B21 -> 480 | F21: =B21/C21 -> 0.35135135 | G21: =B21/D21 -> 0.35135135
A24: 目标
A25: 大区 | B25: 办事处 | C25: 1月 | D25: 2月 | E25: 3月 | F25: 4月 | G25: 5月 | H25: 6月 | I25: 7月 | J25: 8月 | K25: 9月 | L25: 10月 | M25: 11月 | N25: 12月 | O25: 合计
A26: 东北 | B26: 哈尔滨办
B27: 沈阳办
B28: 长春办
B29: 汇总
A30: 华北 | B30: 北京办
B31: 呼和浩特办
B32: 石家庄办
B33: 太原办
B34: 汇总
A35: 华东 | B35: 杭州办
B36: 济南办
B37: 南京办
B38: 青岛办
B39: 上海办
B40: 汇总
A41: 华南 | B41: 广州办
B42: 海口办
B43: 南昌办
B44: 南宁办
B45: 厦门办
B46: 汇总
A47: 华中 | B47: 合肥办
B48: 武汉办
B49: 长沙办
B50: 郑州办
B51: 汇总
A52: 西北 | B52: 兰州办
B53: 乌鲁木齐办
B54: 西安办
B55: 银川办
B56: 汇总
A57: 西南 | B57: 成都办
B58: 贵阳办
B59: 昆明办
B60: 重庆办
B61: 汇总
A62: 总计
A65: BU
A66: BU | B66: 1月 | C66: 2月 | D66: 3月 | E66: 4月 | F66: 5月 | G66: 6月 | H66: 7月 | I66: 8月 | J66: 9月 | K66: 10月 | L66: 11月 | M66: 12月 | N66: 合计
A67: 多媒体事业部
A68: 学务事业部
A69: 屏显事业部
A70: 教务事业部
A71: 录播事业部
A72: 教培事业部
A73: 幼教事业部
A74: 合计

Sheet 配置表(会议)
A1: √ | B1: BOM标配 | F1: 更新项目
A2: · | B2: 商务标配
A3: · | B3: 带条件适配
A4: · | B4: 商务选配
A5: × | B5: 不适配 | I5: × | O5: ×
F6: ☆ | G6: ☆ | H6: ☆ | I6: ☆ | J6: ☆ | M6: ☆ | N6: ☆ | O6: ☆ | P6: ☆ | Q6: ☆ | R6: ☆ | S6: ☆ | T6: 无 | U6: ☆ | V6: ☆ | W6: 无
A7: 三代产品 | B7: 研发型号 | C7: 壁挂 | F7: 脚架 | J7: 云台支架 | K7: 毛毡笔 | L7: 双头笔 | M7: 电磁笔 | N7: 翻页笔 | O7: 语音笔 | P7: 笔盒 | Q7: 模块 | U7: 摄像头 | V7: 无线传屏 | Y7: 有线传屏
C8: WIB9060G | D8: WIB9060F | E8: WIB6540A | F8: ST26A | G8: ST23A | H8: ST33 | I8: EST02 | J8: WIB8015 | K8: SW01 | L8: SW13 | M8: SP08 | N8: SP05 | O8: SP06 | P8: PB01 | Q8: MT31 | R8: MT23-E | S8: SA06 | T8: SI02 | U8: SC11 | V8: SM01 | W8: WT01A | X8: WT02A | Y8: SL01
A9: E 电商款 | B9: E55CA | C9: × | D9: × | E9: √ | F9: · | G9: · | H9: · | I9: · | J9: · | K9: √ | L9: × | M9: × | N9: · | O9: × | P9: · | Q9: × | R9: · | S9: × | T9: × | U9: · | V9: · | W9: · | X9: · | Y9: ·
B10: E65CA | C10: × | D10: × | E10: √ | F10: · | G10: · | H10: · | I10: · | J10: · | K10: √ | L10: × | M10: × | N10: · | O10: × | P10: · | Q10: × | R10: · | S10: × | T10: × | U10: · | V10: · | W10: · | X10: · | Y10: ·
A11: S 标准款 | B11: S55CA | C11: √ | D11: × | E11: × | F11: · | G11: · | H11: · | I11: · | J11: · | K11: × | L11: √ | M11: × | N11: · | O11: × | P11: · | Q11: · | R11: × | S11: · | T11: × | U11: × | V11: · | W11: · | X11: · | Y11: ·
B12: S65CA | C12: √ | D12: × | E12: × | F12: · | G12: · | H12: · | I12: · | J12: · | K12: × | L12: √ | M12: × | N12: · | O12: × | P12: · | Q12: · | R12: × | S12: · | T12: × | U12: × | V12: · | W12: · | X12: · | Y12: ·
B13: S75CA | C13: √ | D13: × | E13: × | F13: × | G13: · | H13: · | I13: · | J13: · | K13: × | L13: √ | M13: × | N13: · | O13: × | P13: · | Q13: · | R13: × | S13: · | T13: × | U13: × | V13: · | W13: · | X13: · | Y13: ·
B14: S86CA | C14: √ | D14: × | E14: × | F14: × | G14: · | H14: · | I14: × | J14: · | K14: × | L14: √ | M14: × | N14: · | O14: × | P14: · | Q14: · | R14: × | S14: · | T14: × | U14: × | V14: · | W14: · | X14: · | Y14: ·
B15: S98CA | C15: × | D15: √ | E15: × | F15: × | G15: · | H15: × | I15: × | J15: · | K15: × | L15: √ | M15: × | N15: · | O15: × | P15: · | Q15: · | R15: × | S15: · | T15: × | U15: × | V15: · | W15: · | X15: · | Y15: ·
A16: T 技术款 | B16: P65CA/CB | C16: √ | D16: × | E16: × | F16: · | G16: · | H16: · | I16: · | J16: · | K16: × | L16: √ | M16: · | N16: × | O16: · | P16: · | Q16: · | R16: × | S16: · | T16: · | U16: × | V16: · | W16: · | X16: · | Y16: ·
B17: P75CA/CB | C17: √ | D17: × | E17: × | F17: × | G17: · | H17: · | I17: · | J17: · | K17: × | L17: √ | M17: · | N17: × | O17: · | P17: · | Q17: · | R17: × | S17: · | T17: · | U17: × | V17: · | W17: · | X17: · | Y17: ·
B18: P86CA/CB | C18: √ | D18: × | E18: × | F18: × | G18: · | H18: · | I18: × | J18: · | K18: × | L18: √ | M18: · | N18: × | O18: · | P18: · | Q18: · | R18: × | S18: · | T18: · | U18: × | V18: · | W18: · | X18: · | Y18: ·
A19: U 旗舰款 | B19: U65CA | C19: √ | D19: × | E19: × | F19: · | G19: · | H19: · | I19: × | J19: · | K19: × | L19: × | M19: · | N19: × | O19: · | P19: · | Q19: · | R19: × | S19: · | T19: × | U19: × | V19: · | W19: · | X19: · | Y19: ·
B20: U75CA | C20: √ | D20: × | E20: × | F20: × | G20: · | H20: · | I20: × | J20: · | K20: × | L20: × | M20: · | N20: × | O20: · | P20: · | Q20: · | R20: × | S20: · | T20: × | U20: × | V20: · | W20: · | X20: · | Y20: ·
B21: U86CA | C21: √ | D21: × | E21: × | F21: × | G21: · | H21: · | I21: × | J21: · | K21: × | L21: × | M21: · | N21: × | O21: · | P21: · | Q21: · | R21: × | S21: · | T21: × | U21: × | V21: · | W21: · | X21: · | Y21: ·
A22: 备注 | C22: 降本方案 | D22: 98吋专用 | E22: 电商专用 | F22: 55/65吋 | G22: 75吋以上 | H22: 55/65/75/86吋 | I22: 电动支架，不支持长时间平躺 | K22: 被SW13替代 | L22: 3.4.2版本之后支持，替代SW01存在切换周期 | M22: 电磁低配 | N22: 红外高配 | O22: 电磁高配 | R22: 电商专用 | S22: 高性能安卓模块 | T22: 可插拔Wi-Fi模块 | U22: 电商选配 | V22: 19年6月发起退市 | W22: 替代SM01，顺切导入 | X22: 6月1日 3.4.2之后版本才能支持 | Y22: 5月份发布的3.4.1 版本才能支持
A23: √ | B23: 标配 | S23: 变更
A24: · | B24: 可选配
A25: × | B25: 不适配
A27: 二代产品 | B27: 研发型号 | C27: 壁挂 | F27: 脚架 | J27: 云台支架 | K27: 毛毡笔 | L27: 双头笔 | M27: 电磁笔 | N27: 翻页笔 | O27: 语音笔 | P27: 笔盒 | Q27: 模块 | U27: 摄像头 | V27: 无线传屏 | Y27: 有线传屏
C28: WIB9060F | D28: U型壁挂 | F28: ST26A | G28: ST23A | H28: ST33 | I28: EST02 | J28: WIB8015 | K28: SW01 | L28: SW13 | M28: SP08 | N28: SP05 | O28: SP06 | P28: PB01 | Q28: MT31 | R28: MT23-E | S28: SA06 | T28: SI02 | U28: SC11 | V28: SM01 | W28: WT01A | X28: WT02A | Y28: SL01
A29: S 标准版 | B29: C55MC | C29: √ | D29: × | F29: · | G29: · | H29: · | I29: · | J29: · | K29: √ | L29: × | M29: × | N29: · | O29: × | P29: × | Q29: × | R29: × | S29: × | T29: × | U29: · | V29: · | W29: · | X29: · | Y29: ×
B30: C65MC | C30: √ | D30: × | F30: · | G30: · | H30: · | I30: · | J30: · | K30: √ | L30: × | M30: × | N30: · | O30: × | P30: × | Q30: × | R30: × | S30: × | T30: × | U30: · | V30: · | W30: · | X30: · | Y30: ×
B31: C75MC | C31: √ | D31: × | F31: × | G31: · | H31: · | I31: · | J31: · | K31: √ | L31: × | M31: × | N31: · | O31: × | P31: × | Q31: × | R31: × | S31: × | T31: × | U31: · | V31: · | W31: · | X31: · | Y31: ×
B32: C86MC | C32: √ | D32: × | F32: × | G32: · | H32: · | I32: · | J32: · | K32: √ | L32: × | M32: × | N32: · | O32: × | P32: × | Q32: × | R32: × | S32: × | T32: × | U32: · | V32: · | W32: · | X32: · | Y32: ×
A33: S+ PC配置 | B33: C55MD | C33: √ | D33: × | F33: · | G33: · | H33: · | I33: · | J33: · | K33: √ | L33: × | M33: × | N33: · | O33: × | P33: · | Q33: · | R33: × | S33: × | T33: × | U33: · | V33: · | W33: · | X33: · | Y33: ×
A34: PC配置 | B34: C65MD | C34: √ | D34: × | F34: · | G34: · | H34: · | I34: · | J34: · | K34: √ | L34: × | M34: × | N34: · | O34: × | P34: · | Q34: · | R34: × | S34: × | T34: × | U34: · | V34: · | W34: · | X34: · | Y34: ×
A35: P系列 增强版 | B35: C55MJ | C35: × | D35: √ | F35: · | G35: · | H35: × | I35: × | J35: × | K35: √ | L35: × | M35: · | N35: × | O35: · | P35: · | Q35: · | R35: · | S35: × | T35: × | U35: × | V35: · | W35: · | X35: · | Y35: ×
B36: C65MJ | C36: × | D36: √ | F36: · | G36: · | H36: × | I36: × | J36: × | K36: √ | L36: × | M36: · | N36: × | O36: · | P36: · | Q36: · | R36: · | S36: × | T36: × | U36: × | V36: · | W36: · | X36: · | Y36: ×
B37: C75MJ | C37: × | D37: √ | F37: × | G37: · | H37: × | I37: × | J37: × | K37: √ | L37: × | M37: · | N37: × | O37: · | P37: · | Q37: · | R37: · | S37: × | T37: × | U37: × | V37: · | W37: · | X37: · | Y37: ×
A38: U系列 旗舰版 | B38: I65EB | C38: × | D38: √ | F38: · | G38: · | H38: × | I38: × | J38: × | K38: × | L38: × | M38: · | N38: × | O38: · | P38: · | Q38: · | R38: · | S38: × | T38: × | U38: × | V38: · | W38: · | X38: · | Y38: ×
B39: I75EB | C39: × | D39: √ | F39: × | G39: · | H39: × | I39: × | J39: × | K39: × | L39: × | M39: · | N39: × | O39: · | P39: · | Q39: · | R39: · | S39: × | T39: × | U39: × | V39: · | W39: · | X39: · | Y39: ×
B40: I86EB | C40: × | D40: √ | F40: × | G40: · | H40: × | I40: × | J40: × | K40: × | L40: × | M40: · | N40: × | O40: · | P40: · | Q40: · | R40: · | S40: × | T40: × | U40: × | V40: · | W40: · | X40: · | Y40: ×
V41: 19年6月发起退市 | W41: 替代SM01，顺切导入 | X41: 需要3迁移2版本软件

Sheet 商机表单（教育）
A2: BU | B2: 需求挖掘 | C2: 参数确定 | D2: 已挂网 | E2: 已开标 | F2: 其中：已开标预计出货时间 | I2: 总计
F3: Q1 | G3: Q2 | H3: Q2以后
A4: 多媒体事业部 | I4: =B4+C4+D4+E4 -> 0
A5: 教培事业部 | I5: =B5+C5+D5+E5 -> 0
A6: 教务事业部 | I6: =B6+C6+D6+E6 -> 0
A7: 录播事业部 | I7: =B7+C7+D7+E7 -> 0
A8: 屏显事业部 | I8: =B8+C8+D8+E8 -> 0
A9: 学务事业部 | I9: =B9+C9+D9+E9 -> 0
A10: 幼教事业部 | I10: =B10+C10+D10+E10 -> 0
A11: 合计 | B11: =SUM(B4:B10) -> 0 | C11: =SUM(C4:C10) -> 0 | D11: =SUM(D4:D10) -> 0 | E11: =SUM(E4:E10) -> 0 | F11: =SUM(F4:F10) -> 0 | G11: =SUM(G4:G10) -> 0 | H11: =SUM(H4:H10) -> 0 | I11: =SUM(I4:I10) -> 0
A14: 区域 | B14: 需求挖掘 | C14: 参数确定 | D14: 已挂网 | E14: 已开标 | F14: 其中：已开标预计出货时间 | I14: 总计
F15: Q1 | G15: Q2 | H15: Q2以后
A16: 东北区域 | I16: =SUM(B16:E16) -> 0
A17: 华北区域 | I17: =SUM(B17:E17) -> 0
A18: 华东区域 | I18: =SUM(B18:E18) -> 0
A19: 华南区域 | I19: =SUM(B19:E19) -> 0
A20: 华中区域 | I20: =SUM(B20:E20) -> 0
A21: 西北区域 | I21: =SUM(B21:E21) -> 0
A22: 西南区域 | I22: =SUM(B22:E22) -> 0
A23: 总计 | B23: =SUM(B16:B22) -> 0 | C23: =SUM(C16:C22) -> 0 | D23: =SUM(D16:D22) -> 0 | E23: =SUM(E16:E22) -> 0 | F23: =SUM(F16:F22) -> 0 | G23: =SUM(G16:G22) -> 0 | H23: =SUM(H16:H22) -> 0 | I23: =SUM(I16:I22) -> 0

Sheet 目标（教育）
A1: 区域分事业部业务目标
A2: 大区 | B2: 办事处 | C2: 事业部 | D2: 1月 | E2: 2月 | F2: 3月 | G2: 4月 | H2: 5月 | I2: 6月 | J2: 7月 | K2: 8月 | L2: 9月 | M2: 10月 | N2: 11月 | O2: 12月 | P2: 合计
A3: 东北 | B3: 哈尔滨办 | C3: 多媒体 | D3: 68.141593 | E3: 252.21239 | F3: 250.44248 | G3: 88.053097 | H3: 119.02655 | I3: 146.90265 | J3: 514.15929 | K3: 692.0354 | L3: 551.32743 | M3: 347.34513 | N3: 351.76991 | O3: 335.39823 | P3: =SUM(D3:O3) -> 3716.8142
C4: 教培 | D4: 0 | E4: 19.469027 | F4: 7.9646018 | G4: 12.831858 | H4: 17.256637 | I4: 30.973451 | J4: 66.371681 | K4: 84.070796 | L4: 88.495575 | M4: 62.831858 | N4: 63.716814 | O4: 76.99115 | P4: =SUM(D4:O4) -> 530.97345
C5: 录播 | D5: 5.3097345 | E5: 13.274336 | F5: 10.619469 | G5: 5.7522124 | H5: 7.5221239 | I5: 12.389381 | J5: 61.946903 | K5: 74.336283 | L5: 56.637168 | M5: 29.20354 | N5: 29.20354 | O5: 47.787611 | P5: =SUM(D5:O5) -> 353.9823
C6: 幼教 | D6: 4.4247788 | E6: 6.1946903 | F6: 11.504425 | G6: 14.60177 | H6: 19.026549 | I6: 19.469027 | J6: 66.371681 | K6: 66.371681 | L6: 79.646018 | M6: 23.00885 | N6: 23.00885 | O6: 20.353982 | P6: =SUM(D6:O6) -> 353.9823
C7: 校务 | D7: 0.88495575 | E7: 3.539823 | F7: 4.4247788 | G7: 5.7522124 | H7: 5.7522124 | I7: 10.619469 | J7: 35.39823 | K7: 48.672566 | L7: 44.247788 | M7: 29.20354 | N7: 38.053097 | O7: 38.938053 | P7: =SUM(D7:O7) -> 265.48673
C8: 学务 | D8: 0 | E8: 36.283186 | F8: 7.9646018 | G8: 0.88495575 | H8: 1.7699115 | I8: 6.1946903 | J8: 4.4247788 | K8: 13.274336 | L8: 4.4247788 | M8: 2.6548673 | N8: 2.6548673 | O8: 7.9646018 | P8: =SUM(D8:O8) -> 88.495575
B9: 哈尔滨办 汇总 | D9: 78.761062 | E9: 330.97345 | F9: 292.92035 | G9: 127.87611 | H9: 170.35398 | I9: 226.54867 | J9: 748.67257 | K9: 978.76106 | L9: 824.77876 | M9: 494.24779 | N9: 508.40708 | O9: 527.43363 | P9: =SUM(D9:O9) -> 5309.7345
B10: 沈阳办 | C10: 多媒体 | D10: 60.176991 | E10: 81.415929 | F10: 323.89381 | G10: 246.90265 | H10: 406.19469 | I10: 350.44248 | J10: 535.39823 | K10: 601.76991 | L10: 600.88496 | M10: 487.61062 | N10: 575.22124 | O10: 508.84956 | P10: =SUM(D10:O10) -> 4778.7611
C11: 教培 | D11: 0 | E11: 6.1946903 | F11: 50.442478 | G11: 38.938053 | H11: 42.477876 | I11: 43.362832 | J11: 64.60177 | K11: 69.911504 | L11: 75.221239 | M11: 66.371681 | N11: 86.725664 | O11: 75.221239 | P11: =SUM(D11:O11) -> 619.46903
C12: 幼教 | D12: 0 | E12: 12.389381 | F12: 53.097345 | G12: 30.973451 | H12: 34.513274 | I12: 33.628319 | J12: 46.902655 | K12: 66.371681 | L12: 66.371681 | M12: 52.212389 | N12: 69.911504 | O12: 64.60177 | P12: =SUM(D12:O12) -> 530.97345
C13: 录播 | D13: 0 | E13: 2.6548673 | F13: 41.59292 | G13: 42.477876 | H13: 39.823009 | I13: 32.743363 | J13: 47.787611 | K13: 52.212389 | L13: 52.212389 | M13: 38.938053 | N13: 47.787611 | O13: 44.247788 | P13: =SUM(D13:O13) -> 442.47788
C14: 校务 | D14: 32.743363 | E14: 8.8495575 | F14: 30.973451 | G14: 17.699115 | H14: 23.893805 | I14: 21.238938 | J14: 37.168142 | K14: 43.362832 | L14: 38.053097 | M14: 33.628319 | N14: 37.168142 | O14: 29.20354 | P14: =SUM(D14:O14) -> 353.9823
C15: 学务 | D15: 0 | E15: 0 | F15: 13.274336 | G15: 4.4247788 | H15: 10.619469 | I15: 5.3097345 | J15: 7.079646 | K15: 14.159292 | L15: 9.7345133 | M15: 8.8495575 | N15: 9.7345133 | O15: 5.3097345 | P15: =SUM(D15:O15) -> 88.495575
B16: 沈阳办 汇总 | D16: 92.920354 | E16: 111.50442 | F16: 513.27434 | G16: 381.41593 | H16: 557.52212 | I16: 486.72566 | J16: 738.93805 | K16: 847.78761 | L16: 842.47788 | M16: 687.61062 | N16: 826.54867 | O16: 727.43363 | P16: =SUM(D16:O16) -> 6814.1593
B17: 长春办 | C17: 多媒体 | D17: 93.80531 | E17: 238.93805 | F17: 238.0531 | G17: 261.06195 | H17: 371.68142 | I17: 384.95575 | J17: 425.66372 | K17: 535.39823 | L17: 544.24779 | M17: 349.55752 | N17: 375.22124 | O17: 340.70796 | P17: =SUM(D17:O17) -> 4159.292
C18: 教培 | D18: 0 | E18: 7.079646 | F18: 20.353982 | G18: 48.672566 | H18: 48.672566 | I18: 53.097345 | J18: 75.221239 | K18: 75.221239 | L18: 70.79646 | M18: 73.451327 | N18: 75.221239 | O18: 71.681416 | P18: =SUM(D18:O18) -> 619.46903
C19: 幼教 | D19: 6.1946903 | E19: 9.7345133 | F19: 27.433628 | G19: 30.973451 | H19: 36.283186 | I19: 31.858407 | J19: 42.477876 | K19: 46.902655 | L19: 42.477876 | M19: 53.097345 | N19: 56.637168 | O19: 58.40708 | P19: =SUM(D19:O19) -> 442.47788
C20: 校务 | D20: 13.274336 | E20: 9.7345133 | F20: 17.699115 | G20: 29.20354 | H20: 34.513274 | I20: 40.707965 | J20: 43.362832 | K20: 43.362832 | L20: 41.59292 | M20: 52.212389 | N20: 59.292035 | O20: 57.522124 | P20: =SUM(D20:O20) -> 442.47788
C21: 录播 | D21: 0 | E21: 9.7345133 | F21: 14.159292 | G21: 20.353982 | H21: 24.778761 | I21: 22.123894 | J21: 28.318584 | K21: 29.20354 | L21: 28.318584 | M21: 28.318584 | N21: 30.973451 | O21: 29.20354 | P21: =SUM(D21:O21) -> 265.48673
C22: 学务 | D22: 35.39823 | E22: 0 | F22: 3.539823 | G22: 7.079646 | H22: 4.4247788 | I22: 3.539823 | J22: 6.1946903 | K22: 4.4247788 | L22: 4.4247788 | M22: 4.4247788 | N22: 9.7345133 | O22: 5.3097345 | P22: =SUM(D22:O22) -> 88.495575
B23: 长春办 汇总 | D23: 148.67257 | E23: 275.22124 | F23: 321.23894 | G23: 397.34513 | H23: 520.35398 | I23: 536.28319 | J23: 621.23894 | K23: 734.51327 | L23: 731.85841 | M23: 561.06195 | N23: 607.07965 | O23: 562.83186 | P23: =SUM(D23:O23) -> 6017.6991
A24: 东北 汇总 | D24: 320.35398 | E24: 717.69912 | F24: 1127.4336 | G24: 906.63717 | H24: 1248.2301 | I24: 1249.5575 | J24: 2108.8496 | K24: 2561.0619 | L24: 2399.115 | M24: 1742.9204 | N24: 1942.0354 | O24: 1817.6991 | P24: =SUM(D24:O24) -> 18141.593
A25: 华北 | B25: 北京办 | C25: 多媒体 | D25: 529.20354 | E25: 127.43363 | F25: 473.45133 | G25: 938.0531 | H25: 1166.3717 | I25: 1350.4425 | J25: 1995.5752 | K25: 2907.0796 | L25: 1405.3097 | M25: 623.89381 | N25: 1092.0354 | O25: 1240.708 | P25: =SUM(D25:O25) -> 13849.558
C26: 教培 | D26: 15.044248 | E26: 24.778761 | F26: 106.19469 | G26: 238.93805 | H26: 150.44248 | I26: 369.02655 | J26: 353.9823 | K26: 356.63717 | L26: 358.40708 | M26: 150.44248 | N26: 159.29204 | O26: 238.93805 | P26: =SUM(D26:O26) -> 2522.1239
C27: 录播 | D27: 0 | E27: 1.7699115 | F27: 22.123894 | G27: 17.699115 | H27: 42.477876 | I27: 45.132743 | J27: 44.247788 | K27: 49.557522 | L27: 53.097345 | M27: 8.8495575 | N27: 46.902655 | O27: 22.123894 | P27: =SUM(D27:O27) -> 353.9823
C28: 幼教 | D28: 0 | E28: 0 | F28: 23.893805 | G28: 22.123894 | H28: 30.973451 | I28: 53.097345 | J28: 39.823009 | K28: 44.247788 | L28: 54.867257 | M28: 44.247788 | N28: 18.584071 | O28: 22.123894 | P28: =SUM(D28:O28) -> 353.9823
C29: 校务 | D29: 22.123894 | E29: 53.097345 | F29: 150.44248 | G29: 0 | H29: 0 | I29: 62.831858 | J29: 13.274336 | K29: 40.707965 | L29: 35.39823 | M29: 4.4247788 | N29: 24.778761 | O29: 35.39823 | P29: =SUM(D29:O29) -> 442.47788
C30: 学务 | D30: 13.274336 | E30: 0 | F30: 8.8495575 | G30: 0 | H30: 8.8495575 | I30: 61.946903 | J30: 22.123894 | K30: 26.548673 | L30: 7.9646018 | M30: 0 | N30: 4.4247788 | O30: 23.00885 | P30: =SUM(D30:O30) -> 176.99115
B31: 北京办 汇总 | D31: 579.64602 | E31: 207.07965 | F31: 784.95575 | G31: 1216.8142 | H31: 1399.115 | I31: 1942.4779 | J31: 2469.0265 | K31: 3424.7788 | L31: 1915.0442 | M31: 831.85841 | N31: 1346.0177 | O31: 1582.3009 | P31: =SUM(D31:O31) -> 17699.115
B32: 呼市办 | C32: 多媒体 | D32: 376.99115 | E32: 280.53097 | F32: 749.55752 | G32: 159.29204 | H32: 245.13274 | I32: 254.86726 | J32: 968.14159 | K32: 1100.885 | L32: 1160.177 | M32: 719.46903 | N32: 674.33628 | O32: 602.65487 | P32: =SUM(D32:O32) -> 7292.0354
C33: 校务 | D33: 17.699115 | E33: 0 | F33: 18.584071 | G33: 47.787611 | H33: 39.823009 | I33: 55.752212 | J33: 130.0885 | K33: 137.16814 | L33: 137.16814 | M33: 130.97345 | N33: 94.690265 | O33: 57.522124 | P33: =SUM(D33:O33) -> 867.25664
C34: 教培 | D34: 0 | E34: 0 | F34: 15.044248 | G34: 10.619469 | H34: 10.619469 | I34: 23.893805 | J34: 68.141593 | K34: 83.185841 | L34: 92.035398 | M34: 65.486726 | N34: 46.902655 | O34: 26.548673 | P34: =SUM(D34:O34) -> 442.47788
C35: 录播 | D35: 0 | E35: 0 | F35: 23.893805 | G35: 4.4247788 | H35: 3.539823 | I35: 4.4247788 | J35: 92.920354 | K35: 79.646018 | L35: 61.946903 | M35: 61.946903 | N35: 38.938053 | O35: 26.548673 | P35: =SUM(D35:O35) -> 398.23009
C36: 学务 | D36: 0 | E36: 0 | F36: 35.39823 | G36: 0 | H36: 16.814159 | I36: 17.699115 | J36: 117.69912 | K36: 69.911504 | L36: 56.637168 | M36: 3.539823 | N36: 78.761062 | O36: 1.7699115 | P36: =SUM(D36:O36) -> 398.23009
C37: 幼教 | D37: 0 | E37: 0 | F37: 13.274336 | G37: 19.469027 | H37: 16.814159 | I37: 17.699115 | J37: 53.097345 | K37: 53.097345 | L37: 51.327434 | M37: 50.442478 | N37: 35.39823 | O37: 25.663717 | P37: =SUM(D37:O37) -> 336.28319
B38: 呼市办 汇总 | D38: 394.69027 | E38: 280.53097 | F38: 855.75221 | G38: 241.59292 | H38: 332.74336 | I38: 374.33628 | J38: 1430.0885 | K38: 1523.8938 | L38: 1559.292 | M38: 1031.8584 | N38: 969.02655 | O38: 740.70796 | P38: =SUM(D38:O38) -> 9734.5133
B39: 石家庄办 | C39: 多媒体 | D39: 316.81416 | E39: 353.09735 | F39: 462.83186 | G39: 499.11504 | H39: 538.93805 | I39: 667.25664 | J39: 1423.0088 | K39: 1493.8053 | L39: 1854.8673 | M39: 1341.5929 | N39: 1471.6814 | O39: 1568.1416 | P39: =SUM(D39:O39) -> 11991.15
C40: 教培 | D40: 36.283186 | E40: 63.716814 | F40: 99.115044 | G40: 124.77876 | H40: 134.51327 | I40: 183.18584 | J40: 366.37168 | K40: 366.37168 | L40: 506.19469 | M40: 386.72566 | N40: 378.76106 | O40: 451.32743 | P40: =SUM(D40:O40) -> 3097.3451
C41: 学务 | D41: 18.584071 | E41: 29.20354 | F41: 40.707965 | G41: 50.442478 | H41: 54.867257 | I41: 70.79646 | J41: 147.78761 | K41: 149.55752 | L41: 200.88496 | M41: 155.75221 | N41: 146.90265 | O41: 182.30088 | P41: =SUM(D41:O41) -> 1247.7876
C42: 校务 | D42: 15.044248 | E42: 24.778761 | F42: 37.168142 | G42: 45.132743 | H42: 46.017699 | I42: 69.026549 | J42: 127.43363 | K42: 131.85841 | L42: 180.53097 | M42: 146.90265 | N42: 127.43363 | O42: 146.0177 | P42: =SUM(D42:O42) -> 1097.3451
C43: 幼教 | D43: 13.274336 | E43: 25.663717 | F43: 31.858407 | G43: 43.362832 | H43: 46.017699 | I43: 64.60177 | J43: 141.59292 | K43: 123.89381 | L43: 160.17699 | M43: 128.31858 | N43: 131.85841 | O43: 151.32743 | P43: =SUM(D43:O43) -> 1061.9469
C44: 录播 | D44: 11.504425 | E44: 19.469027 | F44: 23.893805 | G44: 31.858407 | H44: 34.513274 | I44: 46.902655 | J44: 97.345133 | K44: 101.76991 | L44: 120.35398 | M44: 99.115044 | N44: 97.345133 | O44: 112.38938 | P44: =SUM(D44:O44) -> 796.46018
B45: 石家庄办 汇总 | D45: 411.50442 | E45: 515.9292 | F45: 695.57522 | G45: 794.69027 | H45: 854.86726 | I45: 1101.7699 | J45: 2303.5398 | K45: 2367.2566 | L45: 3023.0088 | M45: 2258.4071 | N45: 2353.9823 | O45: 2611.5044 | P45: =SUM(D45:O45) -> 19292.035
B46: 太原办 | C46: 多媒体 | D46: 185.9292 | E46: 365.27434 | F46: 547.9115 | G46: 274.77876 | H46: 457.9646 | I46: 824.33628 | J46: 1007.5221 | K46: 1648.6726 | L46: 1099.115 | M46: 824.33628 | N46: 1099.115 | O46: 824.33628 | P46: =SUM(D46:O46) -> 9159.292
C47: 教培 | D47: 0 | E47: 65.819469 | F47: 98.729204 | G47: 41.137168 | H47: 68.561947 | I47: 123.4115 | J47: 150.83628 | K47: 246.82301 | L47: 164.54867 | M47: 123.4115 | N47: 164.54867 | O47: 123.4115 | P47: =SUM(D47:O47) -> 1371.2389
C48: 幼教 | D48: 0 | E48: 39.504425 | F48: 59.256637 | G48: 24.690265 | H48: 41.150442 | I48: 74.070796 | J48: 90.530973 | K48: 148.14159 | L48: 98.761062 | M48: 74.070796 | N48: 98.761062 | O48: 74.070796 | P48: =SUM(D48:O48) -> 823.00885
C49: 校务 | D49: 0 | E49: 32.941593 | F49: 49.412389 | G49: 20.588496 | H49: 34.314159 | I49: 61.765487 | J49: 75.49115 | K49: 123.53097 | L49: 82.353982 | M49: 61.765487 | N49: 82.353982 | O49: 61.765487 | P49: =SUM(D49:O49) -> 686.28319
C50: 录播 | D50: 0 | E50: 32.941593 | F50: 49.412389 | G50: 20.588496 | H50: 34.314159 | I50: 61.765487 | J50: 75.49115 | K50: 123.53097 | L50: 82.353982 | M50: 61.765487 | N50: 82.353982 | O50: 61.765487 | P50: =SUM(D50:O50) -> 686.28319
C51: 学务 | D51: 0 | E51: 26.315044 | F51: 39.472566 | G51: 16.446903 | H51: 27.411504 | I51: 49.340708 | J51: 60.30531 | K51: 98.681416 | L51: 65.787611 | M51: 49.340708 | N51: 65.787611 | O51: 49.340708 | P51: =SUM(D51:O51) -> 548.23009
B52: 太原办 汇总 | D52: 185.9292 | E52: 562.79646 | F52: 844.19469 | G52: 398.23009 | H52: 663.71681 | I52: 1194.6903 | J52: 1460.177 | K52: 2389.3805 | L52: 1592.9204 | M52: 1194.6903 | N52: 1592.9204 | O52: 1194.6903 | P52: =SUM(D52:O52) -> 13274.336
A53: 华北 汇总 | D53: 1571.7699 | E53: 1566.3363 | F53: 3180.4779 | G53: 2651.3274 | H53: 3250.4425 | I53: 4613.2743 | J53: 7662.8319 | K53: 9705.3097 | L53: 8090.2655 | M53: 5316.8142 | N53: 6261.9469 | O53: 6129.2035 | P53: =SUM(D53:O53) -> 60000
A54: 华东 | B54: 杭州办 | C54: 多媒体 | D54: 598.23009 | E54: 893.80531 | F54: 1283.1858 | G54: 1330.9735 | H54: 1729.2035 | I54: 2114.1593 | J54: 3904.4248 | K54: 5145.1327 | L54: 3667.2566 | M54: 2153.9823 | N54: 2242.4779 | O54: 2193.8053 | P54: =SUM(D54:O54) -> 27256.637
C55: 教培 | D55: 88.495575 | E55: 132.74336 | F55: 194.69027 | G55: 194.69027 | H55: 194.69027 | I55: 194.69027 | J55: 407.07965 | K55: 407.07965 | L55: 407.07965 | M55: 238.93805 | N55: 238.93805 | O55: 221.23894 | P55: =SUM(D55:O55) -> 2920.354
C56: 录播 | D56: 29.20354 | E56: 33.628319 | F56: 41.59292 | G56: 48.672566 | H56: 61.061947 | I56: 65.486726 | J56: 120.35398 | K56: 217.69912 | L56: 101.76991 | M56: 48.672566 | N56: 52.212389 | O56: 64.60177 | P56: =SUM(D56:O56) -> 884.95575
C57: 幼教 | D57: 36.283186 | E57: 40.707965 | F57: 44.247788 | G57: 50.442478 | H57: 62.831858 | I57: 75.221239 | J57: 103.53982 | K57: 201.76991 | L57: 99.115044 | M57: 50.442478 | N57: 53.982301 | O57: 66.371681 | P57: =SUM(D57:O57) -> 884.95575
C58: 校务 | D58: 46.902655 | E58: 45.132743 | F58: 46.017699 | G58: 59.292035 | H58: 77.876106 | I58: 98.230088 | J58: 154.86726 | K58: 190.26549 | L58: 133.62832 | M58: 60.176991 | N58: 69.026549 | O58: 80.530973 | P58: =SUM(D58:O58) -> 1061.9469
C59: 学务 | D59: 27.433628 | E59: 47.787611 | F59: 73.893805 | G59: 90.265487 | H59: 81.415929 | I59: 79.646018 | J59: 170.79646 | K59: 157.07965 | L59: 126.54867 | M59: 60.176991 | N59: 69.026549 | O59: 77.876106 | P59: =SUM(D59:O59) -> 1061.9469
B60: 杭州办 汇总 | D60: 826.54867 | E60: 1193.8053 | F60: 1683.6283 | G60: 1774.3363 | H60: 2207.0796 | I60: 2627.4336 | J60: 4861.0619 | K60: 6319.0265 | L60: 4535.3982 | M60: 2612.3894 | N60: 2725.6637 | O60: 2704.4248 | P60: =SUM(D60:O60) -> 34070.796
B61: 济南办 | C61: 多媒体 | D61: 344.24779 | E61: 350.44248 | F61: 1663.7168 | G61: 1153.0973 | H61: 1356.6372 | I61: 1830.9735 | J61: 3243.3628 | K61: 6508.8496 | L61: 4057.5221 | M61: 1839.823 | N61: 1522.1239 | O61: 1253.0973 | P61: =SUM(D61:O61) -> 25123.894
C62: 教培 | D62: 35.39823 | E62: 39.823009 | F62: 216.81416 | G62: 141.59292 | H62: 159.29204 | I62: 247.78761 | J62: 353.9823 | K62: 530.97345 | L62: 340.70796 | M62: 196.46018 | N62: 207.07965 | O62: 184.95575 | P62: =SUM(D62:O62) -> 2654.8673
C63: 校务 | D63: 29.20354 | E63: 7.079646 | F63: 105.30973 | G63: 48.672566 | H63: 73.451327 | I63: 97.345133 | J63: 183.18584 | K63: 347.78761 | L63: 159.29204 | M63: 134.51327 | N63: 101.76991 | O63: 84.070796 | P63: =SUM(D63:O63) -> 1371.6814
C64: 学务 | D64: 20.353982 | E64: 6.1946903 | F64: 170.79646 | G64: 59.292035 | H64: 59.292035 | I64: 138.0531 | J64: 211.50442 | K64: 276.99115 | L64: 409.73451 | M64: 127.43363 | N64: 90.265487 | O64: 93.80531 | P64: =SUM(D64:O64) -> 1663.7168
C65: 录播 | D65: 17.699115 | E65: 8.8495575 | F65: 60.176991 | G65: 49.557522 | H65: 38.938053 | I65: 62.831858 | J65: 119.46903 | K65: 181.41593 | L65: 123.89381 | M65: 54.867257 | N65: 44.247788 | O65: 34.513274 | P65: =SUM(D65:O65) -> 796.46018
